Workbook
Name BaseFloor: Settings!$B$14
Name K_league: Settings!$B$10
Name Lambda: Settings!$B$11
Name MinGP_base: Settings!$B$5
Name MinGP_curve: Settings!$B$6
Name RatioCap: Settings!$B$13
Name RatioFloor: Settings!$B$12
Name W_older: Settings!$B$8
Name W_recent: Settings!$B$7
Name Yardstick: Settings!$B$9

Sheet Read me
A1: Aging curve walkthrough: three traded forwards
A3: What this is | B3: The production aging curve worked through with real data for three forwards, each valued on the day he was traded. Every number is either copied from the source data (blue) or computed by an Excel formula you can inspect (black). Change a setting on the Settings sheet and everything updates.
A4: Built by | B4: valuation_walkthrough.py v1.0 (2026-09-25). Its hand arithmetic was checked against the production code (aging_curve.py, skater_forward_projection.py) before this file was written, and this file's formula results were checked against it after recalculation.
A5: Players | B5: Ryan O'Reilly (Buffalo to St. Louis, 2018-07-01, valued as of 2018-19); Nazem Kadri (Toronto to Colorado, 2019-07-01, valued as of 2019-20); Max Pacioretty (Montreal to Vegas, 2018-09-10, valued as of 2018-19)
A6: Sheets, per player | B6: 1 Seasons: his WAR by season and the starting level. 2 Profile: his eight comparison measures. 3 Comparables: every eligible comparable, its distance and weight. 4 Aging path: how the weights become a curve and the curve becomes projected WAR.
A7: Shared sheets | B7: Settings: every constant the formulas use. Yardstick: how the shared yardstick is built and how distance becomes weight.
A8: Colours | B8: Blue text: data copied from source files or from the production code. Black: formulas. Green: links to another sheet. Yellow fill: key results and settings. Grey rows: seasons after the valuation date, shown for hindsight only.
A9: WAR | B9: Wins above replacement from Patrick Bacon's public model. A season total unless a column says 'per 82 games' (WAR / games x 82).
A10: Not included | B10: Dollars, cap hits, exit probabilities and discounting. This file covers the aging curve only.

Sheet Settings
A1: Model settings used in every calculation
A2: Blue numbers are copied from the production code (20_CODE/aging_curve.py and skater_forward_projection.py) or computed by it. Every formula elsewhere points at these cells, so changing one here flows through the whole workbook.
A4: Setting | B4: Value | C4: Where it comes from and what it does
A5: Minimum games for a season to count toward the starting level | B5: 10 | C5: skater_forward_projection.py MIN_GP. A season with fewer games is ignored for the starting level.
A6: Minimum games for a season to count in the aging model | B6: 20 | C6: aging_curve.py MIN_GP. Applies to the player's own profile seasons and to every comparable.
A7: Starting level: weight on last season | B7: 0.6 | C7: skater_forward_projection.py W_T1.
A8: Starting level: weight on the season before | B8: 0.4 | C8: skater_forward_projection.py W_T2.
A9: Yardstick (median profile distance) | B9: 2.5264128 | C9: AgingModel.h, recomputed on the Yardstick sheet. One number for every player, both positions, all ages.
A10: Weight given to the league average (in comparable-weight units) | B10: 10 | C10: aging_curve.py SHRINK_K. Every 'players like him' average is blended with the league average for his position and age as if the league average were one more comparable carrying this much weight.
A11: Share of the starting curve level kept from his own production | B11: 0.55 | C11: aging_curve.py LAMBDA. The rest (1 - Lambda) comes from the 'players like him' level.
A12: Lowest multiplier allowed | B12: 0 | C12: skater_forward_projection.py RATIO_FLOOR: a projection can fall to replacement level, not below.
A13: Highest multiplier allowed | B13: 3 | C13: skater_forward_projection.py RATIO_CAP.
A14: Curve level at or below which multipliers are not used | B14: 0.25 | C14: skater_forward_projection.py CURVE_BASE_FLOOR: dividing by a curve level this close to zero is unstable, so the projection holds flat instead.
A16: The eight profile measures (forwards)
A17: Measure | B17: Weight | C17: How it is built / plain meaning | D17: Forward average | E17: Forward standard deviation
A18: Even-strength offence share | B18: 0.2 | C18: his even-strength offence WAR as a share of his total style WAR | D18: 0.19232245 | E18: 0.27941252
A19: Even-strength defence share | B19: 0.2 | C19: his even-strength defence WAR as a share of his total style WAR | D19: -0.0066418964 | E19: 0.24003106
A20: Power-play share | B20: 0.2 | C20: his power-play WAR as a share of his total style WAR | D20: 0.053127196 | E20: 0.11037293
A21: Penalty-kill share | B21: 0.2 | C21: his penalty-kill WAR as a share of his total style WAR | D21: -0.0029444758 | E21: 0.081318614
A22: Shooting share | B22: 0.2 | C22: his shooting WAR as a share of his total style WAR | D22: 0.24786123 | E22: 0.37167162
A23: Ice time per game (min) | B23: 1 | C23: total minutes over the window divided by total games | D23: 15.255212 | E23: 2.8795457
A24: Production level (WAR per 82) | B24: 1 | C24: simple average of the two seasons' WAR per 82 games | D24: 1.3082679 | E24: 1.4464355
A25: Production trend (WAR per 82, per year) | B25: 1 | C25: later season's WAR per 82 minus the earlier season's | D25: -0.053335801 | E25: 1.482775
A26: Total weight | B26: =SUM(B18:B25) -> 4
A27: Weights are the production values: each of the four groups (style, ice time, level, trend) carries 1.0, and the five style shares split theirs, 0.2 each. As fractions of the total (4.0) that is 1/20 per style share and 1/4 for each of the other three. Scaling every weight by the same number would scale every distance AND the yardstick together, leaving every comparable's weight unchanged. The forward average and standard deviation are taken over every forward profile in the comparable pool, all ages together (AgingModel.stats). Penalty WAR is left out of the style shares (it made the shares add to a fixed total, so one of them carried no new information).

Sheet Yardstick
A1: The yardstick: one shared scale for 'near' and 'far'
A2: How production builds it (AgingModel._build_bank): take every profile in the comparable pool, separately for forwards and defencemen. Draw up to 1,200 profiles per position at random (seed 0). These are profiles of ALL ages mixed together, not just players of one age. Measure the distance between every pair of sampled forwards and every pair of sampled defencemen (never a forward against a defenceman). Pool the two lists of distances and take the middle value (the median). That median is the yardstick: one number used for every player at every age.
B4: Forwards | C4: Defence | D4: Pooled
A5: Profiles in the pool | B5: 4950 | C5: 2581
A6: Profiles sampled | B6: 1200 | C6: 1200
A7: Pairs measured | B7: 719400 | C7: 719400 | D7: =B7+C7 -> 1438800
A8: Median distance within the group | B8: 2.4851603 | C8: 2.5650631 | D8: =Yardstick -> 2.5264128
A10: Spread of the pooled distances
A11: Percentile | B11: Distance | C11: In yardsticks
A12: 10th percentile | B12: 1.5398154 | C12: =B12/Yardstick -> 0.60948685
A13: 25th percentile | B13: 1.9703446 | C13: =B13/Yardstick -> 0.77989813
A14: 50th percentile | B14: 2.5264128 | C14: =B14/Yardstick -> 1
A15: 75th percentile | B15: 3.1986312 | C15: =B15/Yardstick -> 1.2660762
A16: 90th percentile | B16: 3.9078213 | C16: =B16/Yardstick -> 1.5467865
A18: From distance to weight
A19: weight = EXP( -(distance^2) / (2 x yardstick^2) ). An exact match gets weight 1. A comparable exactly one yardstick away gets EXP(-0.5) = 0.607, which is where the 0.61 comes from: it is a weight, not a distance. Two yardsticks away gets EXP(-2) = 0.135. The fall-off speeds up with distance (it is the bell-curve shape), so far-away profiles count for almost nothing.
A21: Distance, in yardsticks | B21: Distance | C21: Weight
A22: 0 | B22: =A22*Yardstick -> 0 | C22: =EXP(-(B22^2)/(2*Yardstick^2)) -> 1
A23: 0.25 | B23: =A23*Yardstick -> 0.63160321 | C23: =EXP(-(B23^2)/(2*Yardstick^2)) -> 0.96923323
A24: 0.5 | B24: =A24*Yardstick -> 1.2632064 | C24: =EXP(-(B24^2)/(2*Yardstick^2)) -> 0.8824969
A25: 0.75 | B25: =A25*Yardstick -> 1.8948096 | C25: =EXP(-(B25^2)/(2*Yardstick^2)) -> 0.7548396
A26: 1 | B26: =A26*Yardstick -> 2.5264128 | C26: =EXP(-(B26^2)/(2*Yardstick^2)) -> 0.60653066
A27: 1.25 | B27: =A27*Yardstick -> 3.158016 | C27: =EXP(-(B27^2)/(2*Yardstick^2)) -> 0.45783336
A28: 1.5 | B28: =A28*Yardstick -> 3.7896192 | C28: =EXP(-(B28^2)/(2*Yardstick^2)) -> 0.32465247
A29: 2 | B29: =A29*Yardstick -> 5.0528257 | C29: =EXP(-(B29^2)/(2*Yardstick^2)) -> 0.13533528
A30: 2.5 | B30: =A30*Yardstick -> 6.3160321 | C30: =EXP(-(B30^2)/(2*Yardstick^2)) -> 0.043936934
A31: 3 | B31: =A31*Yardstick -> 7.5792385 | C31: =EXP(-(B31^2)/(2*Yardstick^2)) -> 0.011108997
A33: For comparison only: a yardstick built from one age and position
A34: Production does NOT do this. These are the medians you would get using only forwards of each walkthrough player's comparison age (every pair, no sampling). Listed so the shared yardstick can be compared with an age-specific one.
A36: Player: forwards of age | B36: Profiles | C36: Median distance | D36: In shared yardsticks
A37: Ryan O'Reilly: forwards aged 26 | B37: 472 | C37: 2.5559835 | D37: =C37/Yardstick -> 1.0117046
A38: Nazem Kadri: forwards aged 28 | B38: 400 | C38: 2.5542229 | D38: =C38/Yardstick -> 1.0110077
A39: Max Pacioretty: forwards aged 29 | B39: 354 | C39: 2.5858027 | D39: =C39/Yardstick -> 1.0235076

Sheet OReilly 1 Seasons
A1: Ryan O'Reilly: every season of WAR
A2: Traded Buffalo to St. Louis on 2018-07-01. The model values him as of the 2018-19 season, so it may use seasons up to 2017-18 only. Grey rows are later seasons, shown for hindsight and never used by the model. Source: Patrick Bacon's WAR export (10_SOURCE/WAR.csv); a season split between two teams is added together into one row.
A4: Season | B4: Team | C4: Age | D4: Games | E4: Ice time (min) | F4: Even-strength offence WAR | G4: Even-strength defence WAR | H4: Power-play WAR | I4: Penalty-kill WAR | J4: Penalties WAR | K4: Shooting WAR | L4: Total WAR | M4: Season-length factor | N4: WAR, season-length adjusted | O4: WAR per 82 games | P4: Used by the model for
A5: 2009-10 | B5: COL | C5: 18 | D5: 81 | E5: 1341.1667 | F5: 0.050008396 | G5: -0.30096042 | H5: -0.047970962 | I5: -0.30259977 | J5: 0.31528571 | K5: -0.032233278 | L5: -0.31847032 | M5: 1 | N5: =L5*M5 -> -0.31847032 | O5: =L5/D5*82 -> -0.32240206
A6: 2010-11 | B6: COL | C6: 19 | D6: 74 | E6: 1165.25 | F6: 0.2748809 | G6: 0.028877659 | H6: -0.0099528967 | I6: -0.15914257 | J6: 0.2753381 | K6: 0.82187542 | L6: 1.2318766 | M6: 1 | N6: =L6*M6 -> 1.2318766 | O6: =L6/D6*82 -> 1.3650525
A7: 2011-12 | B7: COL | C7: 20 | D7: 81 | E7: 1538.1667 | F7: 0.63208416 | G7: 0.63810737 | H7: 0.03150421 | I7: 0.06682396 | J7: 0.41556456 | K7: 0.75676926 | L7: 2.5408535 | M7: 1 | N7: =L7*M7 -> 2.5408535 | O7: =L7/D7*82 -> 2.5722221
A8: 2012-13 | B8: COL | C8: 21 | D8: 29 | E8: 521.91667 | F8: 0.17364263 | G8: 0.19599955 | H8: 0.10578858 | I8: 0.0070170751 | J8: 0.21894985 | K8: 0.40497107 | L8: 1.1063688 | M8: 1 | N8: =L8*M8 -> 1.1063688 | O8: =L8/D8*82 -> 3.1283531
A9: 2013-14 | B9: COL | C9: 22 | D9: 80 | E9: 1540.25 | F9: 0.56618149 | G9: -0.24315999 | H9: 0.44107604 | I9: 0.14174333 | J9: 0.65239323 | K9: 2.3437549 | L9: 3.901989 | M9: 1 | N9: =L9*M9 -> 3.901989 | O9: =L9/D9*82 -> 3.9995388
A10: 2014-15 | B10: COL | C10: 23 | D10: 82 | E10: 1542.25 | F10: 0.39657853 | G10: 0.36431636 | H10: 0.35490069 | I10: -0.052496074 | J10: 0.38220266 | K10: 0.3170187 | L10: 1.7625209 | M10: 1 | N10: =L10*M10 -> 1.7625209 | O10: =L10/D10*82 -> 1.7625209
A11: 2015-16 | B11: BUF | C11: 24 | D11: 71 | E11: 1480.1167 | F11: 0.42734664 | G11: -0.27875102 | H11: 0.94390371 | I11: 0.043422697 | J11: 0.4658086 | K11: 1.4515532 | L11: 3.0532838 | M11: 1 | N11: =L11*M11 -> 3.0532838 | O11: =L11/D11*82 -> 3.5263278
A12: 2016-17 | B12: BUF | C12: 25 | D12: 72 | E12: 1488.55 | F12: 0.56602406 | G12: 0.17154919 | H12: 0.73740933 | I12: -0.22762153 | J12: 0.87936305 | K12: 1.1022063 | L12: 3.2289304 | M12: 1 | N12: =L12*M12 -> 3.2289304 | O12: =L12/D12*82 -> 3.6773929 | P12: starting level (if 10+ games); comparison profile at age 25
A13: 2017-18 | B13: BUF | C13: 26 | D13: 81 | E13: 1606.7333 | F13: 0.63118387 | G13: 0.49498323 | H13: 1.0273105 | I13: -0.19707335 | J13: 0.68316725 | K13: 0.67381113 | L13: 3.3133826 | M13: 1 | N13: =L13*M13 -> 3.3133826 | O13: =L13/D13*82 -> 3.3542886 | P13: starting level (if 10+ games); comparison profile at age 26
A14: 2018-19 | B14: STL | C14: 27 | D14: 82 | E14: 1630.3833 | F14: 1.0202456 | G14: 0.55498014 | H14: 0.64736343 | I14: 0.042690755 | J14: 0.69429213 | K14: 0.98492593 | L14: 3.944498 | M14: 1 | N14: =L14*M14 -> 3.944498 | O14: =L14/D14*82 -> 3.944498 | P14: hindsight only
A15: 2019-20 | B15: STL | C15: 28 | D15: 71 | E15: 1403.2667 | F15: 0.82001771 | G15: 0.70883071 | H15: 0.3631603 | I15: -0.14366879 | J15: 0.26801753 | K15: -0.16512079 | L15: 1.8512367 | M15: 1.1714286 | N15: =L15*M15 -> 2.1685915 | O15: =L15/D15*82 -> 2.138048 | P15: hindsight only
A16: 2020-21 | B16: STL | C16: 29 | D16: 56 | E16: 1098.8167 | F16: 0.41705311 | G16: 0.17641002 | H16: 0.23858789 | I16: -0.28970667 | J16: 0.039056428 | K16: 1.9086624 | L16: 2.4900631 | M16: 1.4642857 | N16: =L16*M16 -> 3.6461639 | O16: =L16/D16*82 -> 3.6461639 | P16: hindsight only
A17: 2021-22 | B17: STL | C17: 30 | D17: 78 | E17: 1424.6 | F17: -0.059689024 | G17: 0.67677893 | H17: 0.55605068 | I17: -0.10534502 | J17: 0.76340378 | K17: 0.38676175 | L17: 2.2179611 | M17: 1 | N17: =L17*M17 -> 2.2179611 | O17: =L17/D17*82 -> 2.3317027 | P17: hindsight only
A18: 2022-23 | B18: STL/TOR | C18: 31 | D18: 53 | E18: 924.4 | F18: 0.89572481 | G18: 0.1636061 | H18: -0.075736027 | I18: -0.066168608 | J18: 0.032856946 | K18: 0.74704568 | L18: 1.6973289 | M18: 1 | N18: =L18*M18 -> 1.6973289 | O18: =L18/D18*82 -> 2.626056 | P18: hindsight only
A19: 2023-24 | B19: NSH | C19: 32 | D19: 82 | E19: 1553.7333 | F19: 1.0171166 | G19: 0.30146336 | H19: 0.22524603 | I19: 0.14129415 | J19: 0.19356352 | K19: 1.1033694 | L19: 3.0624426 | M19: 1 | N19: =L19*M19 -> 3.0624426 | O19: =L19/D19*82 -> 3.0624426 | P19: hindsight only
A20: 2024-25 | B20: NSH | C20: 33 | D20: 79 | E20: 1428.35 | F20: 0.56887549 | G20: 0.30937604 | H20: 0.35879725 | I20: -0.026653396 | J20: 0.19702474 | K20: 0.16775271 | L20: 1.5805724 | M20: 1 | N20: =L20*M20 -> 1.5805724 | O20: =L20/D20*82 -> 1.6405942 | P20: hindsight only
A21: 2025-26 | B21: NSH | C21: 34 | D21: 81 | E21: 1586.2 | F21: 0.53158823 | G21: 0.11185785 | H21: 0.48642487 | I21: -0.0057367626 | J21: 0.055873471 | K21: 1.0056776 | L21: 2.2368885 | M21: 1 | N21: =L21*M21 -> 2.2368885 | O21: =L21/D21*82 -> 2.2645044 | P21: hindsight only
A23: Starting level: how good is he now?
A24: 60% of last season's WAR plus 40% of the season before, each counted only if he played at least the minimum games. If only one season counts, it supplies the whole starting level. This is a season total (not a per-82 rate); it is the number the aging curve's multipliers are applied to on the Aging path sheet.
B26: Season | C26: Games | D26: Adjusted WAR | E26: Counts? | F26: Weight
A27: Last season | B27: =A13 -> 2017-18 | C27: =D13 -> 81 | D27: =N13 -> 3.3133826 | E27: =C27>=MinGP_base -> TRUE | F27: =W_recent -> 0.6
A28: Season before | B28: =A12 -> 2016-17 | C28: =D12 -> 72 | D28: =N12 -> 3.2289304 | E28: =C28>=MinGP_base -> TRUE | F28: =W_older -> 0.4
A30: Starting level (WAR) | D30: =IF(AND(E27,E28),F27*D27+F28*D28,IF(E27,D27,IF(E28,D28,NA()))) -> 3.2796017

Sheet OReilly 2 Profile
A1: Ryan O'Reilly: his comparison profile
A2: He is 27 in the valuation season (2018-19). The comparison is made one season earlier, at age 26, so it rests only on completed seasons (2017-18 and before). His profile at age 26 uses his two consecutive seasons at ages 25 and 26, each with at least 20 games. It is then compared with every other forward's profile at age 26.
A4: Profile season | B4: Age | C4: Games | D4: Ice time (min) | E4: EV offence WAR | F4: EV defence WAR | G4: Power-play WAR | H4: Penalty-kill WAR | I4: Shooting WAR | J4: Total WAR | K4: WAR per 82
A5: ='OReilly 1 Seasons'!$A$12 -> 2016-17 | B5: ='OReilly 1 Seasons'!$C$12 -> 25 | C5: ='OReilly 1 Seasons'!$D$12 -> 72 | D5: ='OReilly 1 Seasons'!$E$12 -> 1488.55 | E5: ='OReilly 1 Seasons'!$F$12 -> 0.56602406 | F5: ='OReilly 1 Seasons'!$G$12 -> 0.17154919 | G5: ='OReilly 1 Seasons'!$H$12 -> 0.73740933 | H5: ='OReilly 1 Seasons'!$I$12 -> -0.22762153 | I5: ='OReilly 1 Seasons'!$K$12 -> 1.1022063 | J5: ='OReilly 1 Seasons'!$L$12 -> 3.2289304 | K5: ='OReilly 1 Seasons'!$O$12 -> 3.6773929
A6: ='OReilly 1 Seasons'!$A$13 -> 2017-18 | B6: ='OReilly 1 Seasons'!$C$13 -> 26 | C6: ='OReilly 1 Seasons'!$D$13 -> 81 | D6: ='OReilly 1 Seasons'!$E$13 -> 1606.7333 | E6: ='OReilly 1 Seasons'!$F$13 -> 0.63118387 | F6: ='OReilly 1 Seasons'!$G$13 -> 0.49498323 | G6: ='OReilly 1 Seasons'!$H$13 -> 1.0273105 | H6: ='OReilly 1 Seasons'!$I$13 -> -0.19707335 | I6: ='OReilly 1 Seasons'!$K$13 -> 0.67381113 | J6: ='OReilly 1 Seasons'!$L$13 -> 3.3133826 | K6: ='OReilly 1 Seasons'!$O$13 -> 3.3542886
A8: Style shares: each style WAR summed over the two seasons, divided by the sum of the five style WARs ignoring their signs (Penalties WAR is left out). They describe the MIX of his game, not its size. Standard score = (value - forward average) / forward standard deviation. Weighted score = standard score x square root of the measure weight.
A9: Measure | D9: His value | E9: Forward average | F9: Forward SD | G9: Standard score | H9: Measure weight | I9: Weighted score
A10: Even-strength offence share | D10: =SUM(E5:E6)/(ABS(SUM(E5:E6))+ABS(SUM(F5:F6))+ABS(SUM(G5:G6))+ABS(SUM(H5:H6))+ABS(SUM(I5:I6))) -> 0.20538214 | E10: =Settings!$D$18 -> 0.19232245 | F10: =Settings!$E$18 -> 0.27941252 | G10: =(D10-E10)/F10 -> 0.046739823 | H10: =Settings!$B$18 -> 0.2 | I10: =G10*SQRT(H10) -> 0.020902684
A11: Even-strength defence share | D11: =SUM(F5:F6)/(ABS(SUM(E5:E6))+ABS(SUM(F5:F6))+ABS(SUM(G5:G6))+ABS(SUM(H5:H6))+ABS(SUM(I5:I6))) -> 0.11434426 | E11: =Settings!$D$19 -> -0.0066418964 | F11: =Settings!$E$19 -> 0.24003106 | G11: =(D11-E11)/F11 -> 0.50404375 | H11: =Settings!$B$19 -> 0.2 | I11: =G11*SQRT(H11) -> 0.22541522
A12: Power-play share | D12: =SUM(G5:G6)/(ABS(SUM(E5:E6))+ABS(SUM(F5:F6))+ABS(SUM(G5:G6))+ABS(SUM(H5:H6))+ABS(SUM(I5:I6))) -> 0.30273934 | E12: =Settings!$D$20 -> 0.053127196 | F12: =Settings!$E$20 -> 0.11037293 | G12: =(D12-E12)/F12 -> 2.261534 | H12: =Settings!$B$20 -> 0.2 | I12: =G12*SQRT(H12) -> 1.0113888
A13: Penalty-kill share | D13: =SUM(H5:H6)/(ABS(SUM(E5:E6))+ABS(SUM(F5:F6))+ABS(SUM(G5:G6))+ABS(SUM(H5:H6))+ABS(SUM(I5:I6))) -> -0.072856805 | E13: =Settings!$D$21 -> -0.0029444758 | F13: =Settings!$E$21 -> 0.081318614 | G13: =(D13-E13)/F13 -> -0.85973342 | H13: =Settings!$B$21 -> 0.2 | I13: =G13*SQRT(H13) -> -0.38448447
A14: Shooting share | D14: =SUM(I5:I6)/(ABS(SUM(E5:E6))+ABS(SUM(F5:F6))+ABS(SUM(G5:G6))+ABS(SUM(H5:H6))+ABS(SUM(I5:I6))) -> 0.30467745 | E14: =Settings!$D$22 -> 0.24786123 | F14: =Settings!$E$22 -> 0.37167162 | G14: =(D14-E14)/F14 -> 0.15286671 | H14: =Settings!$B$22 -> 0.2 | I14: =G14*SQRT(H14) -> 0.068364072
A15: Ice time per game (min) | D15: =SUM(D5:D6)/SUM(C5:C6) -> 20.23061 | E15: =Settings!$D$23 -> 15.255212 | F15: =Settings!$E$23 -> 2.8795457 | G15: =(D15-E15)/F15 -> 1.7278414 | H15: =Settings!$B$23 -> 1 | I15: =G15*SQRT(H15) -> 1.7278414
A16: Production level (WAR per 82) | D16: =AVERAGE(K5:K6) -> 3.5158407 | E16: =Settings!$D$24 -> 1.3082679 | F16: =Settings!$E$24 -> 1.4464355 | G16: =(D16-E16)/F16 -> 1.5262158 | H16: =Settings!$B$24 -> 1 | I16: =G16*SQRT(H16) -> 1.5262158
A17: Production trend (WAR per 82, per year) | D17: =(K6-K5)/(B6-B5) -> -0.32310432 | E17: =Settings!$D$25 -> -0.053335801 | F17: =Settings!$E$25 -> 1.482775 | G17: =(D17-E17)/F17 -> -0.1819349 | H17: =Settings!$B$25 -> 1 | I17: =G17*SQRT(H17) -> -0.1819349

Sheet OReilly 3 Comparables
A1: Ryan O'Reilly: every forward profile at age 26, and how close each one is
A2: Every forward with a qualifying two-season profile at age 26 is eligible; there is no fixed number of comparables. Ryan O'Reilly's own career is excluded (1 row). Distance = square root of the sum of the eight distance pieces; each piece = measure weight x (his standard score - comparable's standard score)^2. Weight = EXP(-(distance^2) / (2 x yardstick^2)). Rows are sorted by weight. 'After valuation date' marks profiles or yearly changes from seasons that had not been played by 2018-07-01: production draws its comparables from the full 2007-2025 data, so these later seasons do inform the valuation (a documented look-ahead limitation).
A4: Ryan O'Reilly (the target)
F5: Target standard score: Even-strength offence share | G5: Target standard score: Even-strength defence share | H5: Target standard score: Power-play share | I5: Target standard score: Penalty-kill share | J5: Target standard score: Shooting share | K5: Target standard score: Ice time per game (min) | L5: Target standard score: Production level (WAR per 82) | M5: Target standard score: Production trend (WAR per 82, per year)
F6: ='OReilly 2 Profile'!$G$10 -> 0.046739823 | G6: ='OReilly 2 Profile'!$G$11 -> 0.50404375 | H6: ='OReilly 2 Profile'!$G$12 -> 2.261534 | I6: ='OReilly 2 Profile'!$G$13 -> -0.85973342 | J6: ='OReilly 2 Profile'!$G$14 -> 0.15286671 | K6: ='OReilly 2 Profile'!$G$15 -> 1.7278414 | L6: ='OReilly 2 Profile'!$G$16 -> 1.5262158 | M6: ='OReilly 2 Profile'!$G$17 -> -0.1819349
A7: Sum of comparable weights | E7: =SUM($AF$11:$AF$481) -> 231.62089 | G7: Share of weight on the 5 closest | K7: =SUM($AF$11:$AF$15)/E7 -> 0.020229049
A8: Effective number of comparables | E8: =SUM($AF$11:$AF$481)^2/SUMPRODUCT($AF$11:$AF$481,$AF$11:$AF$481) -> 390.5683 | G8: Share of weight on profiles after valuation date | K8: =SUMPRODUCT($AF$11:$AF$481,$E$11:$E$481)/E7 -> 0.56496803
A10: Rank | B10: Comparable | C10: Profile seasons | D10: Age | E10: After valuation date (1 = yes) | F10: Value: Even-strength offence share | G10: Value: Even-strength defence share | H10: Value: Power-play share | I10: Value: Penalty-kill share | J10: Value: Shooting share | K10: Value: Ice time per game (min) | L10: Value: Production level (WAR per 82) | M10: Value: Production trend (WAR per 82, per year) | N10: Standard score: Even-strength offence share | O10: Standard score: Even-strength defence share | P10: Standard score: Power-play share | Q10: Standard score: Penalty-kill share | R10: Standard score: Shooting share | S10: Standard score: Ice time per game (min) | T10: Standard score: Production level (WAR per 82) | U10: Standard score: Production trend (WAR per 82, per year) | V10: Distance piece: Even-strength offence share | W10: Distance piece: Even-strength defence share | X10: Distance piece: Power-play share | Y10: Distance piece: Penalty-kill share | Z10: Distance piece: Shooting share | AA10: Distance piece: Ice time per game (min) | AB10: Distance piece: Production level (WAR per 82) | AC10: Distance piece: Production trend (WAR per 82, per year) | AD10: Distance | AE10: Distance in yardsticks | AF10: Weight | AG10: Share of total weight | AH10: Change in WAR per 82, age 26 to 27 | AI10: That change after valuation date (1 = yes) | AJ10: Change in WAR per 82, age 27 to 28 | AK10: That change after valuation date (1 = yes) | AL10: Change in WAR per 82, age 28 to 29 | AM10: That change after valuation date (1 = yes) | AN10: Change in WAR per 82, age 29 to 30 | AO10: That change after valuation date (1 = yes) | AP10: Change in WAR per 82, age 30 to 31 | AQ10: That change after valuation date (1 = yes)
A11: 1 | B11: Joe Pavelski | C11: 2009-10 & 2010-11 | D11: 26 | E11: 0 | F11: 0.50772108 | G11: 0.027678589 | H11: 0.29345704 | I11: -0.085191313 | J11: 0.085951979 | K11: 19.148921 | L11: 3.0228633 | M11: 0.050163994 | N11: =(F11-Settings!$D$18)/Settings!$E$18 -> 1.128792 | O11: =(G11-Settings!$D$19)/Settings!$E$19 -> 0.14298352 | P11: =(H11-Settings!$D$20)/Settings!$E$20 -> 2.1774346 | Q11: =(I11-Settings!$D$21)/Settings!$E$21 -> -1.0114146 | R11: =(J11-Settings!$D$22)/Settings!$E$22 -> -0.43562446 | S11: =(K11-Settings!$D$23)/Settings!$E$23 -> 1.3521957 | T11: =(L11-Settings!$D$24)/Settings!$E$24 -> 1.1853936 | U11: =(M11-Settings!$D$25)/Settings!$E$25 -> 0.069801414 | V11: =Settings!$B$18*(N11-F$6)^2 -> 0.2341674 | W11: =Settings!$B$19*(O11-G$6)^2 -> 0.026072899 | X11: =Settings!$B$20*(P11-H$6)^2 -> 0.0014145438 | Y11: =Settings!$B$21*(Q11-I$6)^2 -> 0.004601439 | Z11: =Settings!$B$22*(R11-J$6)^2 -> 0.069264372 | AA11: =Settings!$B$23*(S11-K$6)^2 -> 0.14110974 | AB11: =Settings!$B$24*(T11-L$6)^2 -> 0.1161598 | AC11: =Settings!$B$25*(U11-M$6)^2 -> 0.06337117 | AD11: =SQRT(SUM(V11:AC11)) -> 0.81003788 | AE11: =AD11/Yardstick -> 0.32062768 | AF11: =EXP(-(AD11^2)/(2*Yardstick^2)) -> 0.94989763 | AG11: =AF11/$E$7 -> 0.0041010879 | AH11: 0.33035045 | AI11: 0 | AJ11: 0.25739387 | AK11: 0 | AL11: 1.3086287 | AM11: 0 | AN11: 0.85297009 | AO11: 0 | AP11: -0.99598651 | AQ11: 0
A12: 2 | B12: Loui Eriksson | C12: 2010-11 & 2011-12 | D12: 26 | E12: 0 | F12: 0.10753187 | G12: -0.041372676 | H12: 0.25448458 | I12: 0.040017128 | J12: 0.55659375 | K12: 19.778468 | L12: 3.1195734 | M12: -0.25004317 | N12: =(F12-Settings!$D$18)/Settings!$E$18 -> -0.30346022 | O12: =(G12-Settings!$D$19)/Settings!$E$19 -> -0.14469286 | P12: =(H12-Settings!$D$20)/Settings!$E$20 -> 1.8243366 | Q12: =(I12-Settings!$D$21)/Settings!$E$21 -> 0.52831205 | R12: =(J12-Settings!$D$22)/Settings!$E$22 -> 0.83065937 | S12: =(K12-Settings!$D$23)/Settings!$E$23 -> 1.5708229 | T12: =(L12-Settings!$D$24)/Settings!$E$24 -> 1.2522546 | U12: =(M12-Settings!$D$25)/Settings!$E$25 -> -0.13266164 | V12: =Settings!$B$18*(N12-F$6)^2 -> 0.024528014 | W12: =Settings!$B$19*(O12-G$6)^2 -> 0.084171838 | X12: =Settings!$B$20*(P12-H$6)^2 -> 0.038228312 | Y12: =Settings!$B$21*(Q12-I$6)^2 -> 0.38533404 | Z12: =Settings!$B$22*(R12-J$6)^2 -> 0.091880579 | AA12: =Settings!$B$23*(S12-K$6)^2 -> 0.024654827 | AB12: =Settings!$B$24*(T12-L$6)^2 -> 0.075054787 | AC12: =Settings!$B$25*(U12-M$6)^2 -> 0.0024278534 | AD12: =SQRT(SUM(V12:AC12)) -> 0.85222078 | AE12: =AD12/Yardstick -> 0.33732443 | AF12: =EXP(-(AD12^2)/(2*Yardstick^2)) -> 0.94469431 | AG12: =AF12/$E$7 -> 0.0040786231 | AH12: -0.57804338 | AI12: 0 | AJ12: -0.65431191 | AK12: 0 | AL12: 0.5139469 | AM12: 0 | AN12: 1.7044441 | AO12: 0 | AP12: -0.91910328 | AQ12: 0
A13: 3 | B13: Nick Suzuki | C13: 2024-25 & 2025-26 | D13: 26 | E13: 1 | F13: 0.30839482 | G13: 0.1369975 | H13: 0.16305717 | I13: 0.025209162 | J13: 0.36634134 | K13: 19.522967 | L13: 3.4740979 | M13: -0.95900817 | N13: =(F13-Settings!$D$18)/Settings!$E$18 -> 0.41541578 | O13: =(G13-Settings!$D$19)/Settings!$E$19 -> 0.59842005 | P13: =(H13-Settings!$D$20)/Settings!$E$20 -> 0.99598672 | Q13: =(I13-Settings!$D$21)/Settings!$E$21 -> 0.34621394 | R13: =(J13-Settings!$D$22)/Settings!$E$22 -> 0.31877631 | S13: =(K13-Settings!$D$23)/Settings!$E$23 -> 1.4820935 | T13: =(L13-Settings!$D$24)/Settings!$E$24 -> 1.4973567 | U13: =(M13-Settings!$D$25)/Settings!$E$25 -> -0.61079553 | V13: =Settings!$B$18*(N13-F$6)^2 -> 0.027184392 | W13: =Settings!$B$19*(O13-G$6)^2 -> 0.001781377 | X13: =Settings!$B$20*(P13-H$6)^2 -> 0.320322 | Y13: =Settings!$B$21*(Q13-I$6)^2 -> 0.29086181 | Z13: =Settings!$B$22*(R13-J$6)^2 -> 0.0055051992 | AA13: =Settings!$B$23*(S13-K$6)^2 -> 0.060392069 | AB13: =Settings!$B$24*(T13-L$6)^2 -> 0.00083284877 | AC13: =Settings!$B$25*(U13-M$6)^2 -> 0.18392145 | AD13: =SQRT(SUM(V13:AC13)) -> 0.94382262 | AE13: =AD13/Yardstick -> 0.3735821 | AF13: =EXP(-(AD13^2)/(2*Yardstick^2)) -> 0.9325973 | AG13: =AF13/$E$7 -> 0.0040263954
A14: 4 | B14: Mitch Marner | C14: 2022-23 & 2023-24 | D14: 26 | E14: 1 | F14: 0.12272677 | G14: 0.063112713 | H14: 0.24234025 | I14: -0.005492629 | J14: 0.56632763 | K14: 20.460962 | L14: 4.6096923 | M14: -0.5167408 | N14: =(F14-Settings!$D$18)/Settings!$E$18 -> -0.24907859 | O14: =(G14-Settings!$D$19)/Settings!$E$19 -> 0.29060659 | P14: =(H14-Settings!$D$20)/Settings!$E$20 -> 1.7143067 | Q14: =(I14-Settings!$D$21)/Settings!$E$21 -> -0.031335424 | R14: =(J14-Settings!$D$22)/Settings!$E$22 -> 0.85684885 | S14: =(K14-Settings!$D$23)/Settings!$E$23 -> 1.8078374 | T14: =(L14-Settings!$D$24)/Settings!$E$24 -> 2.2824552 | U14: =(M14-Settings!$D$25)/Settings!$E$25 -> -0.31252549 | V14: =Settings!$B$18*(N14-F$6)^2 -> 0.017501707 | W14: =Settings!$B$19*(O14-G$6)^2 -> 0.0091110843 | X14: =Settings!$B$20*(P14-H$6)^2 -> 0.059891558 | Y14: =Settings!$B$21*(Q14-I$6)^2 -> 0.13724865 | Z14: =Settings!$B$22*(R14-J$6)^2 -> 0.099118171 | AA14: =Settings!$B$23*(S14-K$6)^2 -> 0.0063993493 | AB14: =Settings!$B$24*(T14-L$6)^2 -> 0.57189801 | AC14: =Settings!$B$25*(U14-M$6)^2 -> 0.017053903 | AD14: =SQRT(SUM(V14:AC14)) -> 0.95823923 | AE14: =AD14/Yardstick -> 0.37928846 | AF14: =EXP(-(AD14^2)/(2*Yardstick^2)) -> 0.93059616 | AG14: =AF14/$E$7 -> 0.0040177557 | AH14: -0.48909737 | AI14: 1 | AJ14: -0.3425315 | AK14: 1
A15: 5 | B15: Claude Giroux | C15: 2012-13 & 2013-14 | D15: 26 | E15: 0 | F15: 0.23256167 | G15: -0.18234015 | H15: 0.20313402 | I15: 0.012944155 | J15: 0.36902001 | K15: 20.015897 | L15: 3.5269289 | M15: -1.0698504 | N15: =(F15-Settings!$D$18)/Settings!$E$18 -> 0.14401365 | O15: =(G15-Settings!$D$19)/Settings!$E$19 -> -0.7319813 | P15: =(H15-Settings!$D$20)/Settings!$E$20 -> 1.3590906 | Q15: =(I15-Settings!$D$21)/Settings!$E$21 -> 0.19538738 | R15: =(J15-Settings!$D$22)/Settings!$E$22 -> 0.32598341 | S15: =(K15-Settings!$D$23)/Settings!$E$23 -> 1.6532767 | T15: =(L15-Settings!$D$24)/Settings!$E$24 -> 1.5338817 | U15: =(M15-Settings!$D$25)/Settings!$E$25 -> -0.68554876 | V15: =Settings!$B$18*(N15-F$6)^2 -> 0.0018924395 | W15: =Settings!$B$19*(O15-G$6)^2 -> 0.30555159 | X15: =Settings!$B$20*(P15-H$6)^2 -> 0.16288081 | Y15: =Settings!$B$21*(Q15-I$6)^2 -> 0.22265598 | Z15: =Settings!$B$22*(R15-J$6)^2 -> 0.0059938783 | AA15: =Settings!$B$23*(S15-K$6)^2 -> 0.0055599008 | AB15: =Settings!$B$24*(T15-L$6)^2 -> 5.8765095e-05 | AC15: =Settings!$B$25*(U15-M$6)^2 -> 0.25362693 | AD15: =SQRT(SUM(V15:AC15)) -> 0.97888727 | AE15: =AD15/Yardstick -> 0.38746133 | AF15: =EXP(-(AD15^2)/(2*Yardstick^2)) -> 0.92768491 | AG15: =AF15/$E$7 -> 0.0040051867 | AH15: -0.3351623 | AI15: 0 | AJ15: -0.25167536 | AK15: 0 | AL15: -0.7379041 | AM15: 0 | AN15: 1.8476021 | AO15: 0 | AP15: 0.60494629 | AQ15: 1
A16: 6 | B16: Nathan Mackinnon | C16: 2020-21 & 2021-22 | D16: 26 | E16: 1 | F16: 0.3562191 | G16: -0.1126197 | H16: 0.16051761 | I16: 0.00012244434 | J16: 0.37052115 | K16: 19.992183 | L16: 4.2984445 | M16: -0.47765556 | N16: =(F16-Settings!$D$18)/Settings!$E$18 -> 0.58657588 | O16: =(G16-Settings!$D$19)/Settings!$E$19 -> -0.44151703 | P16: =(H16-Settings!$D$20)/Settings!$E$20 -> 0.97297777 | Q16: =(I16-Settings!$D$21)/Settings!$E$21 -> 0.03771486 | R16: =(J16-Settings!$D$22)/Settings!$E$22 -> 0.33002229 | S16: =(K16-Settings!$D$23)/Settings!$E$23 -> 1.6450412 | T16: =(L16-Settings!$D$24)/Settings!$E$24 -> 2.0672727 | U16: =(M16-Settings!$D$25)/Settings!$E$25 -> -0.28616597 | V16: =Settings!$B$18*(N16-F$6)^2 -> 0.058284595 | W16: =Settings!$B$19*(O16-G$6)^2 -> 0.17881704 | X16: =Settings!$B$20*(P16-H$6)^2 -> 0.33207544 | Y16: =Settings!$B$21*(Q16-I$6)^2 -> 0.16108268 | Z16: =Settings!$B$22*(R16-J$6)^2 -> 0.0062768198 | AA16: =Settings!$B$23*(S16-K$6)^2 -> 0.0068558828 | AB16: =Settings!$B$24*(T16-L$6)^2 -> 0.29274248 | AC16: =Settings!$B$25*(U16-M$6)^2 -> 0.010864117 | AD16: =SQRT(SUM(V16:AC16)) -> 1.0232297 | AE16: =AD16/Yardstick -> 0.40501287 | AF16: =EXP(-(AD16^2)/(2*Yardstick^2)) -> 0.92125564 | AG16: =AF16/$E$7 -> 0.003977429 | AH16: 0.63124458 | AI16: 1 | AJ16: 2.6460712 | AK16: 1 | AL16: -0.20769262 | AM16: 1 | AN16: -0.66171672 | AO16: 1
A17: 7 | B17: Mathew Barzal | C17: 2022-23 & 2023-24 | D17: 26 | E17: 1 | F17: 0.38049616 | G17: -0.13031032 | H17: 0.2594289 | I17: 1.2102934e-05 | J17: 0.22975252 | K17: 18.918357 | L17: 2.6804045 | M17: 0.069187325 | N17: =(F17-Settings!$D$18)/Settings!$E$18 -> 0.67346197 | O17: =(G17-Settings!$D$19)/Settings!$E$19 -> -0.51521843 | P17: =(H17-Settings!$D$20)/Settings!$E$20 -> 1.8691331 | Q17: =(I17-Settings!$D$21)/Settings!$E$21 -> 0.036357958 | R17: =(J17-Settings!$D$22)/Settings!$E$22 -> -0.048722344 | S17: =(K17-Settings!$D$23)/Settings!$E$23 -> 1.2721263 | T17: =(L17-Settings!$D$24)/Settings!$E$24 -> 0.94863306 | U17: =(M17-Settings!$D$25)/Settings!$E$25 -> 0.08263096 | V17: =Settings!$B$18*(N17-F$6)^2 -> 0.078556131 | W17: =Settings!$B$19*(O17-G$6)^2 -> 0.20777908 | X17: =Settings!$B$20*(P17-H$6)^2 -> 0.030795702 | Y17: =Settings!$B$21*(Q17-I$6)^2 -> 0.16059595 | Z17: =Settings!$B$22*(R17-J$6)^2 -> 0.0081276296 | AA17: =Settings!$B$23*(S17-K$6)^2 -> 0.20767627 | AB17: =Settings!$B$24*(T17-L$6)^2 -> 0.33360187 | AC17: =Settings!$B$25*(U17-M$6)^2 -> 0.069995092 | AD17: =SQRT(SUM(V17:AC17)) -> 1.0474387 | AE17: =AD17/Yardstick -> 0.41459521 | AF17: =EXP(-(AD17^2)/(2*Yardstick^2)) -> 0.91764507 | AG17: =AF17/$E$7 -> 0.0039618407 | AH17: -0.3712362 | AI17: 1 | AJ17: -0.089494464 | AK17: 1
A18: 8 | B18: Ryan Callahan | C18: 2010-11 & 2011-12 | D18: 26 | E18: 0 | F18: 0.11597382 | G18: -0.024835333 | H18: 0.27595417 | I18: 0.03069616 | J18: 0.55254051 | K18: 19.937255 | L18: 3.2605522 | M18: -1.4472951 | N18: =(F18-Settings!$D$18)/Settings!$E$18 -> -0.27324699 | O18: =(G18-Settings!$D$19)/Settings!$E$19 -> -0.075796175 | P18: =(H18-Settings!$D$20)/Settings!$E$20 -> 2.0188553 | Q18: =(I18-Settings!$D$21)/Settings!$E$21 -> 0.41368925 | R18: =(J18-Settings!$D$22)/Settings!$E$22 -> 0.81975396 | S18: =(K18-Settings!$D$23)/Settings!$E$23 -> 1.6259659 | T18: =(L18-Settings!$D$24)/Settings!$E$24 -> 1.3497209 | U18: =(M18-Settings!$D$25)/Settings!$E$25 -> -0.9401017 | V18: =Settings!$B$18*(N18-F$6)^2 -> 0.020478312 | W18: =Settings!$B$19*(O18-G$6)^2 -> 0.067242869 | X18: =Settings!$B$20*(P18-H$6)^2 -> 0.011778598 | Y18: =Settings!$B$21*(Q18-I$6)^2 -> 0.32432106 | Z18: =Settings!$B$22*(R18-J$6)^2 -> 0.088947719 | AA18: =Settings!$B$23*(S18-K$6)^2 -> 0.010378615 | AB18: =Settings!$B$24*(T18-L$6)^2 -> 0.031150466 | AC18: =Settings!$B$25*(U18-M$6)^2 -> 0.5748169 | AD18: =SQRT(SUM(V18:AC18)) -> 1.062598 | AE18: =AD18/Yardstick -> 0.42059556 | AF18: =EXP(-(AD18^2)/(2*Yardstick^2)) -> 0.91534859 | AG18: =AF18/$E$7 -> 0.0039519259 | AH18: -0.41966118 | AI18: 0 | AJ18: -0.39013486 | AK18: 0 | AL18: -0.21604564 | AM18: 0 | AN18: -1.040292 | AO18: 0
A19: 9 | B19: John Tavares | C19: 2015-16 & 2016-17 | D19: 26 | E19: 0 | F19: 0.46710781 | G19: -0.14957658 | H19: 0.16998335 | I19: 0.014638972 | J19: 0.19869328 | K19: 19.59129 | L19: 3.0032701 | M19: -0.18257105 | N19: =(F19-Settings!$D$18)/Settings!$E$18 -> 0.98343968 | O19: =(G19-Settings!$D$19)/Settings!$E$19 -> -0.59548412 | P19: =(H19-Settings!$D$20)/Settings!$E$20 -> 1.0587392 | Q19: =(I19-Settings!$D$21)/Settings!$E$21 -> 0.21622906 | R19: =(J19-Settings!$D$22)/Settings!$E$22 -> -0.13228867 | S19: =(K19-Settings!$D$23)/Settings!$E$23 -> 1.5058204 | T19: =(L19-Settings!$D$24)/Settings!$E$24 -> 1.1718477 | U19: =(M19-Settings!$D$25)/Settings!$E$25 -> -0.087157694 | V19: =Settings!$B$18*(N19-F$6)^2 -> 0.17548133 | W19: =Settings!$B$19*(O19-G$6)^2 -> 0.24179231 | X19: =Settings!$B$20*(P19-H$6)^2 -> 0.28934308 | Y19: =Settings!$B$21*(Q19-I$6)^2 -> 0.23153905 | Z19: =Settings!$B$22*(R19-J$6)^2 -> 0.016262719 | AA19: =Settings!$B$23*(S19-K$6)^2 -> 0.049293336 | AB19: =Settings!$B$24*(T19-L$6)^2 -> 0.12557676 | AC19: =Settings!$B$25*(U19-M$6)^2 -> 0.0089827179 | AD19: =SQRT(SUM(V19:AC19)) -> 1.066898 | AE19: =AD19/Yardstick -> 0.42229756 | AF19: =EXP(-(AD19^2)/(2*Yardstick^2)) -> 0.91469224 | AG19: =AF19/$E$7 -> 0.0039490922 | AH19: 0.1003808 | AI19: 0 | AJ19: 0.94778134 | AK19: 1 | AL19: -0.065618058 | AM19: 1 | AN19: -1.4225728 | AO19: 1 | AP19: -0.61502027 | AQ19: 1
A20: 10 | B20: Corey Perry | C20: 2010-11 & 2011-12 | D20: 26 | E20: 0 | F20: 0.16664295 | G20: 0.0014466935 | H20: 0.15449131 | I20: 0.012900591 | J20: 0.66451846 | K20: 21.203909 | L20: 4.2475294 | M20: -0.45197796 | N20: =(F20-Settings!$D$18)/Settings!$E$18 -> -0.091905346 | O20: =(G20-Settings!$D$19)/Settings!$E$19 -> 0.033698096 | P20: =(H20-Settings!$D$20)/Settings!$E$20 -> 0.91837839 | Q20: =(I20-Settings!$D$21)/Settings!$E$21 -> 0.19485166 | R20: =(J20-Settings!$D$22)/Settings!$E$22 -> 1.1210359 | S20: =(K20-Settings!$D$23)/Settings!$E$23 -> 2.0658459 | T20: =(L20-Settings!$D$24)/Settings!$E$24 -> 2.0320722 | U20: =(M20-Settings!$D$25)/Settings!$E$25 -> -0.26884871 | V20: =Settings!$B$18*(N20-F$6)^2 -> 0.0038444966 | W20: =Settings!$B$19*(O20-G$6)^2 -> 0.044245008 | X20: =Settings!$B$20*(P20-H$6)^2 -> 0.36081342 | Y20: =Settings!$B$21*(Q20-I$6)^2 -> 0.22242994 | Z20: =Settings!$B$22*(R20-J$6)^2 -> 0.18747031 | AA20: =Settings!$B$23*(S20-K$6)^2 -> 0.11424705 | AB20: =Settings!$B$24*(T20-L$6)^2 -> 0.25589069 | AC20: =Settings!$B$25*(U20-M$6)^2 -> 0.0075540116 | AD20: =SQRT(SUM(V20:AC20)) -> 1.0938441 | AE20: =AD20/Yardstick -> 0.43296333 | AF20: =EXP(-(AD20^2)/(2*Yardstick^2)) -> 0.91052983 | AG20: =AF20/$E$7 -> 0.0039311214 | AH20: -1.5098182 | AI20: 0 | AJ20: 0.71003937 | AK20: 0 | AL20: 1.294527 | AM20: 0 | AN20: -1.5072786 | AO20: 0 | AP20: -1.8452489 | AQ20: 0
A21: 11 | B21: Kyle Okposo | C21: 2013-14 & 2014-15 | D21: 26 | E21: 0 | F21: 0.32562787 | G21: -0.168693 | H21: 0.15778631 | I21: -0.00076710586 | J21: 0.34712571 | K21: 19.495929 | L21: 2.7267188 | M21: -0.59461491 | N21: =(F21-Settings!$D$18)/Settings!$E$18 -> 0.47709178 | O21: =(G21-Settings!$D$19)/Settings!$E$19 -> -0.67512556 | P21: =(H21-Settings!$D$20)/Settings!$E$20 -> 0.94823174 | Q21: =(I21-Settings!$D$21)/Settings!$E$21 -> 0.026775788 | R21: =(J21-Settings!$D$22)/Settings!$E$22 -> 0.26707575 | S21: =(K21-Settings!$D$23)/Settings!$E$23 -> 1.4727035 | T21: =(L21-Settings!$D$24)/Settings!$E$24 -> 0.9806527 | U21: =(M21-Settings!$D$25)/Settings!$E$25 -> -0.36504466 | V21: =Settings!$B$18*(N21-F$6)^2 -> 0.037040562 | W21: =Settings!$B$19*(O21-G$6)^2 -> 0.27808806 | X21: =Settings!$B$20*(P21-H$6)^2 -> 0.34495258 | Y21: =Settings!$B$21*(Q21-I$6)^2 -> 0.15717971 | Z21: =Settings!$B$22*(R21-J$6)^2 -> 0.0026087409 | AA21: =Settings!$B$23*(S21-K$6)^2 -> 0.065095351 | AB21: =Settings!$B$24*(T21-L$6)^2 -> 0.29763914 | AC21: =Settings!$B$25*(U21-M$6)^2 -> 0.033529186 | AD21: =SQRT(SUM(V21:AC21)) -> 1.1027844 | AE21: =AD21/Yardstick -> 0.43650204 | AF21: =EXP(-(AD21^2)/(2*Yardstick^2)) -> 0.90913015 | AG21: =AF21/$E$7 -> 0.0039250784 | AH21: -0.23118646 | AI21: 0 | AJ21: 0.098558957 | AK21: 0 | AL21: -1.2201049 | AM21: 0 | AN21: -1.1180921 | AO21: 1 | AP21: 0.60967124 | AQ21: 1
A22: 12 | B22: William Nylander | C22: 2021-22 & 2022-23 | D22: 26 | E22: 1 | F22: 0.34222721 | G22: -0.098390263 | H22: 0.25060226 | I22: 0.0040602 | J22: 0.30472006 | K22: 17.839366 | L22: 3.9369356 | M22: -0.13967572 | N22: =(F22-Settings!$D$18)/Settings!$E$18 -> 0.53649979 | O22: =(G22-Settings!$D$19)/Settings!$E$19 -> -0.38223539 | P22: =(H22-Settings!$D$20)/Settings!$E$20 -> 1.7891621 | Q22: =(I22-Settings!$D$21)/Settings!$E$21 -> 0.086138652 | R22: =(J22-Settings!$D$22)/Settings!$E$22 -> 0.15298136 | S22: =(K22-Settings!$D$23)/Settings!$E$23 -> 0.8974174 | T22: =(L22-Settings!$D$24)/Settings!$E$24 -> 1.8173417 | U22: =(M22-Settings!$D$25)/Settings!$E$25 -> -0.0582286 | V22: =Settings!$B$18*(N22-F$6)^2 -> 0.047972965 | W22: =Settings!$B$19*(O22-G$6)^2 -> 0.15709814 | X22: =Settings!$B$20*(P22-H$6)^2 -> 0.044627048 | Y22: =Settings!$B$21*(Q22-I$6)^2 -> 0.1789348 | Z22: =Settings!$B$22*(R22-J$6)^2 -> 2.6288406e-09 | AA22: =Settings!$B$23*(S22-K$6)^2 -> 0.68960407 | AB22: =Settings!$B$24*(T22-L$6)^2 -> 0.08475428 | AC22: =Settings!$B$25*(U22-M$6)^2 -> 0.015303248 | AD22: =SQRT(SUM(V22:AC22)) -> 1.1037638 | AE22: =AD22/Yardstick -> 0.43688973 | AF22: =EXP(-(AD22^2)/(2*Yardstick^2)) -> 0.90897625 | AG22: =AF22/$E$7 -> 0.0039244139 | AH22: 0.23928665 | AI22: 1 | AJ22: 0.23503102 | AK22: 1 | AL22: -0.93913551 | AM22: 1
A23: 13 | B23: Ryan Kesler | C23: 2009-10 & 2010-11 | D23: 26 | E23: 0 | F23: 0.2425076 | G23: -0.016935511 | H23: 0.23719868 | I23: -0.10298328 | J23: 0.40037493 | K23: 19.499284 | L23: 3.5435546 | M23: 1.1697164 | N23: =(F23-Settings!$D$18)/Settings!$E$18 -> 0.17960952 | O23: =(G23-Settings!$D$19)/Settings!$E$19 -> -0.042884512 | P23: =(H23-Settings!$D$20)/Settings!$E$20 -> 1.667723 | Q23: =(I23-Settings!$D$21)/Settings!$E$21 -> -1.2302079 | R23: =(J23-Settings!$D$22)/Settings!$E$22 -> 0.41034529 | S23: =(K23-Settings!$D$23)/Settings!$E$23 -> 1.4738688 | T23: =(L23-Settings!$D$24)/Settings!$E$24 -> 1.545376 | U23: =(M23-Settings!$D$25)/Settings!$E$25 -> 0.82484001 | V23: =Settings!$B$18*(N23-F$6)^2 -> 0.0035308711 | W23: =Settings!$B$19*(O23-G$6)^2 -> 0.059826106 | X23: =Settings!$B$20*(P23-H$6)^2 -> 0.070522296 | Y23: =Settings!$B$21*(Q23-I$6)^2 -> 0.027450273 | Z23: =Settings!$B$22*(R23-J$6)^2 -> 0.013259043 | AA23: =Settings!$B$23*(S23-K$6)^2 -> 0.064502091 | AB23: =Settings!$B$24*(T23-L$6)^2 -> 0.00036711022 | AC23: =Settings!$B$25*(U23-M$6)^2 -> 1.0135957 | AD23: =SQRT(SUM(V23:AC23)) -> 1.1193987 | AE23: =AD23/Yardstick -> 0.44307831 | AF23: =EXP(-(AD23^2)/(2*Yardstick^2)) -> 0.90650458 | AG23: =AF23/$E$7 -> 0.0039137428 | AH23: -0.94137902 | AI23: 0 | AN23: -0.21824838 | AO23: 0 | AP23: 0.1182402 | AQ23: 0
A24: 14 | B24: Jamie Benn | C24: 2014-15 & 2015-16 | D24: 26 | E24: 0 | F24: 0.3449204 | G24: -0.058298587 | H24: 0.15521663 | I24: 0.019743575 | J24: 0.42182081 | K24: 19.319614 | L24: 4.40853 | M24: -0.032292762 | N24: =(F24-Settings!$D$18)/Settings!$E$18 -> 0.54613855 | O24: =(G24-Settings!$D$19)/Settings!$E$19 -> -0.21520836 | P24: =(H24-Settings!$D$20)/Settings!$E$20 -> 0.92494991 | Q24: =(I24-Settings!$D$21)/Settings!$E$21 -> 0.27900193 | R24: =(J24-Settings!$D$22)/Settings!$E$22 -> 0.46804643 | S24: =(K24-Settings!$D$23)/Settings!$E$23 -> 1.4114734 | T24: =(L24-Settings!$D$24)/Settings!$E$24 -> 2.1433808 | U24: =(M24-Settings!$D$25)/Settings!$E$25 -> 0.01419166 | V24: =Settings!$B$18*(N24-F$6)^2 -> 0.049879817 | W24: =Settings!$B$19*(O24-G$6)^2 -> 0.10346472 | X24: =Settings!$B$20*(P24-H$6)^2 -> 0.35729142 | Y24: =Settings!$B$21*(Q24-I$6)^2 -> 0.25934364 | Z24: =Settings!$B$22*(R24-J$6)^2 -> 0.019867651 | AA24: =Settings!$B$23*(S24-K$6)^2 -> 0.10008873 | AB24: =Settings!$B$24*(T24-L$6)^2 -> 0.38089254 | AC24: =Settings!$B$25*(U24-M$6)^2 -> 0.038465626 | AD24: =SQRT(SUM(V24:AC24)) -> 1.1442439 | AE24: =AD24/Yardstick -> 0.45291249 | AF24: =EXP(-(AD24^2)/(2*Yardstick^2)) -> 0.90251961 | AG24: =AF24/$E$7 -> 0.003896538 | AH24: -1.4236101 | AI24: 0 | AJ24: -0.48071519 | AK24: 0 | AL24: 0.31286203 | AM24: 1 | AN24: -0.46999239 | AO24: 1 | AP24: -0.28865244 | AQ24: 1
A25: 15 | B25: Jon Huberdeau | C25: 2018-19 & 2019-20 | D25: 26 | E25: 1 | F25: 0.22924031 | G25: -0.071534159 | H25: 0.17667476 | I25: 0.0012995536 | J25: 0.52125121 | K25: 18.086755 | L25: 2.8771261 | M25: -0.13865212 | N25: =(F25-Settings!$D$18)/Settings!$E$18 -> 0.13212672 | O25: =(G25-Settings!$D$19)/Settings!$E$19 -> -0.27034944 | P25: =(H25-Settings!$D$20)/Settings!$E$20 -> 1.1193647 | Q25: =(I25-Settings!$D$21)/Settings!$E$21 -> 0.052190135 | R25: =(J25-Settings!$D$22)/Settings!$E$22 -> 0.73556862 | S25: =(K25-Settings!$D$23)/Settings!$E$23 -> 0.98332988 | T25: =(L25-Settings!$D$24)/Settings!$E$24 -> 1.0846375 | U25: =(M25-Settings!$D$25)/Settings!$E$25 -> -0.057538273 | V25: =Settings!$B$18*(N25-F$6)^2 -> 0.0014581844 | W25: =Settings!$B$19*(O25-G$6)^2 -> 0.11993696 | X25: =Settings!$B$20*(P25-H$6)^2 -> 0.26091014 | Y25: =Settings!$B$21*(Q25-I$6)^2 -> 0.16632091 | Z25: =Settings!$B$22*(R25-J$6)^2 -> 0.067908302 | AA25: =Settings!$B$23*(S25-K$6)^2 -> 0.55429745 | AB25: =Settings!$B$24*(T25-L$6)^2 -> 0.19499146 | AC25: =Settings!$B$25*(U25-M$6)^2 -> 0.01547452 | AD25: =SQRT(SUM(V25:AC25)) -> 1.1752863 | AE25: =AD25/Yardstick -> 0.46519963 | AF25: =EXP(-(AD25^2)/(2*Yardstick^2)) -> 0.89744329 | AG25: =AF25/$E$7 -> 0.0038746215 | AH25: 0.4674795 | AI25: 1 | AJ25: -0.33301118 | AK25: 1 | AL25: -1.4501321 | AM25: 1 | AN25: -0.75336464 | AO25: 1 | AP25: 1.1487507 | AQ25: 1
A26: 16 | B26: Artemi Panarin | C26: 2016-17 & 2017-18 | D26: 26 | E26: 0 | F26: 0.30304475 | G26: -0.05440448 | H26: 0.099305898 | I26: 6.4957469e-06 | J26: 0.54323838 | K26: 19.231084 | L26: 3.0895536 | M26: -1.0740975 | N26: =(F26-Settings!$D$18)/Settings!$E$18 -> 0.3962682 | O26: =(G26-Settings!$D$19)/Settings!$E$19 -> -0.19898501 | P26: =(H26-Settings!$D$20)/Settings!$E$20 -> 0.41838792 | Q26: =(I26-Settings!$D$21)/Settings!$E$21 -> 0.036289005 | R26: =(J26-Settings!$D$22)/Settings!$E$22 -> 0.79472612 | S26: =(K26-Settings!$D$23)/Settings!$E$23 -> 1.380729 | T26: =(L26-Settings!$D$24)/Settings!$E$24 -> 1.2315002 | U26: =(M26-Settings!$D$25)/Settings!$E$25 -> -0.68841305 | V26: =Settings!$B$18*(N26-F$6)^2 -> 0.024434017 | W26: =Settings!$B$19*(O26-G$6)^2 -> 0.098849889 | X26: =Settings!$B$20*(P26-H$6)^2 -> 0.67943751 | Y26: =Settings!$B$21*(Q26-I$6)^2 -> 0.16057124 | Z26: =Settings!$B$22*(R26-J$6)^2 -> 0.082396701 | AA26: =Settings!$B$23*(S26-K$6)^2 -> 0.12048705 | AB26: =Settings!$B$24*(T26-L$6)^2 -> 0.086857286 | AC26: =Settings!$B$25*(U26-M$6)^2 -> 0.25652012 | AD26: =SQRT(SUM(V26:AC26)) -> 1.228639 | AE26: =AD26/Yardstick -> 0.48631759 | AF26: =EXP(-(AD26^2)/(2*Yardstick^2)) -> 0.88847177 | AG26: =AF26/$E$7 -> 0.0038358879 | AH26: 0.6119958 | AI26: 1 | AJ26: 1.2355766 | AK26: 1 | AL26: -0.59375804 | AM26: 1 | AN26: -1.9216072 | AO26: 1 | AP26: 0.09099142 | AQ26: 1
A27: 17 | B27: Dylan Larkin | C27: 2021-22 & 2022-23 | D27: 26 | E27: 1 | F27: 0.29148679 | G27: 0.018638673 | H27: 0.1724683 | I27: -0.010095224 | J27: 0.50731102 | K27: 18.842053 | L27: 4.1285941 | M27: -1.4718056 | N27: =(F27-Settings!$D$18)/Settings!$E$18 -> 0.35490298 | O27: =(G27-Settings!$D$19)/Settings!$E$19 -> 0.10532207 | P27: =(H27-Settings!$D$20)/Settings!$E$20 -> 1.0812533 | Q27: =(I27-Settings!$D$21)/Settings!$E$21 -> -0.087934948 | R27: =(J27-Settings!$D$22)/Settings!$E$22 -> 0.69806187 | S27: =(K27-Settings!$D$23)/Settings!$E$23 -> 1.2456275 | T27: =(L27-Settings!$D$24)/Settings!$E$24 -> 1.9498457 | U27: =(M27-Settings!$D$25)/Settings!$E$25 -> -0.95663182 | V27: =Settings!$B$18*(N27-F$6)^2 -> 0.018992906 | W27: =Settings!$B$19*(O27-G$6)^2 -> 0.031795796 | X27: =Settings!$B$20*(P27-H$6)^2 -> 0.27861251 | Y27: =Settings!$B$21*(Q27-I$6)^2 -> 0.11913458 | Z27: =Settings!$B$22*(R27-J$6)^2 -> 0.059447551 | AA27: =Settings!$B$23*(S27-K$6)^2 -> 0.23253027 | AB27: =Settings!$B$24*(T27-L$6)^2 -> 0.17946229 | AC27: =Settings!$B$25*(U27-M$6)^2 -> 0.60015532 | AD27: =SQRT(SUM(V27:AC27)) -> 1.232936 | AE27: =AD27/Yardstick -> 0.48801843 | AF27: =EXP(-(AD27^2)/(2*Yardstick^2)) -> 0.8877359 | AG27: =AF27/$E$7 -> 0.0038327109 | AH27: 0.14761959 | AI27: 1 | AJ27: -0.21884885 | AK27: 1 | AL27: -1.3468144 | AM27: 1
A28: 18 | B28: Mikko Rantanen | C28: 2021-22 & 2022-23 | D28: 26 | E28: 1 | F28: 0.22356683 | G28: -0.12027257 | H28: 0.13687945 | I28: -2.5123729e-05 | J28: 0.51925603 | K28: 20.740658 | L28: 4.718305 | M28: -0.0018451867 | N28: =(F28-Settings!$D$18)/Settings!$E$18 -> 0.11182168 | O28: =(G28-Settings!$D$19)/Settings!$E$19 -> -0.47339985 | P28: =(H28-Settings!$D$20)/Settings!$E$20 -> 0.75881152 | Q28: =(I28-Settings!$D$21)/Settings!$E$21 -> 0.03590017 | R28: =(J28-Settings!$D$22)/Settings!$E$22 -> 0.73020049 | S28: =(K28-Settings!$D$23)/Settings!$E$23 -> 1.9049694 | T28: =(L28-Settings!$D$24)/Settings!$E$24 -> 2.3575451 | U28: =(M28-Settings!$D$25)/Settings!$E$25 -> 0.034725844 | V28: =Settings!$B$18*(N28-F$6)^2 -> 0.00084712974 | W28: =Settings!$B$19*(O28-G$6)^2 -> 0.1910792 | X28: =Settings!$B$20*(P28-H$6)^2 -> 0.45163499 | Y28: =Settings!$B$21*(Q28-I$6)^2 -> 0.16043191 | Z28: =Settings!$B$22*(R28-J$6)^2 -> 0.066662858 | AA28: =Settings!$B$23*(S28-K$6)^2 -> 0.031374325 | AB28: =Settings!$B$24*(T28-L$6)^2 -> 0.69110838 | AC28: =Settings!$B$25*(U28-M$6)^2 -> 0.046941876 | AD28: =SQRT(SUM(V28:AC28)) -> 1.2806563 | AE28: =AD28/Yardstick -> 0.506907 | AF28: =EXP(-(AD28^2)/(2*Yardstick^2)) -> 0.87943348 | AG28: =AF28/$E$7 -> 0.003796866 | AH28: -0.76785446 | AI28: 1 | AJ28: -2.7408486 | AK28: 1 | AL28: -0.55932765 | AM28: 1
A29: 19 | B29: Mark Scheifele | C29: 2018-19 & 2019-20 | D29: 26 | E29: 1 | F29: 0.21775739 | G29: -0.20061631 | H29: 0.10929928 | I29: -0.012682744 | J29: 0.45964428 | K29: 21.019499 | L29: 2.8622566 | M29: -1.0857048 | N29: =(F29-Settings!$D$18)/Settings!$E$18 -> 0.091030054 | O29: =(G29-Settings!$D$19)/Settings!$E$19 -> -0.80812211 | P29: =(H29-Settings!$D$20)/Settings!$E$20 -> 0.50892987 | Q29: =(I29-Settings!$D$21)/Settings!$E$21 -> -0.11975448 | R29: =(J29-Settings!$D$22)/Settings!$E$22 -> 0.56981227 | S29: =(K29-Settings!$D$23)/Settings!$E$23 -> 2.0018044 | T29: =(L29-Settings!$D$24)/Settings!$E$24 -> 1.0743574 | U29: =(M29-Settings!$D$25)/Settings!$E$25 -> -0.69624112 | V29: =Settings!$B$18*(N29-F$6)^2 -> 0.00039232492 | W29: =Settings!$B$19*(O29-G$6)^2 -> 0.34435585 | X29: =Settings!$B$20*(P29-H$6)^2 -> 0.61432427 | Y29: =Settings!$B$21*(Q29-I$6)^2 -> 0.10951377 | Z29: =Settings!$B$22*(R29-J$6)^2 -> 0.03476872 | AA29: =Settings!$B$23*(S29-K$6)^2 -> 0.075055707 | AB29: =Settings!$B$24*(T29-L$6)^2 -> 0.20417606 | AC29: =Settings!$B$25*(U29-M$6)^2 -> 0.26451089 | AD29: =SQRT(SUM(V29:AC29)) -> 1.283393 | AE29: =AD29/Yardstick -> 0.50799022 | AF29: =EXP(-(AD29^2)/(2*Yardstick^2)) -> 0.87895021 | AG29: =AF29/$E$7 -> 0.0037947795 | AH29: -0.24542502 | AI29: 1 | AJ29: 0.42880443 | AK29: 1 | AL29: 0.7230788 | AM29: 1 | AN29: -0.84999619 | AO29: 1 | AP29: -0.55870973 | AQ29: 1
A30: 20 | B30: Phil Kessel | C30: 2012-13 & 2013-14 | D30: 26 | E30: 0 | F30: 0.28244394 | G30: -0.20213645 | H30: 0.075962874 | I30: 1.5674202e-05 | J30: 0.43944106 | K30: 19.802949 | L30: 3.5404889 | M30: 0.40151811 | N30: =(F30-Settings!$D$18)/Settings!$E$18 -> 0.3225392 | O30: =(G30-Settings!$D$19)/Settings!$E$19 -> -0.81445521 | P30: =(H30-Settings!$D$20)/Settings!$E$20 -> 0.20689564 | Q30: =(I30-Settings!$D$21)/Settings!$E$21 -> 0.036401875 | R30: =(J30-Settings!$D$22)/Settings!$E$22 -> 0.51545456 | S30: =(K30-Settings!$D$23)/Settings!$E$23 -> 1.5793245 | T30: =(L30-Settings!$D$24)/Settings!$E$24 -> 1.5432565 | U30: =(M30-Settings!$D$25)/Settings!$E$25 -> 0.30675855 | V30: =Settings!$B$18*(N30-F$6)^2 -> 0.015213059 | W30: =Settings!$B$19*(O30-G$6)^2 -> 0.3476879 | X30: =Settings!$B$20*(P30-H$6)^2 -> 0.84430778 | Y30: =Settings!$B$21*(Q30-I$6)^2 -> 0.16061169 | Z30: =Settings!$B$22*(R30-J$6)^2 -> 0.02629399 | AA30: =Settings!$B$23*(S30-K$6)^2 -> 0.02205728 | AB30: =Settings!$B$24*(T30-L$6)^2 -> 0.00029038271 | AC30: =Settings!$B$25*(U30-M$6)^2 -> 0.23882128 | AD30: =SQRT(SUM(V30:AC30)) -> 1.2865782 | AE30: =AD30/Yardstick -> 0.50925096 | AF30: =EXP(-(AD30^2)/(2*Yardstick^2)) -> 0.87838677 | AG30: =AF30/$E$7 -> 0.0037923469 | AH30: -1.2910538 | AI30: 0 | AJ30: -0.92501285 | AK30: 0 | AL30: 0.10456436 | AM30: 0 | AN30: 0.47071941 | AO30: 0 | AP30: 0.28731504 | AQ30: 1
A31: 21 | B31: Jason Spezza | C31: 2008-09 & 2009-10 | D31: 26 | E31: 0 | F31: 0.234805 | G31: -0.15915123 | H31: 0.096536599 | I31: -0.0027039284 | J31: 0.50680324 | K31: 18.937262 | L31: 2.6257775 | M31: -0.05830565 | N31: =(F31-Settings!$D$18)/Settings!$E$18 -> 0.15204239 | O31: =(G31-Settings!$D$19)/Settings!$E$19 -> -0.63537334 | P31: =(H31-Settings!$D$20)/Settings!$E$20 -> 0.39329754 | Q31: =(I31-Settings!$D$21)/Settings!$E$21 -> 0.002958085 | R31: =(J31-Settings!$D$22)/Settings!$E$22 -> 0.69669566 | S31: =(K31-Settings!$D$23)/Settings!$E$23 -> 1.2786914 | T31: =(L31-Settings!$D$24)/Settings!$E$24 -> 0.91086644 | U31: =(M31-Settings!$D$25)/Settings!$E$25 -> -0.0033517218 | V31: =Settings!$B$18*(N31-F$6)^2 -> 0.0022177262 | W31: =Settings!$B$19*(O31-G$6)^2 -> 0.25965426 | X31: =Settings!$B$20*(P31-H$6)^2 -> 0.69806151 | Y31: =Settings!$B$21*(Q31-I$6)^2 -> 0.14884733 | Z31: =Settings!$B$22*(R31-J$6)^2 -> 0.059149985 | AA31: =Settings!$B$23*(S31-K$6)^2 -> 0.20173577 | AB31: =Settings!$B$24*(T31-L$6)^2 -> 0.37865489 | AC31: =Settings!$B$25*(U31-M$6)^2 -> 0.03189195 | AD31: =SQRT(SUM(V31:AC31)) -> 1.3342464 | AE31: =AD31/Yardstick -> 0.52811891 | AF31: =EXP(-(AD31^2)/(2*Yardstick^2)) -> 0.86983235 | AG31: =AF31/$E$7 -> 0.0037554141 | AH31: -0.02041842 | AI31: 0 | AJ31: 0.13215851 | AK31: 0 | AP31: 0.4066143 | AQ31: 0
A32: 22 | B32: Alex Steen | C32: 2009-10 & 2010-11 | D32: 26 | E32: 0 | F32: 0.045356957 | G32: 0.13884342 | H32: 0.15578696 | I32: -0.019026005 | J32: 0.64098665 | K32: 17.533452 | L32: 3.4099875 | M32: -1.0314474 | N32: =(F32-Settings!$D$18)/Settings!$E$18 -> -0.52598035 | O32: =(G32-Settings!$D$19)/Settings!$E$19 -> 0.60611039 | P32: =(H32-Settings!$D$20)/Settings!$E$20 -> 0.93011723 | Q32: =(I32-Settings!$D$21)/Settings!$E$21 -> -0.19775951 | R32: =(J32-Settings!$D$22)/Settings!$E$22 -> 1.0577225 | S32: =(K32-Settings!$D$23)/Settings!$E$23 -> 0.79118062 | T32: =(L32-Settings!$D$24)/Settings!$E$24 -> 1.4530337 | U32: =(M32-Settings!$D$25)/Settings!$E$25 -> -0.65964934 | V32: =Settings!$B$18*(N32-F$6)^2 -> 0.065601678 | W32: =Settings!$B$19*(O32-G$6)^2 -> 0.0020835197 | X32: =Settings!$B$20*(P32-H$6)^2 -> 0.35453414 | Y32: =Settings!$B$21*(Q32-I$6)^2 -> 0.087641891 | Z32: =Settings!$B$22*(R32-J$6)^2 -> 0.16375278 | AA32: =Settings!$B$23*(S32-K$6)^2 -> 0.87733347 | AB32: =Settings!$B$24*(T32-L$6)^2 -> 0.0053556226 | AC32: =Settings!$B$25*(U32-M$6)^2 -> 0.22821109 | AD32: =SQRT(SUM(V32:AC32)) -> 1.3358571 | AE32: =AD32/Yardstick -> 0.52875646 | AF32: =EXP(-(AD32^2)/(2*Yardstick^2)) -> 0.86953934 | AG32: =AF32/$E$7 -> 0.0037541491 | AH32: 0.015483206 | AI32: 0 | AJ32: -0.78721689 | AK32: 0 | AL32: 1.4884603 | AM32: 0 | AN32: 1.2673512 | AO32: 0 | AP32: -3.1875179 | AQ32: 0
A33: 23 | B33: Jon Toews | C33: 2013-14 & 2014-15 | D33: 26 | E33: 0 | F33: 0.44959952 | G33: -0.026377285 | H33: 0.10353327 | I33: -0.015400205 | J33: 0.40508971 | K33: 19.510828 | L33: 4.1362305 | M33: -1.5167123 | N33: =(F33-Settings!$D$18)/Settings!$E$18 -> 0.9207786 | O33: =(G33-Settings!$D$19)/Settings!$E$19 -> -0.082220145 | P33: =(H33-Settings!$D$20)/Settings!$E$20 -> 0.45668876 | Q33: =(I33-Settings!$D$21)/Settings!$E$21 -> -0.15317193 | R33: =(J33-Settings!$D$22)/Settings!$E$22 -> 0.42303064 | S33: =(K33-Settings!$D$23)/Settings!$E$23 -> 1.4778777 | T33: =(L33-Settings!$D$24)/Settings!$E$24 -> 1.9551252 | U33: =(M33-Settings!$D$25)/Settings!$E$25 -> -0.98691744 | V33: =Settings!$B$18*(N33-F$6)^2 -> 0.15278876 | W33: =Settings!$B$19*(O33-G$6)^2 -> 0.068741072 | X33: =Settings!$B$20*(P33-H$6)^2 -> 0.65149329 | Y33: =Settings!$B$21*(Q33-I$6)^2 -> 0.099845828 | Z33: =Settings!$B$22*(R33-J$6)^2 -> 0.014597709 | AA33: =Settings!$B$23*(S33-K$6)^2 -> 0.062481867 | AB33: =Settings!$B$24*(T33-L$6)^2 -> 0.18396326 | AC33: =Settings!$B$25*(U33-M$6)^2 -> 0.64799689 | AD33: =SQRT(SUM(V33:AC33)) -> 1.3718268 | AE33: =AD33/Yardstick -> 0.5429939 | AF33: =EXP(-(AD33^2)/(2*Yardstick^2)) -> 0.86293044 | AG33: =AF33/$E$7 -> 0.0037256158 | AH33: -0.7265329 | AI33: 0 | AJ33: -1.0814918 | AK33: 0 | AL33: -1.1200769 | AM33: 0 | AN33: 0.89403445 | AO33: 1 | AP33: -0.37673917 | AQ33: 1
A34: 24 | B34: Drake Batherson | C34: 2023-24 & 2024-25 | D34: 26 | E34: 1 | F34: 0.069513607 | G34: -0.082440585 | H34: 0.31660199 | I34: 0.00010592703 | J34: 0.53133789 | K34: 17.516057 | L34: 2.4717436 | M34: 0.16657961 | N34: =(F34-Settings!$D$18)/Settings!$E$18 -> -0.4395252 | O34: =(G34-Settings!$D$19)/Settings!$E$19 -> -0.315787 | P34: =(H34-Settings!$D$20)/Settings!$E$20 -> 2.3871323 | Q34: =(I34-Settings!$D$21)/Settings!$E$21 -> 0.037511742 | R34: =(J34-Settings!$D$22)/Settings!$E$22 -> 0.76270729 | S34: =(K34-Settings!$D$23)/Settings!$E$23 -> 0.78513957 | T34: =(L34-Settings!$D$24)/Settings!$E$24 -> 0.8043744 | U34: =(M34-Settings!$D$25)/Settings!$E$25 -> 0.1483134 | V34: =Settings!$B$18*(N34-F$6)^2 -> 0.047290735 | W34: =Settings!$B$19*(O34-G$6)^2 -> 0.13442449 | X34: =Settings!$B$20*(P34-H$6)^2 -> 0.0031549873 | Y34: =Settings!$B$21*(Q34-I$6)^2 -> 0.16100978 | Z34: =Settings!$B$22*(R34-J$6)^2 -> 0.074381106 | AA34: =Settings!$B$23*(S34-K$6)^2 -> 0.88868679 | AB34: =Settings!$B$24*(T34-L$6)^2 -> 0.52105506 | AC34: =Settings!$B$25*(U34-M$6)^2 -> 0.10906394 | AD34: =SQRT(SUM(V34:AC34)) -> 1.3925038 | AE34: =AD34/Yardstick -> 0.55117826 | AF34: =EXP(-(AD34^2)/(2*Yardstick^2)) -> 0.85907527 | AG34: =AF34/$E$7 -> 0.0037089715 | AH34: 0.65328014 | AI34: 1
A35: 25 | B35: Sam Reinhart | C35: 2020-21 & 2021-22 | D35: 26 | E35: 1 | F35: 0.16623875 | G35: 0.11162263 | H35: 0.091111768 | I35: -0.010959551 | J35: 0.6200673 | K35: 17.855682 | L35: 4.1032811 | M35: -0.81740332 | N35: =(F35-Settings!$D$18)/Settings!$E$18 -> -0.093351934 | O35: =(G35-Settings!$D$19)/Settings!$E$19 -> 0.49270509 | P35: =(H35-Settings!$D$20)/Settings!$E$20 -> 0.34414753 | Q35: =(I35-Settings!$D$21)/Settings!$E$21 -> -0.098563844 | R35: =(J35-Settings!$D$22)/Settings!$E$22 -> 1.001438 | S35: =(K35-Settings!$D$23)/Settings!$E$23 -> 0.90308349 | T35: =(L35-Settings!$D$24)/Settings!$E$24 -> 1.9323455 | U35: =(M35-Settings!$D$25)/Settings!$E$25 -> -0.51529564 | V35: =Settings!$B$18*(N35-F$6)^2 -> 0.0039251401 | W35: =Settings!$B$19*(O35-G$6)^2 -> 2.5713071e-05 | X35: =Settings!$B$20*(P35-H$6)^2 -> 0.7352742 | Y35: =Settings!$B$21*(Q35-I$6)^2 -> 0.11587582 | Z35: =Settings!$B$22*(R35-J$6)^2 -> 0.14401463 | AA35: =Settings!$B$23*(S35-K$6)^2 -> 0.68022566 | AB35: =Settings!$B$24*(T35-L$6)^2 -> 0.16494128 | AC35: =Settings!$B$25*(U35-M$6)^2 -> 0.11112939 | AD35: =SQRT(SUM(V35:AC35)) -> 1.3983604 | AE35: =AD35/Yardstick -> 0.5534964 | AF35: =EXP(-(AD35^2)/(2*Yardstick^2)) -> 0.85797602 | AG35: =AF35/$E$7 -> 0.0037042255 | AH35: -1.0736689 | AI35: 1 | AJ35: 1.5612159 | AK35: 1 | AL35: 0.95568301 | AM35: 1 | AN35: -2.7501519 | AO35: 1
A36: 26 | B36: Logan Couture | C36: 2014-15 & 2015-16 | D36: 26 | E36: 0 | F36: 0.36999268 | G36: -0.0013826467 | H36: 0.34769374 | I36: 0.018077729 | J36: 0.2628532 | K36: 17.773507 | L36: 2.8649759 | M36: 0.92267762 | N36: =(F36-Settings!$D$18)/Settings!$E$18 -> 0.63587067 | O36: =(G36-Settings!$D$19)/Settings!$E$19 -> 0.021910704 | P36: =(H36-Settings!$D$20)/Settings!$E$20 -> 2.6688295 | Q36: =(I36-Settings!$D$21)/Settings!$E$21 -> 0.25851652 | R36: =(J36-Settings!$D$22)/Settings!$E$22 -> 0.040336608 | S36: =(K36-Settings!$D$23)/Settings!$E$23 -> 0.87454623 | T36: =(L36-Settings!$D$24)/Settings!$E$24 -> 1.0762374 | U36: =(M36-Settings!$D$25)/Settings!$E$25 -> 0.65823432 | V36: =Settings!$B$18*(N36-F$6)^2 -> 0.069415032 | W36: =Settings!$B$19*(O36-G$6)^2 -> 0.046490456 | X36: =Settings!$B$20*(P36-H$6)^2 -> 0.033177927 | Y36: =Settings!$B$21*(Q36-I$6)^2 -> 0.25009659 | Z36: =Settings!$B$22*(R36-J$6)^2 -> 0.0025326049 | AA36: =Settings!$B$23*(S36-K$6)^2 -> 0.7281127 | AB36: =Settings!$B$24*(T36-L$6)^2 -> 0.20248061 | AC36: =Settings!$B$25*(U36-M$6)^2 -> 0.70588431 | AD36: =SQRT(SUM(V36:AC36)) -> 1.427652 | AE36: =AD36/Yardstick -> 0.56509054 | AF36: =EXP(-(AD36^2)/(2*Yardstick^2)) -> 0.85243045 | AG36: =AF36/$E$7 -> 0.0036802831 | AH36: 0.49064431 | AI36: 0 | AJ36: 0.24529317 | AK36: 0 | AL36: -0.88786357 | AM36: 1 | AN36: -0.89879346 | AO36: 1 | AP36: 0.16323974 | AQ36: 1
A37: 27 | B37: Gabriel Vilardi | C37: 2024-25 & 2025-26 | D37: 26 | E37: 1 | F37: 0.23808089 | G37: -0.12777416 | H37: 0.076194753 | I37: 8.23095e-06 | J37: 0.55794197 | K37: 17.890959 | L37: 3.1591986 | M37: 0.031318898 | N37: =(F37-Settings!$D$18)/Settings!$E$18 -> 0.16376658 | O37: =(G37-Settings!$D$19)/Settings!$E$19 -> -0.50465245 | P37: =(H37-Settings!$D$20)/Settings!$E$20 -> 0.20899651 | Q37: =(I37-Settings!$D$21)/Settings!$E$21 -> 0.036310343 | R37: =(J37-Settings!$D$22)/Settings!$E$22 -> 0.83428683 | S37: =(K37-Settings!$D$23)/Settings!$E$23 -> 0.91533431 | T37: =(L37-Settings!$D$24)/Settings!$E$24 -> 1.2796496 | U37: =(M37-Settings!$D$25)/Settings!$E$25 -> 0.057092072 | V37: =Settings!$B$18*(N37-F$6)^2 -> 0.0027390526 | W37: =Settings!$B$19*(O37-G$6)^2 -> 0.20349361 | X37: =Settings!$B$20*(P37-H$6)^2 -> 0.84258205 | Y37: =Settings!$B$21*(Q37-I$6)^2 -> 0.16057888 | Z37: =Settings!$B$22*(R37-J$6)^2 -> 0.092866675 | AA37: =Settings!$B$23*(S37-K$6)^2 -> 0.66016782 | AB37: =Settings!$B$24*(T37-L$6)^2 -> 0.060794888 | AC37: =Settings!$B$25*(U37-M$6)^2 -> 0.057133891 | AD37: =SQRT(SUM(V37:AC37)) -> 1.4423442 | AE37: =AD37/Yardstick -> 0.570906 | AF37: =EXP(-(AD37^2)/(2*Yardstick^2)) -> 0.84961937 | AG37: =AF37/$E$7 -> 0.0036681466
A38: 28 | B38: Clayton Keller | C38: 2023-24 & 2024-25 | D38: 26 | E38: 1 | F38: 0.23729539 | G38: -0.036762068 | H38: 0.064966971 | I38: 5.9321291e-05 | J38: 0.66091625 | K38: 18.492558 | L38: 2.7144312 | M38: 0.032690177 | N38: =(F38-Settings!$D$18)/Settings!$E$18 -> 0.16095532 | O38: =(G38-Settings!$D$19)/Settings!$E$19 -> -0.12548447 | P38: =(H38-Settings!$D$20)/Settings!$E$20 -> 0.10727064 | Q38: =(I38-Settings!$D$21)/Settings!$E$21 -> 0.036938617 | R38: =(J38-Settings!$D$22)/Settings!$E$22 -> 1.111344 | S38: =(K38-Settings!$D$23)/Settings!$E$23 -> 1.1242558 | T38: =(L38-Settings!$D$24)/Settings!$E$24 -> 0.97215756 | U38: =(M38-Settings!$D$25)/Settings!$E$25 -> 0.058016878 | V38: =Settings!$B$18*(N38-F$6)^2 -> 0.0026090361 | W38: =Settings!$B$19*(O38-G$6)^2 -> 0.079261158 | X38: =Settings!$B$20*(P38-H$6)^2 -> 0.92817015 | Y38: =Settings!$B$21*(Q38-I$6)^2 -> 0.16080415 | Z38: =Settings!$B$22*(R38-J$6)^2 -> 0.18373574 | AA38: =Settings!$B$23*(S38-K$6)^2 -> 0.36431559 | AB38: =Settings!$B$24*(T38-L$6)^2 -> 0.30698058 | AC38: =Settings!$B$25*(U38-M$6)^2 -> 0.057576854 | AD38: =SQRT(SUM(V38:AC38)) -> 1.4434172 | AE38: =AD38/Yardstick -> 0.5713307 | AF38: =EXP(-(AD38^2)/(2*Yardstick^2)) -> 0.84941332 | AG38: =AF38/$E$7 -> 0.0036672569 | AH38: -0.070236539 | AI38: 1
A39: 29 | B39: Kyle Connor | C39: 2021-22 & 2022-23 | D39: 26 | E39: 1 | F39: 0.20144691 | G39: -0.22485851 | H39: 0.16228326 | I39: 0.0019271704 | J39: 0.40948415 | K39: 20.403854 | L39: 2.354188 | M39: -1.4298045 | N39: =(F39-Settings!$D$18)/Settings!$E$18 -> 0.032655863 | O39: =(G39-Settings!$D$19)/Settings!$E$19 -> -0.90911822 | P39: =(H39-Settings!$D$20)/Settings!$E$20 -> 0.98897495 | Q39: =(I39-Settings!$D$21)/Settings!$E$21 -> 0.059908132 | R39: =(J39-Settings!$D$22)/Settings!$E$22 -> 0.43485408 | S39: =(K39-Settings!$D$23)/Settings!$E$23 -> 1.7880051 | T39: =(L39-Settings!$D$24)/Settings!$E$24 -> 0.72310174 | U39: =(M39-Settings!$D$25)/Settings!$E$25 -> -0.92830584 | V39: =Settings!$B$18*(N39-F$6)^2 -> 3.9671584e-05 | W39: =Settings!$B$19*(O39-G$6)^2 -> 0.39940535 | X39: =Settings!$B$20*(P39-H$6)^2 -> 0.32388132 | Y39: =Settings!$B$21*(Q39-I$6)^2 -> 0.16914812 | Z39: =Settings!$B$22*(R39-J$6)^2 -> 0.015903375 | AA39: =Settings!$B$23*(S39-K$6)^2 -> 0.0036196716 | AB39: =Settings!$B$24*(T39-L$6)^2 -> 0.64499226 | AC39: =Settings!$B$25*(U39-M$6)^2 -> 0.55706958 | AD39: =SQRT(SUM(V39:AC39)) -> 1.4539805 | AE39: =AD39/Yardstick -> 0.57551185 | AF39: =EXP(-(AD39^2)/(2*Yardstick^2)) -> 0.84737924 | AG39: =AF39/$E$7 -> 0.003658475 | AH39: 0.11124259 | AI39: 1 | AJ39: 1.0510692 | AK39: 1 | AL39: -0.17231287 | AM39: 1
A40: 30 | B40: Pat Kane | C40: 2013-14 & 2014-15 | D40: 26 | E40: 0 | F40: 0.18595313 | G40: -0.059127968 | H40: 0.093192471 | I40: -6.7544278e-05 | J40: 0.66165889 | K40: 19.407436 | L40: 4.1487194 | M40: 0.9546113 | N40: =(F40-Settings!$D$18)/Settings!$E$18 -> -0.022795423 | O40: =(G40-Settings!$D$19)/Settings!$E$19 -> -0.21866366 | P40: =(H40-Settings!$D$20)/Settings!$E$20 -> 0.3629991 | Q40: =(I40-Settings!$D$21)/Settings!$E$21 -> 0.035378512 | R40: =(J40-Settings!$D$22)/Settings!$E$22 -> 1.1133421 | S40: =(K40-Settings!$D$23)/Settings!$E$23 -> 1.441972 | T40: =(L40-Settings!$D$24)/Settings!$E$24 -> 1.9637595 | U40: =(M40-Settings!$D$25)/Settings!$E$25 -> 0.67977075 | V40: =Settings!$B$18*(N40-F$6)^2 -> 0.00096703007 | W40: =Settings!$B$19*(O40-G$6)^2 -> 0.1044612 | X40: =Settings!$B$20*(P40-H$6)^2 -> 0.72088698 | Y40: =Settings!$B$21*(Q40-I$6)^2 -> 0.16024507 | Z40: =Settings!$B$22*(R40-J$6)^2 -> 0.18450259 | AA40: =Settings!$B$23*(S40-K$6)^2 -> 0.081721336 | AB40: =Settings!$B$24*(T40-L$6)^2 -> 0.19144446 | AC40: =Settings!$B$25*(U40-M$6)^2 -> 0.74253662 | AD40: =SQRT(SUM(V40:AC40)) -> 1.4787715 | AE40: =AD40/Yardstick -> 0.58532459 | AF40: =EXP(-(AD40^2)/(2*Yardstick^2)) -> 0.84256671 | AG40: =AF40/$E$7 -> 0.0036376974 | AH40: 0.86161163 | AI40: 0 | AJ40: -0.90135466 | AK40: 0 | AL40: -1.8174484 | AM40: 0 | AN40: 0.041911659 | AO40: 1 | AP40: 0.12947769 | AQ40: 1
A41: 31 | B41: Nick Schmaltz | C41: 2021-22 & 2022-23 | D41: 26 | E41: 1 | F41: 0.28947321 | G41: -0.044967058 | H41: 0.023572329 | I41: -0.013784323 | J41: 0.62820308 | K41: 18.399868 | L41: 2.9363742 | M41: -0.4827146 | N41: =(F41-Settings!$D$18)/Settings!$E$18 -> 0.3476965 | O41: =(G41-Settings!$D$19)/Settings!$E$19 -> -0.15966751 | P41: =(H41-Settings!$D$20)/Settings!$E$20 -> -0.26777277 | Q41: =(I41-Settings!$D$21)/Settings!$E$21 -> -0.13330094 | R41: =(J41-Settings!$D$22)/Settings!$E$22 -> 1.0233277 | S41: =(K41-Settings!$D$23)/Settings!$E$23 -> 1.0920667 | T41: =(L41-Settings!$D$24)/Settings!$E$24 -> 1.1255989 | U41: =(M41-Settings!$D$25)/Settings!$E$25 -> -0.28957784 | V41: =Settings!$B$18*(N41-F$6)^2 -> 0.018114984 | W41: =Settings!$B$19*(O41-G$6)^2 -> 0.088102528 | X41: =Settings!$B$20*(P41-H$6)^2 -> 1.2794786 | Y41: =Settings!$B$21*(Q41-I$6)^2 -> 0.10554083 | Z41: =Settings!$B$22*(R41-J$6)^2 -> 0.15154045 | AA41: =Settings!$B$23*(S41-K$6)^2 -> 0.40420946 | AB41: =Settings!$B$24*(T41-L$6)^2 -> 0.16049393 | AC41: =Settings!$B$25*(U41-M$6)^2 -> 0.011587004 | AD41: =SQRT(SUM(V41:AC41)) -> 1.4896536 | AE41: =AD41/Yardstick -> 0.58963189 | AF41: =EXP(-(AD41^2)/(2*Yardstick^2)) -> 0.84043734 | AG41: =AF41/$E$7 -> 0.0036285041 | AH41: -0.75062644 | AI41: 1 | AJ41: -0.41650221 | AK41: 1 | AL41: 0.89900391 | AM41: 1
A42: 32 | B42: Nikita Kucherov | C42: 2018-19 & 2019-20 | D42: 26 | E42: 1 | F42: 0.27757789 | G42: -0.10104755 | H42: 0.062750279 | I42: -2.5796065e-05 | J42: 0.55859848 | K42: 18.709667 | L42: 4.3323277 | M42: 0.44432159 | N42: =(F42-Settings!$D$18)/Settings!$E$18 -> 0.30512391 | O42: =(G42-Settings!$D$19)/Settings!$E$19 -> -0.39330599 | P42: =(H42-Settings!$D$20)/Settings!$E$20 -> 0.087186984 | Q42: =(I42-Settings!$D$21)/Settings!$E$21 -> 0.035891902 | R42: =(J42-Settings!$D$22)/Settings!$E$22 -> 0.8360532 | S42: =(K42-Settings!$D$23)/Settings!$E$23 -> 1.1996528 | T42: =(L42-Settings!$D$24)/Settings!$E$24 -> 2.0906979 | U42: =(M42-Settings!$D$25)/Settings!$E$25 -> 0.33562569 | V42: =Settings!$B$18*(N42-F$6)^2 -> 0.013352467 | W42: =Settings!$B$19*(O42-G$6)^2 -> 0.16104731 | X42: =Settings!$B$20*(P42-H$6)^2 -> 0.94555701 | Y42: =Settings!$B$21*(Q42-I$6)^2 -> 0.16042894 | Z42: =Settings!$B$22*(R42-J$6)^2 -> 0.093348756 | AA42: =Settings!$B$23*(S42-K$6)^2 -> 0.27898324 | AB42: =Settings!$B$24*(T42-L$6)^2 -> 0.31864003 | AC42: =Settings!$B$25*(U42-M$6)^2 -> 0.26786896 | AD42: =SQRT(SUM(V42:AC42)) -> 1.4964046 | AE42: =AD42/Yardstick -> 0.59230407 | AF42: =EXP(-(AD42^2)/(2*Yardstick^2)) -> 0.83911119 | AG42: =AF42/$E$7 -> 0.0036227785 | AL42: -1.0162588 | AM42: 1 | AN42: 0.21845156 | AO42: 1 | AP42: 1.2378646 | AQ42: 1
A43: 33 | B43: Vladimir Tarasenko | C43: 2016-17 & 2017-18 | D43: 26 | E43: 0 | F43: 0.28499361 | G43: -0.060366493 | H43: 0.050236475 | I43: 0.0017739237 | J43: 0.6026295 | K43: 18.186008 | L43: 4.2088043 | M43: -0.64607956 | N43: =(F43-Settings!$D$18)/Settings!$E$18 -> 0.3316643 | O43: =(G43-Settings!$D$19)/Settings!$E$19 -> -0.22382352 | P43: =(H43-Settings!$D$20)/Settings!$E$20 -> -0.026190489 | Q43: =(I43-Settings!$D$21)/Settings!$E$21 -> 0.058023609 | R43: =(J43-Settings!$D$22)/Settings!$E$22 -> 0.95452073 | S43: =(K43-Settings!$D$23)/Settings!$E$23 -> 1.0177983 | T43: =(L43-Settings!$D$24)/Settings!$E$24 -> 2.0052995 | U43: =(M43-Settings!$D$25)/Settings!$E$25 -> -0.39975299 | V43: =Settings!$B$18*(N43-F$6)^2 -> 0.016236391 | W43: =Settings!$B$19*(O43-G$6)^2 -> 0.10595815 | X43: =Settings!$B$20*(P43-H$6)^2 -> 1.0467367 | Y43: =Settings!$B$21*(Q43-I$6)^2 -> 0.16845559 | Z43: =Settings!$B$22*(R43-J$6)^2 -> 0.12852983 | AA43: =Settings!$B$23*(S43-K$6)^2 -> 0.50416131 | AB43: =Settings!$B$24*(T43-L$6)^2 -> 0.22952112 | AC43: =Settings!$B$25*(U43-M$6)^2 -> 0.047444724 | AD43: =SQRT(SUM(V43:AC43)) -> 1.4990143 | AE43: =AD43/Yardstick -> 0.59333703 | AF43: =EXP(-(AD43^2)/(2*Yardstick^2)) -> 0.83859751 | AG43: =AF43/$E$7 -> 0.0036205608 | AH43: -0.34090221 | AI43: 1 | AN43: 0.61009029 | AO43: 1 | AP43: -0.031830951 | AQ43: 1
A44: 34 | B44: Kyle Palmieri | C44: 2015-16 & 2016-17 | D44: 26 | E44: 0 | F44: 0.060751456 | G44: 0.014122397 | H44: 0.1509146 | I44: -0.013956256 | J44: 0.76025529 | K44: 17.007407 | L44: 3.4113054 | M44: -0.86923474 | N44: =(F44-Settings!$D$18)/Settings!$E$18 -> -0.47088439 | O44: =(G44-Settings!$D$19)/Settings!$E$19 -> 0.086506694 | P44: =(H44-Settings!$D$20)/Settings!$E$20 -> 0.8859727 | Q44: =(I44-Settings!$D$21)/Settings!$E$21 -> -0.13541524 | R44: =(J44-Settings!$D$22)/Settings!$E$22 -> 1.3786203 | S44: =(K44-Settings!$D$23)/Settings!$E$23 -> 0.6084973 | T44: =(L44-Settings!$D$24)/Settings!$E$24 -> 1.4539448 | U44: =(M44-Settings!$D$25)/Settings!$E$25 -> -0.55025133 | V44: =Settings!$B$18*(N44-F$6)^2 -> 0.053586966 | W44: =Settings!$B$19*(O44-G$6)^2 -> 0.034867439 | X44: =Settings!$B$20*(P44-H$6)^2 -> 0.3784338 | Y44: =Settings!$B$21*(Q44-I$6)^2 -> 0.10492736 | Z44: =Settings!$B$22*(R44-J$6)^2 -> 0.30049439 | AA44: =Settings!$B$23*(S44-K$6)^2 -> 1.2529313 | AB44: =Settings!$B$24*(T44-L$6)^2 -> 0.0052230988 | AC44: =Settings!$B$25*(U44-M$6)^2 -> 0.135657 | AD44: =SQRT(SUM(V44:AC44)) -> 1.5053642 | AE44: =AD44/Yardstick -> 0.59585044 | AF44: =EXP(-(AD44^2)/(2*Yardstick^2)) -> 0.8373452 | AG44: =AF44/$E$7 -> 0.003615154 | AH44: -0.32370583 | AI44: 0 | AJ44: 0.20668168 | AK44: 1 | AL44: -0.059156486 | AM44: 1 | AN44: -1.8072679 | AO44: 1 | AP44: -1.2471102 | AQ44: 1
A45: 35 | B45: Tj Oshie | C45: 2011-12 & 2012-13 | D45: 26 | E45: 0 | F45: 0.083483844 | G45: 0.24781913 | H45: 0.24253555 | I45: 0.14561655 | J45: 0.28054494 | K45: 19.007576 | L45: 2.5850723 | M45: 0.068648562 | N45: =(F45-Settings!$D$18)/Settings!$E$18 -> -0.38952659 | O45: =(G45-Settings!$D$19)/Settings!$E$19 -> 1.0601171 | P45: =(H45-Settings!$D$20)/Settings!$E$20 -> 1.7160761 | Q45: =(I45-Settings!$D$21)/Settings!$E$21 -> 1.8269006 | R45: =(J45-Settings!$D$22)/Settings!$E$22 -> 0.087937053 | S45: =(K45-Settings!$D$23)/Settings!$E$23 -> 1.3031098 | T45: =(L45-Settings!$D$24)/Settings!$E$24 -> 0.8827247 | U45: =(M45-Settings!$D$25)/Settings!$E$25 -> 0.082267613 | V45: =Settings!$B$18*(N45-F$6)^2 -> 0.038065677 | W45: =Settings!$B$19*(O45-G$6)^2 -> 0.061843504 | X45: =Settings!$B$20*(P45-H$6)^2 -> 0.059504876 | Y45: =Settings!$B$21*(Q45-I$6)^2 -> 1.4436004 | Z45: =Settings!$B$22*(R45-J$6)^2 -> 0.00084317214 | AA45: =Settings!$B$23*(S45-K$6)^2 -> 0.18039699 | AB45: =Settings!$B$24*(T45-L$6)^2 -> 0.41408084 | AC45: =Settings!$B$25*(U45-M$6)^2 -> 0.069802966 | AD45: =SQRT(SUM(V45:AC45)) -> 1.506034 | AE45: =AD45/Yardstick -> 0.59611557 | AF45: =EXP(-(AD45^2)/(2*Yardstick^2)) -> 0.8372129 | AG45: =AF45/$E$7 -> 0.0036145829 | AH45: -0.10994078 | AI45: 0 | AJ45: 0.15899116 | AK45: 0 | AL45: 0.14971674 | AM45: 0 | AN45: 1.3086621 | AO45: 0 | AP45: -0.027335168 | AQ45: 0
A46: 36 | B46: Elias Lindholm | C46: 2019-20 & 2020-21 | D46: 26 | E46: 1 | F46: -0.01639235 | G46: 0.065167334 | H46: 0.045606034 | I46: -0.074542144 | J46: 0.79829214 | K46: 18.959524 | L46: 2.4807766 | M46: -0.017927494 | N46: =(F46-Settings!$D$18)/Settings!$E$18 -> -0.74697727 | O46: =(G46-Settings!$D$19)/Settings!$E$19 -> 0.29916641 | P46: =(H46-Settings!$D$20)/Settings!$E$20 -> -0.06814317 | Q46: =(I46-Settings!$D$21)/Settings!$E$21 -> -0.88045854 | R46: =(J46-Settings!$D$22)/Settings!$E$22 -> 1.4809603 | S46: =(K46-Settings!$D$23)/Settings!$E$23 -> 1.2864224 | T46: =(L46-Settings!$D$24)/Settings!$E$24 -> 0.81061938 | U46: =(M46-Settings!$D$25)/Settings!$E$25 -> 0.023879757 | V46: =Settings!$B$18*(N46-F$6)^2 -> 0.12599736 | W46: =Settings!$B$19*(O46-G$6)^2 -> 0.0083949454 | X46: =Settings!$B$20*(P46-H$6)^2 -> 1.0854792 | Y46: =Settings!$B$21*(Q46-I$6)^2 -> 8.5906163e-05 | Z46: =Settings!$B$22*(R46-J$6)^2 -> 0.3527665 | AA46: =Settings!$B$23*(S46-K$6)^2 -> 0.19485074 | AB46: =Settings!$B$24*(T46-L$6)^2 -> 0.51207829 | AC46: =Settings!$B$25*(U46-M$6)^2 -> 0.042359671 | AD46: =SQRT(SUM(V46:AC46)) -> 1.5238151 | AE46: =AD46/Yardstick -> 0.60315366 | AF46: =EXP(-(AD46^2)/(2*Yardstick^2)) -> 0.83368707 | AG46: =AF46/$E$7 -> 0.0035993604 | AH46: 0.81149227 | AI46: 1 | AJ46: -0.81810385 | AK46: 1 | AL46: -2.7515088 | AM46: 1 | AN46: 0.25346961 | AO46: 1 | AP46: 0.21864086 | AQ46: 1
A47: 37 | B47: Tomas Hertl | C47: 2018-19 & 2019-20 | D47: 26 | E47: 1 | F47: 0.31634318 | G47: -0.039159319 | H47: 0.1026126 | I47: 0.033236868 | J47: 0.50864803 | K47: 17.953733 | L47: 2.7582093 | M47: -1.0704 | N47: =(F47-Settings!$D$18)/Settings!$E$18 -> 0.44386246 | O47: =(G47-Settings!$D$19)/Settings!$E$19 -> -0.13547173 | P47: =(H47-Settings!$D$20)/Settings!$E$20 -> 0.44834726 | Q47: =(I47-Settings!$D$21)/Settings!$E$21 -> 0.44493311 | R47: =(J47-Settings!$D$22)/Settings!$E$22 -> 0.70165917 | S47: =(K47-Settings!$D$23)/Settings!$E$23 -> 0.93713453 | T47: =(L47-Settings!$D$24)/Settings!$E$24 -> 1.0024238 | U47: =(M47-Settings!$D$25)/Settings!$E$25 -> -0.68591945 | V47: =Settings!$B$18*(N47-F$6)^2 -> 0.031541279 | W47: =Settings!$B$19*(O47-G$6)^2 -> 0.08179601 | X47: =Settings!$B$20*(P47-H$6)^2 -> 0.65752925 | Y47: =Settings!$B$21*(Q47-I$6)^2 -> 0.34043095 | Z47: =Settings!$B$22*(R47-J$6)^2 -> 0.060234632 | AA47: =Settings!$B$23*(S47-K$6)^2 -> 0.62521741 | AB47: =Settings!$B$24*(T47-L$6)^2 -> 0.27435813 | AC47: =Settings!$B$25*(U47-M$6)^2 -> 0.25400043 | AD47: =SQRT(SUM(V47:AC47)) -> 1.5248305 | AE47: =AD47/Yardstick -> 0.60355556 | AF47: =EXP(-(AD47^2)/(2*Yardstick^2)) -> 0.83348493 | AG47: =AF47/$E$7 -> 0.0035984877 | AH47: 0.082722107 | AI47: 1 | AJ47: 0.00791207 | AK47: 1 | AL47: -1.8664488 | AM47: 1 | AN47: -0.070114669 | AO47: 1 | AP47: 1.4083861 | AQ47: 1
A48: 38 | B48: James Neal | C48: 2012-13 & 2013-14 | D48: 26 | E48: 0 | F48: 0.23067514 | G48: -0.029627547 | H48: 0.14822067 | I48: 2.6655346e-05 | J48: 0.59144999 | K48: 17.76229 | L48: 4.8821971 | M48: -0.27546794 | N48: =(F48-Settings!$D$18)/Settings!$E$18 -> 0.13726187 | O48: =(G48-Settings!$D$19)/Settings!$E$19 -> -0.095761152 | P48: =(H48-Settings!$D$20)/Settings!$E$20 -> 0.86156517 | Q48: =(I48-Settings!$D$21)/Settings!$E$21 -> 0.036536913 | R48: =(J48-Settings!$D$22)/Settings!$E$22 -> 0.92444173 | S48: =(K48-Settings!$D$23)/Settings!$E$23 -> 0.87065051 | T48: =(L48-Settings!$D$24)/Settings!$E$24 -> 2.4708527 | U48: =(M48-Settings!$D$25)/Settings!$E$25 -> -0.14980839 | V48: =Settings!$B$18*(N48-F$6)^2 -> 0.0016388484 | W48: =Settings!$B$19*(O48-G$6)^2 -> 0.071953185 | X48: =Settings!$B$20*(P48-H$6)^2 -> 0.39198256 | Y48: =Settings!$B$21*(Q48-I$6)^2 -> 0.1606601 | Z48: =Settings!$B$22*(R48-J$6)^2 -> 0.1190656 | AA48: =Settings!$B$23*(S48-K$6)^2 -> 0.73477628 | AB48: =Settings!$B$24*(T48-L$6)^2 -> 0.8923388 | AC48: =Settings!$B$25*(U48-M$6)^2 -> 0.0010321126 | AD48: =SQRT(SUM(V48:AC48)) -> 1.5405997 | AE48: =AD48/Yardstick -> 0.6097973 | AF48: =EXP(-(AD48^2)/(2*Yardstick^2)) -> 0.83033473 | AG48: =AF48/$E$7 -> 0.0035848871 | AH48: -1.3018517 | AI48: 0 | AJ48: -0.92261877 | AK48: 0 | AL48: -0.25398292 | AM48: 0 | AN48: -0.13645239 | AO48: 0 | AP48: -1.6321075 | AQ48: 1
A49: 39 | B49: Jesper Bratt | C49: 2023-24 & 2024-25 | D49: 26 | E49: 1 | F49: 0.59581786 | G49: 0.0050105606 | H49: 0.23816929 | I49: -0.013819153 | J49: 0.14718313 | K49: 18.297546 | L49: 3.016154 | M49: -1.9243385 | N49: =(F49-Settings!$D$18)/Settings!$E$18 -> 1.4440849 | O49: =(G49-Settings!$D$19)/Settings!$E$19 -> 0.048545621 | P49: =(H49-Settings!$D$20)/Settings!$E$20 -> 1.676517 | Q49: =(I49-Settings!$D$21)/Settings!$E$21 -> -0.13372925 | R49: =(J49-Settings!$D$22)/Settings!$E$22 -> -0.27087917 | S49: =(K49-Settings!$D$23)/Settings!$E$23 -> 1.0565328 | T49: =(L49-Settings!$D$24)/Settings!$E$24 -> 1.1807551 | U49: =(M49-Settings!$D$25)/Settings!$E$25 -> -1.2618251 | V49: =Settings!$B$18*(N49-F$6)^2 -> 0.39051467 | W49: =Settings!$B$19*(O49-G$6)^2 -> 0.04149571 | X49: =Settings!$B$20*(P49-H$6)^2 -> 0.068448986 | Y49: =Settings!$B$21*(Q49-I$6)^2 -> 0.10541641 | Z49: =Settings!$B$22*(R49-J$6)^2 -> 0.035912115 | AA49: =Settings!$B$23*(S49-K$6)^2 -> 0.45065533 | AB49: =Settings!$B$24*(T49-L$6)^2 -> 0.11934314 | AC49: =Settings!$B$25*(U49-M$6)^2 -> 1.1661628 | AD49: =SQRT(SUM(V49:AC49)) -> 1.54206 | AE49: =AD49/Yardstick -> 0.61037532 | AF49: =EXP(-(AD49^2)/(2*Yardstick^2)) -> 0.83004197 | AG49: =AF49/$E$7 -> 0.0035836231 | AH49: -0.27830677 | AI49: 1
A50: 40 | B50: Jakub Voracek | C50: 2014-15 & 2015-16 | D50: 26 | E50: 0 | F50: 0.60470031 | G50: 0.0096105743 | H50: 0.36062167 | I50: -0.00015963117 | J50: -0.024907811 | K50: 18.068495 | L50: 2.723213 | M50: -1.5637981 | N50: =(F50-Settings!$D$18)/Settings!$E$18 -> 1.4758746 | O50: =(G50-Settings!$D$19)/Settings!$E$19 -> 0.067709864 | P50: =(H50-Settings!$D$20)/Settings!$E$20 -> 2.7859591 | Q50: =(I50-Settings!$D$21)/Settings!$E$21 -> 0.034246091 | R50: =(J50-Settings!$D$22)/Settings!$E$22 -> -0.73389795 | S50: =(K50-Settings!$D$23)/Settings!$E$23 -> 0.97698848 | T50: =(L50-Settings!$D$24)/Settings!$E$24 -> 0.97822893 | U50: =(M50-Settings!$D$25)/Settings!$E$25 -> -1.0186726 | V50: =Settings!$B$18*(N50-F$6)^2 -> 0.40848527 | W50: =Settings!$B$19*(O50-G$6)^2 -> 0.038077453 | X50: =Settings!$B$20*(P50-H$6)^2 -> 0.055004333 | Y50: =Settings!$B$21*(Q50-I$6)^2 -> 0.15983987 | Z50: =Settings!$B$22*(R50-J$6)^2 -> 0.15727031 | AA50: =Settings!$B$23*(S50-K$6)^2 -> 0.56378015 | AB50: =Settings!$B$24*(T50-L$6)^2 -> 0.30028965 | AC50: =Settings!$B$25*(U50-M$6)^2 -> 0.70012996 | AD50: =SQRT(SUM(V50:AC50)) -> 1.543657 | AE50: =AD50/Yardstick -> 0.61100744 | AF50: =EXP(-(AD50^2)/(2*Yardstick^2)) -> 0.82972161 | AG50: =AF50/$E$7 -> 0.00358224 | AH50: -1.1069938 | AI50: 0 | AJ50: -0.58208482 | AK50: 0 | AL50: -0.082805697 | AM50: 1 | AN50: 0.056177373 | AO50: 1 | AP50: -0.29674905 | AQ50: 1
A51: 41 | B51: Dustin Brown | C51: 2009-10 & 2010-11 | D51: 26 | E51: 0 | F51: 0.3651786 | G51: -0.097181347 | H51: 0.12942859 | I51: 0.10428825 | J51: 0.30392322 | K51: 18.925358 | L51: 3.1820474 | M51: 0.70888193 | N51: =(F51-Settings!$D$18)/Settings!$E$18 -> 0.61864137 | O51: =(G51-Settings!$D$19)/Settings!$E$19 -> -0.37719889 | P51: =(H51-Settings!$D$20)/Settings!$E$20 -> 0.6913053 | Q51: =(I51-Settings!$D$21)/Settings!$E$21 -> 1.3186738 | R51: =(J51-Settings!$D$22)/Settings!$E$22 -> 0.15083741 | S51: =(K51-Settings!$D$23)/Settings!$E$23 -> 1.2745574 | T51: =(L51-Settings!$D$24)/Settings!$E$24 -> 1.2954462 | U51: =(M51-Settings!$D$25)/Settings!$E$25 -> 0.51404813 | V51: =Settings!$B$18*(N51-F$6)^2 -> 0.065414276 | W51: =Settings!$B$19*(O51-G$6)^2 -> 0.15531772 | X51: =Settings!$B$20*(P51-H$6)^2 -> 0.49312365 | Y51: =Settings!$B$21*(Q51-I$6)^2 -> 0.94909161 | Z51: =Settings!$B$22*(R51-J$6)^2 -> 8.2361038e-07 | AA51: =Settings!$B$23*(S51-K$6)^2 -> 0.20546643 | AB51: =Settings!$B$24*(T51-L$6)^2 -> 0.053254617 | AC51: =Settings!$B$25*(U51-M$6)^2 -> 0.48439237 | AD51: =SQRT(SUM(V51:AC51)) -> 1.5511484 | AE51: =AD51/Yardstick -> 0.61397268 | AF51: =EXP(-(AD51^2)/(2*Yardstick^2)) -> 0.82821605 | AG51: =AF51/$E$7 -> 0.0035757399 | AH51: 0.28280114 | AI51: 0 | AJ51: -0.035361212 | AK51: 0 | AL51: -1.2431779 | AM51: 0 | AN51: -1.2895049 | AO51: 0 | AP51: -0.3301299 | AQ51: 0
A52: 42 | B52: Troy Terry | C52: 2022-23 & 2023-24 | D52: 26 | E52: 1 | F52: 0.4222512 | G52: -0.14626445 | H52: 0.329998 | I52: -0.00035384473 | J52: 0.1011325 | K52: 18.185502 | L52: 1.8934028 | M52: 0.042678109 | N52: =(F52-Settings!$D$18)/Settings!$E$18 -> 0.82290064 | O52: =(G52-Settings!$D$19)/Settings!$E$19 -> -0.58168537 | P52: =(H52-Settings!$D$20)/Settings!$E$20 -> 2.5085028 | Q52: =(I52-Settings!$D$21)/Settings!$E$21 -> 0.031857787 | R52: =(J52-Settings!$D$22)/Settings!$E$22 -> -0.39478055 | S52: =(K52-Settings!$D$23)/Settings!$E$23 -> 1.0176226 | T52: =(L52-Settings!$D$24)/Settings!$E$24 -> 0.40453576 | U52: =(M52-Settings!$D$25)/Settings!$E$25 -> 0.06475285 | V52: =Settings!$B$18*(N52-F$6)^2 -> 0.12048512 | W52: =Settings!$B$19*(O52-G$6)^2 -> 0.23576155 | X52: =Settings!$B$20*(P52-H$6)^2 -> 0.012198711 | Y52: =Settings!$B$21*(Q52-I$6)^2 -> 0.15898698 | Z52: =Settings!$B$22*(R52-J$6)^2 -> 0.059983506 | AA52: =Settings!$B$23*(S52-K$6)^2 -> 0.50441085 | AB52: =Settings!$B$24*(T52-L$6)^2 -> 1.2581662 | AC52: =Settings!$B$25*(U52-M$6)^2 -> 0.060854844 | AD52: =SQRT(SUM(V52:AC52)) -> 1.5526905 | AE52: =AD52/Yardstick -> 0.61458305 | AF52: =EXP(-(AD52^2)/(2*Yardstick^2)) -> 0.82790558 | AG52: =AF52/$E$7 -> 0.0035743995 | AH52: 0.54434219 | AI52: 1 | AJ52: 0.18183427 | AK52: 1
A53: 43 | B53: Sebastian Aho | C53: 2022-23 & 2023-24 | D53: 26 | E53: 1 | F53: 0.35704223 | G53: 0.043597225 | H53: 0.12403428 | I53: 0.073989812 | J53: 0.40133646 | K53: 18.919935 | L53: 4.4293812 | M53: -1.4640481 | N53: =(F53-Settings!$D$18)/Settings!$E$18 -> 0.58952181 | O53: =(G53-Settings!$D$19)/Settings!$E$19 -> 0.20930258 | P53: =(H53-Settings!$D$20)/Settings!$E$20 -> 0.64243178 | Q53: =(I53-Settings!$D$21)/Settings!$E$21 -> 0.94608459 | R53: =(J53-Settings!$D$22)/Settings!$E$22 -> 0.41293233 | S53: =(K53-Settings!$D$23)/Settings!$E$23 -> 1.272674 | T53: =(L53-Settings!$D$24)/Settings!$E$24 -> 2.1577963 | U53: =(M53-Settings!$D$25)/Settings!$E$25 -> -0.95140007 | V53: =Settings!$B$18*(N53-F$6)^2 -> 0.058922457 | W53: =Settings!$B$19*(O53-G$6)^2 -> 0.017374472 | X53: =Settings!$B$20*(P53-H$6)^2 -> 0.52429842 | Y53: =Settings!$B$21*(Q53-I$6)^2 -> 0.65219574 | Z53: =Settings!$B$22*(R53-J$6)^2 -> 0.013526825 | AA53: =Settings!$B$23*(S53-K$6)^2 -> 0.20717737 | AB53: =Settings!$B$24*(T53-L$6)^2 -> 0.39889392 | AC53: =Settings!$B$25*(U53-M$6)^2 -> 0.59207665 | AD53: =SQRT(SUM(V53:AC53)) -> 1.5698617 | AE53: =AD53/Yardstick -> 0.62137973 | AF53: =EXP(-(AD53^2)/(2*Yardstick^2)) -> 0.82443548 | AG53: =AF53/$E$7 -> 0.0035594177 | AH53: -0.79984654 | AI53: 1 | AJ53: -0.43638204 | AK53: 1
A54: 44 | B54: Bo Horvat | C54: 2020-21 & 2021-22 | D54: 26 | E54: 1 | F54: 0.14458868 | G54: -0.072747592 | H54: 0.078499966 | I54: -0.012183266 | J54: 0.69198049 | K54: 18.769577 | L54: 2.2202995 | M54: 0.28120437 | N54: =(F54-Settings!$D$18)/Settings!$E$18 -> -0.17083619 | O54: =(G54-Settings!$D$19)/Settings!$E$19 -> -0.27540475 | P54: =(H54-Settings!$D$20)/Settings!$E$20 -> 0.22988218 | Q54: =(I54-Settings!$D$21)/Settings!$E$21 -> -0.11361224 | R54: =(J54-Settings!$D$22)/Settings!$E$22 -> 1.1949238 | S54: =(K54-Settings!$D$23)/Settings!$E$23 -> 1.2204582 | T54: =(L54-Settings!$D$24)/Settings!$E$24 -> 0.63053729 | U54: =(M54-Settings!$D$25)/Settings!$E$25 -> 0.22561762 | V54: =Settings!$B$18*(N54-F$6)^2 -> 0.0094678642 | W54: =Settings!$B$19*(O54-G$6)^2 -> 0.12150799 | X54: =Settings!$B$20*(P54-H$6)^2 -> 0.82552185 | Y54: =Settings!$B$21*(Q54-I$6)^2 -> 0.11133936 | Z54: =Settings!$B$22*(R54-J$6)^2 -> 0.21717659 | AA54: =Settings!$B$23*(S54-K$6)^2 -> 0.25743777 | AB54: =Settings!$B$24*(T54-L$6)^2 -> 0.80224007 | AC54: =Settings!$B$25*(U54-M$6)^2 -> 0.16609905 | AD54: =SQRT(SUM(V54:AC54)) -> 1.5845474 | AE54: =AD54/Yardstick -> 0.6271926 | AF54: =EXP(-(AD54^2)/(2*Yardstick^2)) -> 0.82144912 | AG54: =AF54/$E$7 -> 0.0035465243 | AH54: 0.57381556 | AI54: 1 | AJ54: 0.53834939 | AK54: 1 | AL54: -0.60539134 | AM54: 1 | AN54: -0.081688051 | AO54: 1
A55: 45 | B55: Alex Ovechkin | C55: 2010-11 & 2011-12 | D55: 26 | E55: 0 | F55: 0.2731248 | G55: -0.062352711 | H55: 0.22017086 | I55: -0.00023775535 | J55: 0.44411388 | K55: 20.069639 | L55: 4.4621035 | M55: 1.6289522 | N55: =(F55-Settings!$D$18)/Settings!$E$18 -> 0.28918655 | O55: =(G55-Settings!$D$19)/Settings!$E$19 -> -0.23209835 | P55: =(H55-Settings!$D$20)/Settings!$E$20 -> 1.5134477 | Q55: =(I55-Settings!$D$21)/Settings!$E$21 -> 0.033285374 | R55: =(J55-Settings!$D$22)/Settings!$E$22 -> 0.52802699 | S55: =(K55-Settings!$D$23)/Settings!$E$23 -> 1.6719399 | T55: =(L55-Settings!$D$24)/Settings!$E$24 -> 2.180419 | U55: =(M55-Settings!$D$25)/Settings!$E$25 -> 1.1345537 | V55: =Settings!$B$18*(N55-F$6)^2 -> 0.011756083 | W55: =Settings!$B$19*(O55-G$6)^2 -> 0.10838104 | X55: =Settings!$B$20*(P55-H$6)^2 -> 0.11192663 | Y55: =Settings!$B$21*(Q55-I$6)^2 -> 0.15949651 | Z55: =Settings!$B$22*(R55-J$6)^2 -> 0.028149047 | AA55: =Settings!$B$23*(S55-K$6)^2 -> 0.0031249789 | AB55: =Settings!$B$24*(T55-L$6)^2 -> 0.4279818 | AC55: =Settings!$B$25*(U55-M$6)^2 -> 1.7331424 | AD55: =SQRT(SUM(V55:AC55)) -> 1.6074696 | AE55: =AD55/Yardstick -> 0.6362656 | AF55: =EXP(-(AD55^2)/(2*Yardstick^2)) -> 0.81675431 | AG55: =AF55/$E$7 -> 0.0035262549 | AH55: 1.2832466 | AI55: 0 | AJ55: -0.21291731 | AK55: 0 | AL55: -0.51162167 | AM55: 0 | AN55: 0.86130728 | AO55: 0 | AP55: -1.480052 | AQ55: 0
A56: 46 | B56: Kevin Hayes | C56: 2017-18 & 2018-19 | D56: 26 | E56: 1 | F56: 0.22001624 | G56: 0.11710243 | H56: 0.06870096 | I56: -0.082817254 | J56: 0.51136312 | K56: 17.329705 | L56: 2.3983798 | M56: -0.10453207 | N56: =(F56-Settings!$D$18)/Settings!$E$18 -> 0.099114327 | O56: =(G56-Settings!$D$19)/Settings!$E$19 -> 0.51553464 | P56: =(H56-Settings!$D$20)/Settings!$E$20 -> 0.1411013 | Q56: =(I56-Settings!$D$21)/Settings!$E$21 -> -0.98222012 | R56: =(J56-Settings!$D$22)/Settings!$E$22 -> 0.70896424 | S56: =(K56-Settings!$D$23)/Settings!$E$23 -> 0.72042392 | T56: =(L56-Settings!$D$24)/Settings!$E$24 -> 0.75365396 | U56: =(M56-Settings!$D$25)/Settings!$E$25 -> -0.034527336 | V56: =Settings!$B$18*(N56-F$6)^2 -> 0.00054861774 | W56: =Settings!$B$19*(O56-G$6)^2 -> 2.6408091e-05 | X56: =Settings!$B$20*(P56-H$6)^2 -> 0.899247 | Y56: =Settings!$B$21*(Q56-I$6)^2 -> 0.0030005985 | Z56: =Settings!$B$22*(R56-J$6)^2 -> 0.061848892 | AA56: =Settings!$B$23*(S56-K$6)^2 -> 1.01489 | AB56: =Settings!$B$24*(T56-L$6)^2 -> 0.59685186 | AC56: =Settings!$B$25*(U56-M$6)^2 -> 0.021728989 | AD56: =SQRT(SUM(V56:AC56)) -> 1.6118754 | AE56: =AD56/Yardstick -> 0.63800952 | AF56: =EXP(-(AD56^2)/(2*Yardstick^2)) -> 0.8158473 | AG56: =AF56/$E$7 -> 0.003522339 | AH56: -0.63297627 | AI56: 1 | AJ56: -1.0129573 | AK56: 1 | AL56: -0.39758435 | AM56: 1 | AN56: 0.14956503 | AO56: 1 | AP56: 0.53371929 | AQ56: 1
A57: 47 | B57: Andrew Ladd | C57: 2010-11 & 2011-12 | D57: 26 | E57: 0 | F57: 0.40971493 | G57: -0.10067986 | H57: 0.035772804 | I57: 0.015800829 | J57: 0.43803157 | K57: 19.328732 | L57: 2.2417896 | M57: -0.68298916 | N57: =(F57-Settings!$D$18)/Settings!$E$18 -> 0.77803414 | O57: =(G57-Settings!$D$19)/Settings!$E$19 -> -0.39177414 | P57: =(H57-Settings!$D$20)/Settings!$E$20 -> -0.15723413 | Q57: =(I57-Settings!$D$21)/Settings!$E$21 -> 0.23051677 | R57: =(J57-Settings!$D$22)/Settings!$E$22 -> 0.51166226 | S57: =(K57-Settings!$D$23)/Settings!$E$23 -> 1.41464 | T57: =(L57-Settings!$D$24)/Settings!$E$24 -> 0.64539461 | U57: =(M57-Settings!$D$25)/Settings!$E$25 -> -0.42464524 | V57: =Settings!$B$18*(N57-F$6)^2 -> 0.10695828 | W57: =Settings!$B$19*(O57-G$6)^2 -> 0.16049794 | X57: =Settings!$B$20*(P57-H$6)^2 -> 1.1700879 | Y57: =Settings!$B$21*(Q57-I$6)^2 -> 0.2377291 | Z57: =Settings!$B$22*(R57-J$6)^2 -> 0.025746849 | AA57: =Settings!$B$23*(S57-K$6)^2 -> 0.098095152 | AB57: =Settings!$B$24*(T57-L$6)^2 -> 0.77584605 | AC57: =Settings!$B$25*(U57-M$6)^2 -> 0.058908312 | AD57: =SQRT(SUM(V57:AC57)) -> 1.6229201 | AE57: =AD57/Yardstick -> 0.64238119 | AF57: =EXP(-(AD57^2)/(2*Yardstick^2)) -> 0.81356716 | AG57: =AF57/$E$7 -> 0.0035124948 | AH57: 0.14176865 | AI57: 0 | AJ57: 0.35878645 | AK57: 0 | AL57: -0.78970542 | AM57: 0 | AN57: -0.58398629 | AO57: 0 | AP57: 0.15472317 | AQ57: 0
A58: 48 | B58: Timo Meier | C58: 2021-22 & 2022-23 | D58: 26 | E58: 1 | F58: 0.48489915 | G58: 0.068335101 | H58: 0.043609661 | I58: 0.0013231344 | J58: 0.40183295 | K58: 18.533978 | L58: 4.5484657 | M58: 0.48741045 | N58: =(F58-Settings!$D$18)/Settings!$E$18 -> 1.0471138 | O58: =(G58-Settings!$D$19)/Settings!$E$19 -> 0.31236373 | P58: =(H58-Settings!$D$20)/Settings!$E$20 -> -0.086230697 | Q58: =(I58-Settings!$D$21)/Settings!$E$21 -> 0.052480115 | R58: =(J58-Settings!$D$22)/Settings!$E$22 -> 0.41426816 | S58: =(K58-Settings!$D$23)/Settings!$E$23 -> 1.1386403 | T58: =(L58-Settings!$D$24)/Settings!$E$24 -> 2.240126 | U58: =(M58-Settings!$D$25)/Settings!$E$25 -> 0.3646853 | V58: =Settings!$B$18*(N58-F$6)^2 -> 0.20014961 | W58: =Settings!$B$19*(O58-G$6)^2 -> 0.0073482465 | X58: =Settings!$B$20*(P58-H$6)^2 -> 1.1023998 | Y58: =Settings!$B$21*(Q58-I$6)^2 -> 0.16642671 | Z58: =Settings!$B$22*(R58-J$6)^2 -> 0.013666144 | AA58: =Settings!$B$23*(S58-K$6)^2 -> 0.34715794 | AB58: =Settings!$B$24*(T58-L$6)^2 -> 0.50966766 | AC58: =Settings!$B$25*(U58-M$6)^2 -> 0.29879363 | AD58: =SQRT(SUM(V58:AC58)) -> 1.6265331 | AE58: =AD58/Yardstick -> 0.64381127 | AF58: =EXP(-(AD58^2)/(2*Yardstick^2)) -> 0.81281928 | AG58: =AF58/$E$7 -> 0.0035092659 | AH58: -0.99592441 | AI58: 1 | AJ58: -1.702001 | AK58: 1 | AL58: -0.92314505 | AM58: 1
A59: 49 | B59: Brady Tkachuk | C59: 2024-25 & 2025-26 | D59: 26 | E59: 1 | F59: 0.70294674 | G59: 0.097598778 | H59: 0.16901355 | I59: 0.00020453621 | J59: 0.030236395 | K59: 16.833965 | L59: 3.2048274 | M59: -0.5195353 | N59: =(F59-Settings!$D$18)/Settings!$E$18 -> 1.8274925 | O59: =(G59-Settings!$D$19)/Settings!$E$19 -> 0.43427994 | P59: =(H59-Settings!$D$20)/Settings!$E$20 -> 1.0499527 | Q59: =(I59-Settings!$D$21)/Settings!$E$21 -> 0.038724369 | R59: =(J59-Settings!$D$22)/Settings!$E$22 -> -0.58552986 | S59: =(K59-Settings!$D$23)/Settings!$E$23 -> 0.54826462 | T59: =(L59-Settings!$D$24)/Settings!$E$24 -> 1.3111953 | U59: =(M59-Settings!$D$25)/Settings!$E$25 -> -0.31441013 | V59: =Settings!$B$18*(N59-F$6)^2 -> 0.63421602 | W59: =Settings!$B$19*(O59-G$6)^2 -> 0.0009733981 | X59: =Settings!$B$20*(P59-H$6)^2 -> 0.29358588 | Y59: =Settings!$B$21*(Q59-I$6)^2 -> 0.16144528 | Z59: =Settings!$B$22*(R59-J$6)^2 -> 0.1090459 | AA59: =Settings!$B$23*(S59-K$6)^2 -> 1.3914015 | AB59: =Settings!$B$24*(T59-L$6)^2 -> 0.046233817 | AC59: =Settings!$B$25*(U59-M$6)^2 -> 0.017549689 | AD59: =SQRT(SUM(V59:AC59)) -> 1.6292487 | AE59: =AD59/Yardstick -> 0.64488619 | AF59: =EXP(-(AD59^2)/(2*Yardstick^2)) -> 0.8122565 | AG59: =AF59/$E$7 -> 0.0035068361
A60: 50 | B60: Tyler Seguin | C60: 2016-17 & 2017-18 | D60: 26 | E60: 0 | F60: 0.26285906 | G60: -0.17727655 | H60: 0.2080719 | I60: -0.0035765175 | J60: 0.34821597 | K60: 18.939126 | L60: 2.2009096 | M60: 1.1926799 | N60: =(F60-Settings!$D$18)/Settings!$E$18 -> 0.25244614 | O60: =(G60-Settings!$D$19)/Settings!$E$19 -> -0.7108857 | P60: =(H60-Settings!$D$20)/Settings!$E$20 -> 1.4038288 | Q60: =(I60-Settings!$D$21)/Settings!$E$21 -> -0.0077724112 | R60: =(J60-Settings!$D$22)/Settings!$E$22 -> 0.27000915 | S60: =(K60-Settings!$D$23)/Settings!$E$23 -> 1.2793387 | T60: =(L60-Settings!$D$24)/Settings!$E$24 -> 0.61713201 | U60: =(M60-Settings!$D$25)/Settings!$E$25 -> 0.84032688 | V60: =Settings!$B$18*(N60-F$6)^2 -> 0.0084630177 | W60: =Settings!$B$19*(O60-G$6)^2 -> 0.29521072 | X60: =Settings!$B$20*(P60-H$6)^2 -> 0.14713164 | Y60: =Settings!$B$21*(Q60-I$6)^2 -> 0.14516751 | Z60: =Settings!$B$22*(R60-J$6)^2 -> 0.0027444702 | AA60: =Settings!$B$23*(S60-K$6)^2 -> 0.20115466 | AB60: =Settings!$B$24*(T60-L$6)^2 -> 0.82643341 | AC60: =Settings!$B$25*(U60-M$6)^2 -> 1.0450191 | AD60: =SQRT(SUM(V60:AC60)) -> 1.6344187 | AE60: =AD60/Yardstick -> 0.64693256 | AF60: =EXP(-(AD60^2)/(2*Yardstick^2)) -> 0.81118359 | AG60: =AF60/$E$7 -> 0.003502204 | AH60: 0.61151415 | AI60: 1 | AJ60: -1.1703456 | AK60: 1 | AP60: 0.30651661 | AQ60: 1
A61: 51 | B61: Filip Forsberg | C61: 2019-20 & 2020-21 | D61: 26 | E61: 1 | F61: 0.30850758 | G61: -0.0126119 | H61: 0.27071776 | I61: 0.004196641 | J61: 0.40396612 | K61: 17.093137 | L61: 2.263266 | M61: 0.71959549 | N61: =(F61-Settings!$D$18)/Settings!$E$18 -> 0.41581932 | O61: =(G61-Settings!$D$19)/Settings!$E$19 -> -0.024871797 | P61: =(H61-Settings!$D$20)/Settings!$E$20 -> 1.9714124 | Q61: =(I61-Settings!$D$21)/Settings!$E$21 -> 0.08781651 | R61: =(J61-Settings!$D$22)/Settings!$E$22 -> 0.42000756 | S61: =(K61-Settings!$D$23)/Settings!$E$23 -> 0.6382693 | T61: =(L61-Settings!$D$24)/Settings!$E$24 -> 0.66024238 | U61: =(M61-Settings!$D$25)/Settings!$E$25 -> 0.52127347 | V61: =Settings!$B$18*(N61-F$6)^2 -> 0.027243935 | W61: =Settings!$B$19*(O61-G$6)^2 -> 0.055950332 | X61: =Settings!$B$20*(P61-H$6)^2 -> 0.016834117 | Y61: =Settings!$B$21*(Q61-I$6)^2 -> 0.17957017 | Z61: =Settings!$B$22*(R61-J$6)^2 -> 0.014272846 | AA61: =Settings!$B$23*(S61-K$6)^2 -> 1.1871674 | AB61: =Settings!$B$24*(T61-L$6)^2 -> 0.74991003 | AC61: =Settings!$B$25*(U61-M$6)^2 -> 0.49450201 | AD61: =SQRT(SUM(V61:AC61)) -> 1.650894 | AE61: =AD61/Yardstick -> 0.65345376 | AF61: =EXP(-(AD61^2)/(2*Yardstick^2)) -> 0.80775143 | AG61: =AF61/$E$7 -> 0.0034873859 | AH61: 2.36998 | AI61: 1 | AJ61: 0.24861291 | AK61: 1 | AL61: -0.49204349 | AM61: 1 | AN61: -0.17475394 | AO61: 1 | AP61: -0.91180163 | AQ61: 1
A62: 52 | B62: Ryan Nugent Hopkins | C62: 2018-19 & 2019-20 | D62: 26 | E62: 1 | F62: 0.11592733 | G62: -0.15953704 | H62: 0.17685501 | I62: -0.01596735 | J62: 0.53171327 | K62: 19.608617 | L62: 1.8521719 | M62: 0.88367312 | N62: =(F62-Settings!$D$18)/Settings!$E$18 -> -0.27341338 | O62: =(G62-Settings!$D$19)/Settings!$E$19 -> -0.63698064 | P62: =(H62-Settings!$D$20)/Settings!$E$20 -> 1.1209978 | Q62: =(I62-Settings!$D$21)/Settings!$E$21 -> -0.16014629 | R62: =(J62-Settings!$D$22)/Settings!$E$22 -> 0.76371729 | S62: =(K62-Settings!$D$23)/Settings!$E$23 -> 1.5118375 | T62: =(L62-Settings!$D$24)/Settings!$E$24 -> 0.37603054 | U62: =(M62-Settings!$D$25)/Settings!$E$25 -> 0.63192925 | V62: =Settings!$B$18*(N62-F$6)^2 -> 0.020499615 | W62: =Settings!$B$19*(O62-G$6)^2 -> 0.26038733 | X62: =Settings!$B$20*(P62-H$6)^2 -> 0.26016458 | Y62: =Settings!$B$21*(Q62-I$6)^2 -> 0.097884431 | Z62: =Settings!$B$22*(R62-J$6)^2 -> 0.074627685 | AA62: =Settings!$B$23*(S62-K$6)^2 -> 0.046657705 | AB62: =Settings!$B$24*(T62-L$6)^2 -> 1.3229262 | AC62: =Settings!$B$25*(U62-M$6)^2 -> 0.66237485 | AD62: =SQRT(SUM(V62:AC62)) -> 1.6569618 | AE62: =AD62/Yardstick -> 0.65585552 | AF62: =EXP(-(AD62^2)/(2*Yardstick^2)) -> 0.80648238 | AG62: =AF62/$E$7 -> 0.0034819069 | AH62: 0.20241588 | AI62: 1 | AJ62: -1.1433683 | AK62: 1 | AL62: 0.79885108 | AM62: 1 | AN62: 0.13296787 | AO62: 1 | AP62: -1.2705533 | AQ62: 1
A63: 53 | B63: Brayden Schenn | C63: 2016-17 & 2017-18 | D63: 26 | E63: 0 | F63: 0.33709108 | G63: -0.1327983 | H63: 0.23741844 | I63: -0.0042808443 | J63: 0.28841133 | K63: 18.25176 | L63: 1.5919776 | M63: -0.030245006 | N63: =(F63-Settings!$D$18)/Settings!$E$18 -> 0.51811791 | O63: =(G63-Settings!$D$19)/Settings!$E$19 -> -0.52558366 | P63: =(H63-Settings!$D$20)/Settings!$E$20 -> 1.6697141 | Q63: =(I63-Settings!$D$21)/Settings!$E$21 -> -0.016433735 | R63: =(J63-Settings!$D$22)/Settings!$E$22 -> 0.10910196 | S63: =(K63-Settings!$D$23)/Settings!$E$23 -> 1.0406323 | T63: =(L63-Settings!$D$24)/Settings!$E$24 -> 0.19614405 | U63: =(M63-Settings!$D$25)/Settings!$E$25 -> 0.015572689 | V63: =Settings!$B$18*(N63-F$6)^2 -> 0.04443946 | W63: =Settings!$B$19*(O63-G$6)^2 -> 0.21202652 | X63: =Settings!$B$20*(P63-H$6)^2 -> 0.070050164 | Y63: =Settings!$B$21*(Q63-I$6)^2 -> 0.14223087 | Z63: =Settings!$B$22*(R63-J$6)^2 -> 0.00038307072 | AA63: =Settings!$B$23*(S63-K$6)^2 -> 0.47225642 | AB63: =Settings!$B$24*(T63-L$6)^2 -> 1.769091 | AC63: =Settings!$B$25*(U63-M$6)^2 -> 0.039009246 | AD63: =SQRT(SUM(V63:AC63)) -> 1.6581576 | AE63: =AD63/Yardstick -> 0.65632885 | AF63: =EXP(-(AD63^2)/(2*Yardstick^2)) -> 0.80623196 | AG63: =AF63/$E$7 -> 0.0034808258 | AH63: -0.21095828 | AI63: 1 | AJ63: 0.42122262 | AK63: 1 | AL63: -0.18168065 | AM63: 1 | AN63: -0.33925883 | AO63: 1 | AP63: -0.33259059 | AQ63: 1
A64: 54 | B64: Ondrej Palat | C64: 2016-17 & 2017-18 | D64: 26 | E64: 0 | F64: 0.53219829 | G64: -0.067241297 | H64: 0.20705083 | I64: 0.023585347 | J64: 0.16992423 | K64: 17.717048 | L64: 1.9658694 | M64: -0.44878059 | N64: =(F64-Settings!$D$18)/Settings!$E$18 -> 1.2163944 | O64: =(G64-Settings!$D$19)/Settings!$E$19 -> -0.25246483 | P64: =(H64-Settings!$D$20)/Settings!$E$20 -> 1.3945777 | Q64: =(I64-Settings!$D$21)/Settings!$E$21 -> 0.32624539 | R64: =(J64-Settings!$D$22)/Settings!$E$22 -> -0.20969315 | S64: =(K64-Settings!$D$23)/Settings!$E$23 -> 0.85493927 | T64: =(L64-Settings!$D$24)/Settings!$E$24 -> 0.45463586 | U64: =(M64-Settings!$D$25)/Settings!$E$25 -> -0.26669237 | V64: =Settings!$B$18*(N64-F$6)^2 -> 0.27361838 | W64: =Settings!$B$19*(O64-G$6)^2 -> 0.11446105 | X64: =Settings!$B$20*(P64-H$6)^2 -> 0.15032264 | Y64: =Settings!$B$21*(Q64-I$6)^2 -> 0.28130914 | Z64: =Settings!$B$22*(R64-J$6)^2 -> 0.026289931 | AA64: =Settings!$B$23*(S64-K$6)^2 -> 0.76195817 | AB64: =Settings!$B$24*(T64-L$6)^2 -> 1.1482837 | AC64: =Settings!$B$25*(U64-M$6)^2 -> 0.0071838294 | AD64: =SQRT(SUM(V64:AC64)) -> 1.6623558 | AE64: =AD64/Yardstick -> 0.65799056 | AF64: =EXP(-(AD64^2)/(2*Yardstick^2)) -> 0.80535203 | AG64: =AF64/$E$7 -> 0.0034770268 | AH64: -1.1545191 | AI64: 1 | AJ64: -0.075010748 | AK64: 1 | AL64: 0.88267565 | AM64: 1 | AN64: -0.022226394 | AO64: 1 | AP64: -0.27863279 | AQ64: 1
A65: 55 | B65: Jack Eichel | C65: 2021-22 & 2022-23 | D65: 26 | E65: 1 | F65: 0.18007403 | G65: 0.065446738 | H65: -0.0047360565 | I65: -0.0091096943 | J65: 0.74063348 | K65: 18.213531 | L65: 3.0949213 | M65: 0.41226515 | N65: =(F65-Settings!$D$18)/Settings!$E$18 -> -0.043836334 | O65: =(G65-Settings!$D$19)/Settings!$E$19 -> 0.30033044 | P65: =(H65-Settings!$D$20)/Settings!$E$20 -> -0.52425219 | Q65: =(I65-Settings!$D$21)/Settings!$E$21 -> -0.075815588 | R65: =(J65-Settings!$D$22)/Settings!$E$22 -> 1.3258269 | S65: =(K65-Settings!$D$23)/Settings!$E$23 -> 1.0273564 | T65: =(L65-Settings!$D$24)/Settings!$E$24 -> 1.2352112 | U65: =(M65-Settings!$D$25)/Settings!$E$25 -> 0.31400647 | V65: =Settings!$B$18*(N65-F$6)^2 -> 0.001640808 | W65: =Settings!$B$19*(O65-G$6)^2 -> 0.0082998229 | X65: =Settings!$B$20*(P65-H$6)^2 -> 1.552121 | Y65: =Settings!$B$21*(Q65-I$6)^2 -> 0.12290543 | Z65: =Settings!$B$22*(R65-J$6)^2 -> 0.27516714 | AA65: =Settings!$B$23*(S65-K$6)^2 -> 0.49067927 | AB65: =Settings!$B$24*(T65-L$6)^2 -> 0.084683696 | AC65: =Settings!$B$25*(U65-M$6)^2 -> 0.24595783 | AD65: =SQRT(SUM(V65:AC65)) -> 1.6677695 | AE65: =AD65/Yardstick -> 0.66013339 | AF65: =EXP(-(AD65^2)/(2*Yardstick^2)) -> 0.80421547 | AG65: =AF65/$E$7 -> 0.0034721198 | AH65: 0.72165715 | AI65: 1 | AJ65: -0.12413442 | AK65: 1 | AL65: -0.32615523 | AM65: 1
A66: 56 | B66: Anze Kopitar | C66: 2012-13 & 2013-14 | D66: 26 | E66: 0 | F66: 0.29179318 | G66: 0.13590001 | H66: 0.10046982 | I66: -0.053719403 | J66: 0.41811759 | K66: 20.299483 | L66: 4.1290744 | M66: 1.7231002 | N66: =(F66-Settings!$D$18)/Settings!$E$18 -> 0.35599953 | O66: =(G66-Settings!$D$19)/Settings!$E$19 -> 0.59384775 | P66: =(H66-Settings!$D$20)/Settings!$E$20 -> 0.42893324 | Q66: =(I66-Settings!$D$21)/Settings!$E$21 -> -0.6243949 | R66: =(J66-Settings!$D$22)/Settings!$E$22 -> 0.45808276 | S66: =(K66-Settings!$D$23)/Settings!$E$23 -> 1.7517595 | T66: =(L66-Settings!$D$24)/Settings!$E$24 -> 1.9501778 | U66: =(M66-Settings!$D$25)/Settings!$E$25 -> 1.1980482 | V66: =Settings!$B$18*(N66-F$6)^2 -> 0.019128313 | W66: =Settings!$B$19*(O66-G$6)^2 -> 0.0016129514 | X66: =Settings!$B$20*(P66-H$6)^2 -> 0.67168513 | Y66: =Settings!$B$21*(Q66-I$6)^2 -> 0.011076844 | Z66: =Settings!$B$22*(R66-J$6)^2 -> 0.018631368 | AA66: =Settings!$B$23*(S66-K$6)^2 -> 0.00057207417 | AB66: =Settings!$B$24*(T66-L$6)^2 -> 0.17974378 | AC66: =Settings!$B$25*(U66-M$6)^2 -> 1.9043534 | AD66: =SQRT(SUM(V66:AC66)) -> 1.6753519 | AE66: =AD66/Yardstick -> 0.66313464 | AF66: =EXP(-(AD66^2)/(2*Yardstick^2)) -> 0.8026201 | AG66: =AF66/$E$7 -> 0.0034652319 | AH66: -0.18039642 | AI66: 0 | AJ66: -0.4171231 | AK66: 0 | AL66: -0.57966059 | AM66: 0 | AN66: -0.15221199 | AO66: 0 | AP66: 0.11026423 | AQ66: 1
A67: 57 | B67: Jason Pominville | C67: 2007-08 & 2008-09 | D67: 26 | E67: 0 | F67: 0.12284155 | G67: -0.14779182 | H67: 0.22334112 | I67: 0.035244306 | J67: 0.47078122 | K67: 19.22963 | L67: 2.3869953 | M67: -2.0420614 | N67: =(F67-Settings!$D$18)/Settings!$E$18 -> -0.24866784 | O67: =(G67-Settings!$D$19)/Settings!$E$19 -> -0.58804856 | P67: =(H67-Settings!$D$20)/Settings!$E$20 -> 1.5421709 | Q67: =(I67-Settings!$D$21)/Settings!$E$21 -> 0.46961919 | R67: =(J67-Settings!$D$22)/Settings!$E$22 -> 0.59977672 | S67: =(K67-Settings!$D$23)/Settings!$E$23 -> 1.380224 | T67: =(L67-Settings!$D$24)/Settings!$E$24 -> 0.74578321 | U67: =(M67-Settings!$D$25)/Settings!$E$25 -> -1.3412187 | V67: =Settings!$B$18*(N67-F$6)^2 -> 0.017453137 | W67: =Settings!$B$19*(O67-G$6)^2 -> 0.23853312 | X67: =Settings!$B$20*(P67-H$6)^2 -> 0.10349668 | Y67: =Settings!$B$21*(Q67-I$6)^2 -> 0.35343567 | Z67: =Settings!$B$22*(R67-J$6)^2 -> 0.039945711 | AA67: =Settings!$B$23*(S67-K$6)^2 -> 0.1208379 | AB67: =Settings!$B$24*(T67-L$6)^2 -> 0.60907509 | AC67: =Settings!$B$25*(U67-M$6)^2 -> 1.3439389 | AD67: =SQRT(SUM(V67:AC67)) -> 1.6812841 | AE67: =AD67/Yardstick -> 0.66548273 | AF67: =EXP(-(AD67^2)/(2*Yardstick^2)) -> 0.80136911 | AG67: =AF67/$E$7 -> 0.0034598309 | AH67: -0.37650967 | AI67: 0 | AJ67: 1.2047468 | AK67: 0 | AL67: 1.0295865 | AM67: 0 | AN67: -0.3051559 | AO67: 0 | AP67: -0.13619614 | AQ67: 0
A68: 58 | B68: Jason Robertson | C68: 2024-25 & 2025-26 | D68: 26 | E68: 1 | F68: 0.30764912 | G68: 0.030439994 | H68: 0.189521 | I68: -3.2634776e-05 | J68: 0.47235725 | K68: 18.262398 | L68: 5.2458557 | M68: 0.71396112 | N68: =(F68-Settings!$D$18)/Settings!$E$18 -> 0.41274694 | O68: =(G68-Settings!$D$19)/Settings!$E$19 -> 0.15448788 | P68: =(H68-Settings!$D$20)/Settings!$E$20 -> 1.2357541 | Q68: =(I68-Settings!$D$21)/Settings!$E$21 -> 0.035807805 | R68: =(J68-Settings!$D$22)/Settings!$E$22 -> 0.60401712 | S68: =(K68-Settings!$D$23)/Settings!$E$23 -> 1.0443268 | T68: =(L68-Settings!$D$24)/Settings!$E$24 -> 2.7222698 | U68: =(M68-Settings!$D$25)/Settings!$E$25 -> 0.51747359 | V68: =Settings!$B$18*(N68-F$6)^2 -> 0.026792242 | W68: =Settings!$B$19*(O68-G$6)^2 -> 0.024437862 | X68: =Settings!$B$20*(P68-H$6)^2 -> 0.21044488 | Y68: =Settings!$B$21*(Q68-I$6)^2 -> 0.16039882 | Z68: =Settings!$B$22*(R68-J$6)^2 -> 0.040707338 | AA68: =Settings!$B$23*(S68-K$6)^2 -> 0.46719225 | AB68: =Settings!$B$24*(T68-L$6)^2 -> 1.4305451 | AC68: =Settings!$B$25*(U68-M$6)^2 -> 0.48917222 | AD68: =SQRT(SUM(V68:AC68)) -> 1.6881027 | AE68: =AD68/Yardstick -> 0.66818165 | AF68: =EXP(-(AD68^2)/(2*Yardstick^2)) -> 0.79992816 | AG68: =AF68/$E$7 -> 0.0034536097
A69: 59 | B69: Nikolaj Ehlers | C69: 2021-22 & 2022-23 | D69: 26 | E69: 1 | F69: 0.41108854 | G69: -0.20036119 | H69: 0.11593634 | I69: 2.6726965e-05 | J69: 0.27258721 | K69: 16.50283 | L69: 3.2397375 | M69: -0.2986406 | N69: =(F69-Settings!$D$18)/Settings!$E$18 -> 0.7829502 | O69: =(G69-Settings!$D$19)/Settings!$E$19 -> -0.80705926 | P69: =(H69-Settings!$D$20)/Settings!$E$20 -> 0.56906288 | Q69: =(I69-Settings!$D$21)/Settings!$E$21 -> 0.036537794 | R69: =(J69-Settings!$D$22)/Settings!$E$22 -> 0.06652641 | S69: =(K69-Settings!$D$23)/Settings!$E$23 -> 0.43326924 | T69: =(L69-Settings!$D$24)/Settings!$E$24 -> 1.3353306 | U69: =(M69-Settings!$D$25)/Settings!$E$25 -> -0.16543629 | V69: =Settings!$B$18*(N69-F$6)^2 -> 0.10840114 | W69: =Settings!$B$19*(O69-G$6)^2 -> 0.34379822 | X69: =Settings!$B$20*(P69-H$6)^2 -> 0.57289172 | Y69: =Settings!$B$21*(Q69-I$6)^2 -> 0.16066042 | Z69: =Settings!$B$22*(R69-J$6)^2 -> 0.0014909296 | AA69: =Settings!$B$23*(S69-K$6)^2 -> 1.6759172 | AB69: =Settings!$B$24*(T69-L$6)^2 -> 0.036437193 | AC69: =Settings!$B$25*(U69-M$6)^2 -> 0.00027220414 | AD69: =SQRT(SUM(V69:AC69)) -> 1.7029002 | AE69: =AD69/Yardstick -> 0.67403876 | AF69: =EXP(-(AD69^2)/(2*Yardstick^2)) -> 0.79679 | AG69: =AF69/$E$7 -> 0.003440061 | AH69: -0.10589585 | AI69: 1 | AJ69: 0.3331273 | AK69: 1 | AL69: 0.20093341 | AM69: 1
A70: 60 | B70: Mikko Koivu | C70: 2008-09 & 2009-10 | D70: 26 | E70: 0 | F70: 0.46242154 | G70: 0.23436818 | H70: 0.078879491 | I70: -0.0045297206 | J70: 0.21980107 | K70: 20.656013 | L70: 1.6350266 | M70: -0.2805172 | N70: =(F70-Settings!$D$18)/Settings!$E$18 -> 0.9666678 | O70: =(G70-Settings!$D$19)/Settings!$E$19 -> 1.0040787 | P70: =(H70-Settings!$D$20)/Settings!$E$20 -> 0.23332075 | Q70: =(I70-Settings!$D$21)/Settings!$E$21 -> -0.019494243 | R70: =(J70-Settings!$D$22)/Settings!$E$22 -> -0.07549718 | S70: =(K70-Settings!$D$23)/Settings!$E$23 -> 1.875574 | T70: =(L70-Settings!$D$24)/Settings!$E$24 -> 0.22590613 | U70: =(M70-Settings!$D$25)/Settings!$E$25 -> -0.15321366 | V70: =Settings!$B$18*(N70-F$6)^2 -> 0.1692535 | W70: =Settings!$B$19*(O70-G$6)^2 -> 0.050006987 | X70: =Settings!$B$20*(P70-H$6)^2 -> 0.82272982 | Y70: =Settings!$B$21*(Q70-I$6)^2 -> 0.14120037 | Z70: =Settings!$B$22*(R70-J$6)^2 -> 0.010430013 | AA70: =Settings!$B$23*(S70-K$6)^2 -> 0.021824907 | AB70: =Settings!$B$24*(T70-L$6)^2 -> 1.6908053 | AC70: =Settings!$B$25*(U70-M$6)^2 -> 0.0008249092 | AD70: =SQRT(SUM(V70:AC70)) -> 1.7050149 | AE70: =AD70/Yardstick -> 0.67487581 | AF70: =EXP(-(AD70^2)/(2*Yardstick^2)) -> 0.79634029 | AG70: =AF70/$E$7 -> 0.0034381195 | AH70: -0.26488652 | AI70: 0 | AJ70: -0.49386714 | AK70: 0 | AL70: 0.57704107 | AM70: 0 | AN70: 0.76918756 | AO70: 0 | AP70: -0.68753343 | AQ70: 0
A71: 61 | B71: Nicklas Backstrom | C71: 2012-13 & 2013-14 | D71: 26 | E71: 0 | F71: 0.11383561 | G71: 0.11179281 | H71: 0.49515104 | I71: -0.027224603 | J71: 0.25199593 | K71: 19.553974 | L71: 1.652923 | M71: 0.73199541 | N71: =(F71-Settings!$D$18)/Settings!$E$18 -> -0.28089951 | O71: =(G71-Settings!$D$19)/Settings!$E$19 -> 0.4934141 | P71: =(H71-Settings!$D$20)/Settings!$E$20 -> 4.004821 | Q71: =(I71-Settings!$D$21)/Settings!$E$21 -> -0.29858019 | R71: =(J71-Settings!$D$22)/Settings!$E$22 -> 0.011124617 | S71: =(K71-Settings!$D$23)/Settings!$E$23 -> 1.4928614 | T71: =(L71-Settings!$D$24)/Settings!$E$24 -> 0.23827894 | U71: =(M71-Settings!$D$25)/Settings!$E$25 -> 0.52963611 | V71: =Settings!$B$18*(N71-F$6)^2 -> 0.021469506 | W71: =Settings!$B$19*(O71-G$6)^2 -> 2.2597929e-05 | X71: =Settings!$B$20*(P71-H$6)^2 -> 0.6078099 | Y71: =Settings!$B$21*(Q71-I$6)^2 -> 0.06297859 | Z71: =Settings!$B$22*(R71-J$6)^2 -> 0.0040181644 | AA71: =Settings!$B$23*(S71-K$6)^2 -> 0.055215601 | AB71: =Settings!$B$24*(T71-L$6)^2 -> 1.6587815 | AC71: =Settings!$B$25*(U71-M$6)^2 -> 0.5063333 | AD71: =SQRT(SUM(V71:AC71)) -> 1.7078141 | AE71: =AD71/Yardstick -> 0.6759838 | AF71: =EXP(-(AD71^2)/(2*Yardstick^2)) -> 0.79574456 | AG71: =AF71/$E$7 -> 0.0034355475 | AH71: 0.60856877 | AI71: 0 | AJ71: -0.024646262 | AK71: 0 | AL71: -0.044545826 | AM71: 0 | AN71: -0.28057056 | AO71: 0 | AP71: -0.286851 | AQ71: 1
A72: 62 | B72: Mikael Granlund | C72: 2017-18 & 2018-19 | D72: 26 | E72: 1 | F72: 0.60129789 | G72: 0.064767588 | H72: 0.28618933 | I72: -0.029753996 | J72: 0.017991196 | K72: 17.874893 | L72: 1.797633 | M72: -1.0637897 | N72: =(F72-Settings!$D$18)/Settings!$E$18 -> 1.4636976 | O72: =(G72-Settings!$D$19)/Settings!$E$19 -> 0.29750101 | P72: =(H72-Settings!$D$20)/Settings!$E$20 -> 2.1115877 | Q72: =(I72-Settings!$D$21)/Settings!$E$21 -> -0.32968492 | R72: =(J72-Settings!$D$22)/Settings!$E$22 -> -0.61847615 | S72: =(K72-Settings!$D$23)/Settings!$E$23 -> 0.90975515 | T72: =(L72-Settings!$D$24)/Settings!$E$24 -> 0.33832483 | U72: =(M72-Settings!$D$25)/Settings!$E$25 -> -0.68146134 | V72: =Settings!$B$18*(N72-F$6)^2 -> 0.40155387 | W72: =Settings!$B$19*(O72-G$6)^2 -> 0.0085319809 | X72: =Settings!$B$20*(P72-H$6)^2 -> 0.004496779 | Y72: =Settings!$B$21*(Q72-I$6)^2 -> 0.056190283 | Z72: =Settings!$B$22*(R72-J$6)^2 -> 0.11899396 | AA72: =Settings!$B$23*(S72-K$6)^2 -> 0.66926516 | AB72: =Settings!$B$24*(T72-L$6)^2 -> 1.411085 | AC72: =Settings!$B$25*(U72-M$6)^2 -> 0.24952667 | AD72: =SQRT(SUM(V72:AC72)) -> 1.7086965 | AE72: =AD72/Yardstick -> 0.67633306 | AF72: =EXP(-(AD72^2)/(2*Yardstick^2)) -> 0.79555667 | AG72: =AF72/$E$7 -> 0.0034347362 | AH72: -0.22137606 | AI72: 1 | AJ72: 0.13809473 | AK72: 1 | AL72: -1.1305077 | AM72: 1 | AN72: -1.8975339 | AO72: 1 | AP72: 0.53691938 | AQ72: 1
A73: 63 | B73: Joel Eriksson Ek | C73: 2021-22 & 2022-23 | D73: 26 | E73: 1 | F73: 0.26859103 | G73: 0.25045437 | H73: 0.38310374 | I73: -0.027025444 | J73: 0.07082542 | K73: 17.974086 | L73: 2.2145678 | M73: -1.9481494 | N73: =(F73-Settings!$D$18)/Settings!$E$18 -> 0.2729605 | O73: =(G73-Settings!$D$19)/Settings!$E$19 -> 1.0710958 | P73: =(H73-Settings!$D$20)/Settings!$E$20 -> 2.9896509 | Q73: =(I73-Settings!$D$21)/Settings!$E$21 -> -0.29613107 | R73: =(J73-Settings!$D$22)/Settings!$E$22 -> -0.47632318 | S73: =(K73-Settings!$D$23)/Settings!$E$23 -> 0.94420255 | T73: =(L73-Settings!$D$24)/Settings!$E$24 -> 0.62657467 | U73: =(M73-Settings!$D$25)/Settings!$E$25 -> -1.2778834 | V73: =Settings!$B$18*(N73-F$6)^2 -> 0.010235159 | W73: =Settings!$B$19*(O73-G$6)^2 -> 0.064309603 | X73: =Settings!$B$20*(P73-H$6)^2 -> 0.10603084 | Y73: =Settings!$B$21*(Q73-I$6)^2 -> 0.063529521 | Z73: =Settings!$B$22*(R73-J$6)^2 -> 0.079175984 | AA73: =Settings!$B$23*(S73-K$6)^2 -> 0.6140899 | AB73: =Settings!$B$24*(T73-L$6)^2 -> 0.80935423 | AC73: =Settings!$B$25*(U73-M$6)^2 -> 1.2011032 | AD73: =SQRT(SUM(V73:AC73)) -> 1.7169241 | AE73: =AD73/Yardstick -> 0.67958969 | AF73: =EXP(-(AD73^2)/(2*Yardstick^2)) -> 0.79380211 | AG73: =AF73/$E$7 -> 0.0034271612 | AH73: -0.37590614 | AI73: 1 | AJ73: 0.62836021 | AK73: 1 | AL73: -0.68269048 | AM73: 1
A74: 64 | B74: Derek Stepan | C74: 2015-16 & 2016-17 | D74: 26 | E74: 0 | F74: 0.25255746 | G74: 0.14770371 | H74: 0.12121786 | I74: 0.051913967 | J74: 0.426607 | K74: 17.747168 | L74: 1.9502647 | M74: -0.079569589 | N74: =(F74-Settings!$D$18)/Settings!$E$18 -> 0.21557734 | O74: =(G74-Settings!$D$19)/Settings!$E$19 -> 0.64302347 | P74: =(H74-Settings!$D$20)/Settings!$E$20 -> 0.61691453 | Q74: =(I74-Settings!$D$21)/Settings!$E$21 -> 0.67461114 | R74: =(J74-Settings!$D$22)/Settings!$E$22 -> 0.48092391 | S74: =(K74-Settings!$D$23)/Settings!$E$23 -> 0.86539905 | T74: =(L74-Settings!$D$24)/Settings!$E$24 -> 0.44384746 | U74: =(M74-Settings!$D$25)/Settings!$E$25 -> -0.017692359 | V74: =Settings!$B$18*(N74-F$6)^2 -> 0.0057012217 | W74: =Settings!$B$19*(O74-G$6)^2 -> 0.003863072 | X74: =Settings!$B$20*(P74-H$6)^2 -> 0.54095466 | Y74: =Settings!$B$21*(Q74-I$6)^2 -> 0.47084264 | Z74: =Settings!$B$22*(R74-J$6)^2 -> 0.021524305 | AA74: =Settings!$B$23*(S74-K$6)^2 -> 0.74380685 | AB74: =Settings!$B$24*(T74-L$6)^2 -> 1.1715213 | AC74: =Settings!$B$25*(U74-M$6)^2 -> 0.026975611 | AD74: =SQRT(SUM(V74:AC74)) -> 1.7277701 | AE74: =AD74/Yardstick -> 0.68388275 | AF74: =EXP(-(AD74^2)/(2*Yardstick^2)) -> 0.79148227 | AG74: =AF74/$E$7 -> 0.0034171454 | AH74: -0.8053364 | AI74: 0 | AJ74: -0.62640102 | AK74: 1 | AL74: -0.11983825 | AM74: 1 | AN74: -1.1131041 | AO74: 1 | AP74: 0.30105621 | AQ74: 1
A75: 65 | B75: Jeff Carter | C75: 2009-10 & 2010-11 | D75: 26 | E75: 0 | F75: 0.43397451 | G75: -0.068211764 | H75: 0.30097891 | I75: 0.038978149 | J75: 0.15785667 | K75: 18.23961 | L75: 2.5715956 | M75: 1.4952279 | N75: =(F75-Settings!$D$18)/Settings!$E$18 -> 0.86485766 | O75: =(G75-Settings!$D$19)/Settings!$E$19 -> -0.25650791 | P75: =(H75-Settings!$D$20)/Settings!$E$20 -> 2.2455842 | Q75: =(I75-Settings!$D$21)/Settings!$E$21 -> 0.51553541 | R75: =(J75-Settings!$D$22)/Settings!$E$22 -> -0.24216151 | S75: =(K75-Settings!$D$23)/Settings!$E$23 -> 1.0364131 | T75: =(L75-Settings!$D$24)/Settings!$E$24 -> 0.87340752 | U75: =(M75-Settings!$D$25)/Settings!$E$25 -> 1.0443686 | V75: =Settings!$B$18*(N75-F$6)^2 -> 0.13386336 | W75: =Settings!$B$19*(O75-G$6)^2 -> 0.11568777 | X75: =Settings!$B$20*(P75-H$6)^2 -> 5.0879666e-05 | Y75: =Settings!$B$21*(Q75-I$6)^2 -> 0.37827287 | Z75: =Settings!$B$22*(R75-J$6)^2 -> 0.031209459 | AA75: =Settings!$B$23*(S75-K$6)^2 -> 0.4780732 | AB75: =Settings!$B$24*(T75-L$6)^2 -> 0.42615871 | AC75: =Settings!$B$25*(U75-M$6)^2 -> 1.5038203 | AD75: =SQRT(SUM(V75:AC75)) -> 1.7513242 | AE75: =AD75/Yardstick -> 0.69320588 | AF75: =EXP(-(AD75^2)/(2*Yardstick^2)) -> 0.7864177 | AG75: =AF75/$E$7 -> 0.0033952797 | AH75: -0.0090158198 | AI75: 0 | AJ75: 1.5242564 | AK75: 0 | AL75: 0.039103747 | AM75: 0 | AN75: -1.7921012 | AO75: 0 | AP75: -0.2834928 | AQ75: 0
A76: 66 | B76: Elias Pettersson | C76: 2023-24 & 2024-25 | D76: 26 | E76: 1 | F76: 0.21952753 | G76: 0.029515353 | H76: 0.18479919 | I76: -0.0017743376 | J76: 0.56438359 | K76: 18.449087 | L76: 3.2295459 | M76: -2.4929469 | N76: =(F76-Settings!$D$18)/Settings!$E$18 -> 0.097365264 | O76: =(G76-Settings!$D$19)/Settings!$E$19 -> 0.15063571 | P76: =(H76-Settings!$D$20)/Settings!$E$20 -> 1.1929736 | Q76: =(I76-Settings!$D$21)/Settings!$E$21 -> 0.01438955 | R76: =(J76-Settings!$D$22)/Settings!$E$22 -> 0.85161832 | S76: =(K76-Settings!$D$23)/Settings!$E$23 -> 1.1091594 | T76: =(L76-Settings!$D$24)/Settings!$E$24 -> 1.3282846 | U76: =(M76-Settings!$D$25)/Settings!$E$25 -> -1.6453009 | V76: =Settings!$B$18*(N76-F$6)^2 -> 0.00051258706 | W76: =Settings!$B$19*(O76-G$6)^2 -> 0.024979449 | X76: =Settings!$B$20*(P76-H$6)^2 -> 0.22836428 | Y76: =Settings!$B$21*(Q76-I$6)^2 -> 0.15281819 | Z76: =Settings!$B$22*(R76-J$6)^2 -> 0.097650761 | AA76: =Settings!$B$23*(S76-K$6)^2 -> 0.38276748 | AB76: =Settings!$B$24*(T76-L$6)^2 -> 0.039176795 | AC76: =Settings!$B$25*(U76-M$6)^2 -> 2.14144 | AD76: =SQRT(SUM(V76:AC76)) -> 1.7514878 | AE76: =AD76/Yardstick -> 0.69327063 | AF76: =EXP(-(AD76^2)/(2*Yardstick^2)) -> 0.78638241 | AG76: =AF76/$E$7 -> 0.0033951273 | AH76: -1.5460954 | AI76: 1
A77: 67 | B77: Aleksander Barkov | C77: 2020-21 & 2021-22 | D77: 26 | E77: 1 | F77: 0.28539238 | G77: 0.036831657 | H77: 0.11471266 | I77: 0.011819175 | J77: 0.55124414 | K77: 19.823219 | L77: 5.6032129 | M77: 0.19569914 | N77: =(F77-Settings!$D$18)/Settings!$E$18 -> 0.33309146 | O77: =(G77-Settings!$D$19)/Settings!$E$19 -> 0.18111637 | P77: =(H77-Settings!$D$20)/Settings!$E$20 -> 0.55797612 | Q77: =(I77-Settings!$D$21)/Settings!$E$21 -> 0.18155315 | R77: =(J77-Settings!$D$22)/Settings!$E$22 -> 0.81626599 | S77: =(K77-Settings!$D$23)/Settings!$E$23 -> 1.586364 | T77: =(L77-Settings!$D$24)/Settings!$E$24 -> 2.9693304 | U77: =(M77-Settings!$D$25)/Settings!$E$25 -> 0.16795194 | V77: =Settings!$B$18*(N77-F$6)^2 -> 0.016399451 | W77: =Settings!$B$19*(O77-G$6)^2 -> 0.02085642 | X77: =Settings!$B$20*(P77-H$6)^2 -> 0.58042191 | Y77: =Settings!$B$21*(Q77-I$6)^2 -> 0.21685554 | Z77: =Settings!$B$22*(R77-J$6)^2 -> 0.088019721 | AA77: =Settings!$B$23*(S77-K$6)^2 -> 0.020015855 | AB77: =Settings!$B$24*(T77-L$6)^2 -> 2.0825797 | AC77: =Settings!$B$25*(U77-M$6)^2 -> 0.1224208 | AD77: =SQRT(SUM(V77:AC77)) -> 1.774139 | AE77: =AD77/Yardstick -> 0.7022364 | AF77: =EXP(-(AD77^2)/(2*Yardstick^2)) -> 0.78147823 | AG77: =AF77/$E$7 -> 0.003373954 | AH77: -0.6630519 | AI77: 1 | AJ77: -0.83653836 | AK77: 1 | AL77: -0.12611295 | AM77: 1
A78: 68 | B78: Wayne Simmonds | C78: 2013-14 & 2014-15 | D78: 26 | E78: 0 | F78: 0.25873302 | G78: 0.051883275 | H78: 0.30979231 | I78: -7.2824693e-06 | J78: 0.37958411 | K78: 16.23758 | L78: 3.0267612 | M78: 1.1593395 | N78: =(F78-Settings!$D$18)/Settings!$E$18 -> 0.23767928 | O78: =(G78-Settings!$D$19)/Settings!$E$19 -> 0.24382332 | P78: =(H78-Settings!$D$20)/Settings!$E$20 -> 2.3254353 | Q78: =(I78-Settings!$D$21)/Settings!$E$21 -> 0.03611957 | R78: =(J78-Settings!$D$22)/Settings!$E$22 -> 0.35440662 | S78: =(K78-Settings!$D$23)/Settings!$E$23 -> 0.34115382 | T78: =(L78-Settings!$D$24)/Settings!$E$24 -> 1.1880884 | U78: =(M78-Settings!$D$25)/Settings!$E$25 -> 0.81784175 | V78: =Settings!$B$18*(N78-F$6)^2 -> 0.0072915754 | W78: =Settings!$B$19*(O78-G$6)^2 -> 0.013542935 | X78: =Settings!$B$20*(P78-H$6)^2 -> 0.00081667424 | Y78: =Settings!$B$21*(Q78-I$6)^2 -> 0.16051052 | Z78: =Settings!$B$22*(R78-J$6)^2 -> 0.0081236667 | AA78: =Settings!$B$23*(S78-K$6)^2 -> 1.9229025 | AB78: =Settings!$B$24*(T78-L$6)^2 -> 0.11433017 | AC78: =Settings!$B$25*(U78-M$6)^2 -> 0.99955335 | AD78: =SQRT(SUM(V78:AC78)) -> 1.7964051 | AE78: =AD78/Yardstick -> 0.71104972 | AF78: =EXP(-(AD78^2)/(2*Yardstick^2)) -> 0.77662641 | AG78: =AF78/$E$7 -> 0.0033530068 | AH78: 0.11141976 | AI78: 0 | AJ78: -0.9216846 | AK78: 0 | AL78: -0.86760118 | AM78: 0 | AN78: -1.2529524 | AO78: 1 | AP78: -1.0186463 | AQ78: 1
A79: 69 | B79: Oliver Bjorkstrand | C79: 2020-21 & 2021-22 | D79: 26 | E79: 1 | F79: 0.20356078 | G79: 0.13138183 | H79: 0.09682413 | I79: 0.00031989688 | J79: 0.56791336 | K79: 17.134559 | L79: 2.8112767 | M79: 1.0756553 | N79: =(F79-Settings!$D$18)/Settings!$E$18 -> 0.040221269 | O79: =(G79-Settings!$D$19)/Settings!$E$19 -> 0.57502444 | P79: =(H79-Settings!$D$20)/Settings!$E$20 -> 0.39590262 | Q79: =(I79-Settings!$D$21)/Settings!$E$21 -> 0.040142995 | R79: =(J79-Settings!$D$22)/Settings!$E$22 -> 0.86111534 | S79: =(K79-Settings!$D$23)/Settings!$E$23 -> 0.65265406 | T79: =(L79-Settings!$D$24)/Settings!$E$24 -> 1.0391122 | U79: =(M79-Settings!$D$25)/Settings!$E$25 -> 0.76140415 | V79: =Settings!$B$18*(N79-F$6)^2 -> 8.498308e-06 | W79: =Settings!$B$19*(O79-G$6)^2 -> 0.0010076515 | X79: =Settings!$B$20*(P79-H$6)^2 -> 0.69611611 | Y79: =Settings!$B$21*(Q79-I$6)^2 -> 0.16195551 | Z79: =Settings!$B$22*(R79-J$6)^2 -> 0.10032322 | AA79: =Settings!$B$23*(S79-K$6)^2 -> 1.1560279 | AB79: =Settings!$B$24*(T79-L$6)^2 -> 0.23727001 | AC79: =Settings!$B$25*(U79-M$6)^2 -> 0.88988856 | AD79: =SQRT(SUM(V79:AC79)) -> 1.8007214 | AE79: =AD79/Yardstick -> 0.71275816 | AF79: =EXP(-(AD79^2)/(2*Yardstick^2)) -> 0.77568242 | AG79: =AF79/$E$7 -> 0.0033489312 | AH79: -0.71530571 | AI79: 1 | AJ79: -0.48035281 | AK79: 1 | AL79: 0.98633469 | AM79: 1 | AN79: -1.0884484 | AO79: 1
A80: 70 | B80: Max Pacioretty | C80: 2013-14 & 2014-15 | D80: 26 | E80: 0 | F80: 0.25661891 | G80: -0.059867468 | H80: 0.02021711 | I80: 0.037211699 | J80: 0.62608481 | K80: 18.677778 | L80: 4.3205973 | M80: -1.5850302 | N80: =(F80-Settings!$D$18)/Settings!$E$18 -> 0.23011301 | O80: =(G80-Settings!$D$19)/Settings!$E$19 -> -0.22174452 | P80: =(H80-Settings!$D$20)/Settings!$E$20 -> -0.29817171 | Q80: =(I80-Settings!$D$21)/Settings!$E$21 -> 0.49381283 | R80: =(J80-Settings!$D$22)/Settings!$E$22 -> 1.0176284 | S80: =(K80-Settings!$D$23)/Settings!$E$23 -> 1.1885785 | T80: =(L80-Settings!$D$24)/Settings!$E$24 -> 2.0825881 | U80: =(M80-Settings!$D$25)/Settings!$E$25 -> -1.0329918 | V80: =Settings!$B$18*(N80-F$6)^2 -> 0.006725145 | W80: =Settings!$B$19*(O80-G$6)^2 -> 0.10535372 | X80: =Settings!$B$20*(P80-H$6)^2 -> 1.3104187 | Y80: =Settings!$B$21*(Q80-I$6)^2 -> 0.36641749 | Z80: =Settings!$B$22*(R80-J$6)^2 -> 0.14956254 | AA80: =Settings!$B$23*(S80-K$6)^2 -> 0.2908045 | AB80: =Settings!$B$24*(T80-L$6)^2 -> 0.30955007 | AC80: =Settings!$B$25*(U80-M$6)^2 -> 0.72429784 | AD80: =SQRT(SUM(V80:AC80)) -> 1.8064136 | AE80: =AD80/Yardstick -> 0.71501124 | AF80: =EXP(-(AD80^2)/(2*Yardstick^2)) -> 0.77443578 | AG80: =AF80/$E$7 -> 0.0033435489 | AH80: -1.4003535 | AI80: 0 | AJ80: 0.096393977 | AK80: 0 | AL80: -1.138653 | AM80: 0 | AN80: -1.3750036 | AO80: 1 | AP80: 1.7643625 | AQ80: 1
A81: 71 | B81: Tage Thompson | C81: 2022-23 & 2023-24 | D81: 26 | E81: 1 | F81: 0.23300558 | G81: -0.13017454 | H81: 0.044232916 | I81: -0.012129009 | J81: 0.58045795 | K81: 17.737025 | L81: 3.6614186 | M81: -1.8174338 | N81: =(F81-Settings!$D$18)/Settings!$E$18 -> 0.14560238 | O81: =(G81-Settings!$D$19)/Settings!$E$19 -> -0.51465275 | P81: =(H81-Settings!$D$20)/Settings!$E$20 -> -0.080583889 | Q81: =(I81-Settings!$D$21)/Settings!$E$21 -> -0.11294503 | R81: =(J81-Settings!$D$22)/Settings!$E$22 -> 0.89486714 | S81: =(K81-Settings!$D$23)/Settings!$E$23 -> 0.86187657 | T81: =(L81-Settings!$D$24)/Settings!$E$24 -> 1.6268618 | U81: =(M81-Settings!$D$25)/Settings!$E$25 -> -1.1897273 | V81: =Settings!$B$18*(N81-F$6)^2 -> 0.0019547612 | W81: =Settings!$B$19*(O81-G$6)^2 -> 0.20754852 | X81: =Settings!$B$20*(P81-H$6)^2 -> 1.0971033 | Y81: =Settings!$B$21*(Q81-I$6)^2 -> 0.11153858 | Z81: =Settings!$B$22*(R81-J$6)^2 -> 0.11011293 | AA81: =Settings!$B$23*(S81-K$6)^2 -> 0.74989514 | AB81: =Settings!$B$24*(T81-L$6)^2 -> 0.010129608 | AC81: =Settings!$B$25*(U81-M$6)^2 -> 1.0156456 | AD81: =SQRT(SUM(V81:AC81)) -> 1.8176712 | AE81: =AD81/Yardstick -> 0.7194672 | AF81: =EXP(-(AD81^2)/(2*Yardstick^2)) -> 0.77196465 | AG81: =AF81/$E$7 -> 0.0033328801 | AH81: 0.77335512 | AI81: 1 | AJ81: 0.083003473 | AK81: 1
A82: 72 | B82: Sidney Crosby | C82: 2012-13 & 2013-14 | D82: 26 | E82: 0 | F82: 0.43481032 | G82: -0.0086611851 | H82: 0.15580253 | I82: -0.00066186964 | J82: 0.4000641 | K82: 21.224282 | L82: 5.3585019 | M82: 1.0988702 | N82: =(F82-Settings!$D$18)/Settings!$E$18 -> 0.86784896 | O82: =(G82-Settings!$D$19)/Settings!$E$19 -> -0.0084126144 | P82: =(H82-Settings!$D$20)/Settings!$E$20 -> 0.93025825 | Q82: =(I82-Settings!$D$21)/Settings!$E$21 -> 0.02806991 | R82: =(J82-Settings!$D$22)/Settings!$E$22 -> 0.40950899 | S82: =(K82-Settings!$D$23)/Settings!$E$23 -> 2.0729207 | T82: =(L82-Settings!$D$24)/Settings!$E$24 -> 2.8001483 | U82: =(M82-Settings!$D$25)/Settings!$E$25 -> 0.77706056 | V82: =Settings!$B$18*(N82-F$6)^2 -> 0.13484404 | W82: =Settings!$B$19*(O82-G$6)^2 -> 0.052522306 | X82: =Settings!$B$20*(P82-H$6)^2 -> 0.35445904 | Y82: =Settings!$B$21*(Q82-I$6)^2 -> 0.15763895 | Z82: =Settings!$B$22*(R82-J$6)^2 -> 0.013173051 | AA82: =Settings!$B$23*(S82-K$6)^2 -> 0.11907971 | AB82: =Settings!$B$24*(T82-L$6)^2 -> 1.6229039 | AC82: =Settings!$B$25*(U82-M$6)^2 -> 0.91967229 | AD82: =SQRT(SUM(V82:AC82)) -> 1.8369249 | AE82: =AD82/Yardstick -> 0.7270882 | AF82: =EXP(-(AD82^2)/(2*Yardstick^2)) -> 0.76772121 | AG82: =AF82/$E$7 -> 0.0033145594 | AH82: 0.067987623 | AI82: 0 | AJ82: -1.1092736 | AK82: 0 | AL82: 0.84541231 | AM82: 0 | AN82: -0.26095606 | AO82: 0 | AP82: -0.43766738 | AQ82: 1
A83: 73 | B83: Ryan Getzlaf | C83: 2010-11 & 2011-12 | D83: 26 | E83: 0 | F83: 0.23767432 | G83: 0.22683072 | H83: 0.35603775 | I83: 0.014550477 | J83: 0.16490673 | K83: 21.05179 | L83: 2.0754735 | M83: -2.4421694 | N83: =(F83-Settings!$D$18)/Settings!$E$18 -> 0.1623115 | O83: =(G83-Settings!$D$19)/Settings!$E$19 -> 0.97267668 | P83: =(H83-Settings!$D$20)/Settings!$E$20 -> 2.7444279 | Q83: =(I83-Settings!$D$21)/Settings!$E$21 -> 0.21514082 | R83: =(J83-Settings!$D$22)/Settings!$E$22 -> -0.22319299 | S83: =(K83-Settings!$D$23)/Settings!$E$23 -> 2.0130182 | T83: =(L83-Settings!$D$24)/Settings!$E$24 -> 0.53041119 | U83: =(M83-Settings!$D$25)/Settings!$E$25 -> -1.611056 | V83: =Settings!$B$18*(N83-F$6)^2 -> 0.0026713626 | W83: =Settings!$B$19*(O83-G$6)^2 -> 0.043923364 | X83: =Settings!$B$20*(P83-H$6)^2 -> 0.046637298 | Y83: =Settings!$B$21*(Q83-I$6)^2 -> 0.23107093 | Z83: =Settings!$B$22*(R83-J$6)^2 -> 0.02828418 | AA83: =Settings!$B$23*(S83-K$6)^2 -> 0.081325817 | AB83: =Settings!$B$24*(T83-L$6)^2 -> 0.99162691 | AC83: =Settings!$B$25*(U83-M$6)^2 -> 2.0423872 | AD83: =SQRT(SUM(V83:AC83)) -> 1.8622371 | AE83: =AD83/Yardstick -> 0.73710721 | AF83: =EXP(-(AD83^2)/(2*Yardstick^2)) -> 0.76211065 | AG83: =AF83/$E$7 -> 0.0032903364 | AH83: 0.28039221 | AI83: 0 | AJ83: 2.0183811 | AK83: 0 | AL83: -0.25543036 | AM83: 0 | AN83: -1.356779 | AO83: 0 | AP83: -0.53410614 | AQ83: 0
A84: 74 | B84: Alex Debrincat | C84: 2022-23 & 2023-24 | D84: 26 | E84: 1 | F84: 0.3463625 | G84: -0.21539988 | H84: 0.29340415 | I84: 6.525796e-05 | J84: 0.14476821 | K84: 17.871443 | L84: 1.7418518 | M84: 0.89252097 | N84: =(F84-Settings!$D$18)/Settings!$E$18 -> 0.55129973 | O84: =(G84-Settings!$D$19)/Settings!$E$19 -> -0.86971236 | P84: =(H84-Settings!$D$20)/Settings!$E$20 -> 2.1769554 | Q84: =(I84-Settings!$D$21)/Settings!$E$21 -> 0.037011622 | R84: =(J84-Settings!$D$22)/Settings!$E$22 -> -0.27737661 | S84: =(K84-Settings!$D$23)/Settings!$E$23 -> 0.90855702 | T84: =(L84-Settings!$D$24)/Settings!$E$24 -> 0.29976023 | U84: =(M84-Settings!$D$25)/Settings!$E$25 -> 0.63789634 | V84: =Settings!$B$18*(N84-F$6)^2 -> 0.05091614 | W84: =Settings!$B$19*(O84-G$6)^2 -> 0.37744117 | X84: =Settings!$B$20*(P84-H$6)^2 -> 0.0014307087 | Y84: =Settings!$B$21*(Q84-I$6)^2 -> 0.16083033 | Z84: =Settings!$B$22*(R84-J$6)^2 -> 0.037021864 | AA84: =Settings!$B$23*(S84-K$6)^2 -> 0.67122695 | AB84: =Settings!$B$24*(T84-L$6)^2 -> 1.5041934 | AC84: =Settings!$B$25*(U84-M$6)^2 -> 0.67212325 | AD84: =SQRT(SUM(V84:AC84)) -> 1.8641845 | AE84: =AD84/Yardstick -> 0.73787802 | AF84: =EXP(-(AD84^2)/(2*Yardstick^2)) -> 0.76167754 | AG84: =AF84/$E$7 -> 0.0032884665 | AH84: 1.4204148 | AI84: 1 | AJ84: 0.80776552 | AK84: 1
A85: 75 | B85: Eric Staal | C85: 2009-10 & 2010-11 | D85: 26 | E85: 0 | F85: 0.50136699 | G85: -0.23670954 | H85: 0.12357375 | I85: -0.089336089 | J85: 0.049013629 | K85: 20.630889 | L85: 1.4284635 | M85: 0.13588228 | N85: =(F85-Settings!$D$18)/Settings!$E$18 -> 1.1060511 | O85: =(G85-Settings!$D$19)/Settings!$E$19 -> -0.95849113 | P85: =(H85-Settings!$D$20)/Settings!$E$20 -> 0.63825932 | Q85: =(I85-Settings!$D$21)/Settings!$E$21 -> -1.0623842 | R85: =(J85-Settings!$D$22)/Settings!$E$22 -> -0.53500883 | S85: =(K85-Settings!$D$23)/Settings!$E$23 -> 1.8668491 | T85: =(L85-Settings!$D$24)/Settings!$E$24 -> 0.083097799 | U85: =(M85-Settings!$D$25)/Settings!$E$25 -> 0.12761078 | V85: =Settings!$B$18*(N85-F$6)^2 -> 0.22442809 | W85: =Settings!$B$19*(O85-G$6)^2 -> 0.42780166 | X85: =Settings!$B$20*(P85-H$6)^2 -> 0.52700415 | Y85: =Settings!$B$21*(Q85-I$6)^2 -> 0.008213471 | Z85: =Settings!$B$22*(R85-J$6)^2 -> 0.094634553 | AA85: =Settings!$B$23*(S85-K$6)^2 -> 0.019323125 | AB85: =Settings!$B$24*(T85-L$6)^2 -> 2.0825897 | AC85: =Settings!$B$25*(U85-M$6)^2 -> 0.095818527 | AD85: =SQRT(SUM(V85:AC85)) -> 1.8654258 | AE85: =AD85/Yardstick -> 0.73836934 | AF85: =EXP(-(AD85^2)/(2*Yardstick^2)) -> 0.76140137 | AG85: =AF85/$E$7 -> 0.0032872742 | AH85: 0.33650209 | AI85: 0 | AJ85: -0.050314125 | AK85: 0 | AL85: -0.95293337 | AM85: 0 | AN85: 0.24634698 | AO85: 0 | AP85: 0.34559441 | AQ85: 0
A86: 76 | B86: Jason Zucker | C86: 2016-17 & 2017-18 | D86: 26 | E86: 0 | F86: 0.34107097 | G86: 0.14688048 | H86: 0.063006127 | I86: 0.016713821 | J86: 0.43232859 | K86: 15.886439 | L86: 3.7134626 | M86: -0.40094982 | N86: =(F86-Settings!$D$18)/Settings!$E$18 -> 0.53236169 | O86: =(G86-Settings!$D$19)/Settings!$E$19 -> 0.6395938 | P86: =(H86-Settings!$D$20)/Settings!$E$20 -> 0.089505019 | Q86: =(I86-Settings!$D$21)/Settings!$E$21 -> 0.24174413 | R86: =(J86-Settings!$D$22)/Settings!$E$22 -> 0.49631813 | S86: =(K86-Settings!$D$23)/Settings!$E$23 -> 0.21921073 | T86: =(L86-Settings!$D$24)/Settings!$E$24 -> 1.6628427 | U86: =(M86-Settings!$D$25)/Settings!$E$25 -> -0.23443477 | V86: =Settings!$B$18*(N86-F$6)^2 -> 0.047165719 | W86: =Settings!$B$19*(O86-G$6)^2 -> 0.0036747629 | X86: =Settings!$B$20*(P86-H$6)^2 -> 0.943542 | Y86: =Settings!$B$21*(Q86-I$6)^2 -> 0.24265056 | Z86: =Settings!$B$22*(R86-J$6)^2 -> 0.023591775 | AA86: =Settings!$B$23*(S86-K$6)^2 -> 2.2759666 | AB86: =Settings!$B$24*(T86-L$6)^2 -> 0.018666887 | AC86: =Settings!$B$25*(U86-M$6)^2 -> 0.0027562364 | AD86: =SQRT(SUM(V86:AC86)) -> 1.88627 | AE86: =AD86/Yardstick -> 0.74661987 | AF86: =EXP(-(AD86^2)/(2*Yardstick^2)) -> 0.7567513 | AG86: =AF86/$E$7 -> 0.003267198 | AH86: -0.98625285 | AI86: 1 | AJ86: -0.37509183 | AK86: 1 | AL86: -0.73348004 | AM86: 1 | AN86: -1.1651435 | AO86: 1 | AP86: 1.1638157 | AQ86: 1
A87: 77 | B87: Roope Hintz | C87: 2021-22 & 2022-23 | D87: 26 | E87: 1 | F87: 0.20123874 | G87: -0.013076677 | H87: 0.17356392 | I87: 0.048771774 | J87: 0.56334889 | K87: 17.217102 | L87: 4.604906 | M87: 1.1970708 | N87: =(F87-Settings!$D$18)/Settings!$E$18 -> 0.031910829 | O87: =(G87-Settings!$D$19)/Settings!$E$19 -> -0.026808116 | P87: =(H87-Settings!$D$20)/Settings!$E$20 -> 1.0911799 | Q87: =(I87-Settings!$D$21)/Settings!$E$21 -> 0.63597063 | R87: =(J87-Settings!$D$22)/Settings!$E$22 -> 0.8488344 | S87: =(K87-Settings!$D$23)/Settings!$E$23 -> 0.68131955 | T87: =(L87-Settings!$D$24)/Settings!$E$24 -> 2.2791462 | U87: =(M87-Settings!$D$25)/Settings!$E$25 -> 0.84328814 | V87: =Settings!$B$18*(N87-F$6)^2 -> 4.3979809e-05 | W87: =Settings!$B$19*(O87-G$6)^2 -> 0.056360742 | X87: =Settings!$B$20*(P87-H$6)^2 -> 0.27394575 | Y87: =Settings!$B$21*(Q87-I$6)^2 -> 0.44742612 | Z87: =Settings!$B$22*(R87-J$6)^2 -> 0.096874204 | AA87: =Settings!$B$23*(S87-K$6)^2 -> 1.0952081 | AB87: =Settings!$B$24*(T87-L$6)^2 -> 0.56690416 | AC87: =Settings!$B$25*(U87-M$6)^2 -> 1.0510823 | AD87: =SQRT(SUM(V87:AC87)) -> 1.8941608 | AE87: =AD87/Yardstick -> 0.7497432 | AF87: =EXP(-(AD87^2)/(2*Yardstick^2)) -> 0.75498497 | AG87: =AF87/$E$7 -> 0.003259572 | AH87: 0.21792695 | AI87: 1 | AJ87: -1.2461227 | AK87: 1 | AL87: -1.5975014 | AM87: 1
A88: 78 | B88: Paul Stastny | C88: 2010-11 & 2011-12 | D88: 26 | E88: 0 | F88: 0.49280926 | G88: 0.061461969 | H88: 0.28685586 | I88: -0.047772964 | J88: 0.11109995 | K88: 18.693028 | L88: 2.4416319 | M88: 2.034699 | N88: =(F88-Settings!$D$18)/Settings!$E$18 -> 1.0754235 | O88: =(G88-Settings!$D$19)/Settings!$E$19 -> 0.28372938 | P88: =(H88-Settings!$D$20)/Settings!$E$20 -> 2.1176266 | Q88: =(I88-Settings!$D$21)/Settings!$E$21 -> -0.55126971 | R88: =(J88-Settings!$D$22)/Settings!$E$22 -> -0.36796265 | S88: =(K88-Settings!$D$23)/Settings!$E$23 -> 1.1938747 | T88: =(L88-Settings!$D$24)/Settings!$E$24 -> 0.78355652 | U88: =(M88-Settings!$D$25)/Settings!$E$25 -> 1.4081939 | V88: =Settings!$B$18*(N88-F$6)^2 -> 0.21163804 | W88: =Settings!$B$19*(O88-G$6)^2 -> 0.0097076844 | X88: =Settings!$B$20*(P88-H$6)^2 -> 0.0041418687 | Y88: =Settings!$B$21*(Q88-I$6)^2 -> 0.019029972 | Z88: =Settings!$B$22*(R88-J$6)^2 -> 0.054252646 | AA88: =Settings!$B$23*(S88-K$6)^2 -> 0.2851205 | AB88: =Settings!$B$24*(T88-L$6)^2 -> 0.55154286 | AC88: =Settings!$B$25*(U88-M$6)^2 -> 2.5285096 | AD88: =SQRT(SUM(V88:AC88)) -> 1.9141429 | AE88: =AD88/Yardstick -> 0.75765248 | AF88: =EXP(-(AD88^2)/(2*Yardstick^2)) -> 0.75049774 | AG88: =AF88/$E$7 -> 0.0032401989 | AH88: -0.045137004 | AI88: 0 | AJ88: 0.21303433 | AK88: 0 | AL88: -0.17968514 | AM88: 0 | AN88: -1.2761168 | AO88: 0 | AP88: 0.98751932 | AQ88: 0
A89: 79 | B89: Tyler Bozak | C89: 2011-12 & 2012-13 | D89: 26 | E89: 0 | F89: 0.19243494 | G89: -0.20621301 | H89: 0.10717391 | I89: 0.0004914161 | J89: 0.49368672 | K89: 18.993137 | L89: 2.0171058 | M89: 1.3263756 | N89: =(F89-Settings!$D$18)/Settings!$E$18 -> 0.00040257252 | O89: =(G89-Settings!$D$19)/Settings!$E$19 -> -0.83143871 | P89: =(H89-Settings!$D$20)/Settings!$E$20 -> 0.48967361 | Q89: =(I89-Settings!$D$21)/Settings!$E$21 -> 0.042252219 | R89: =(J89-Settings!$D$22)/Settings!$E$22 -> 0.66140507 | S89: =(K89-Settings!$D$23)/Settings!$E$23 -> 1.2980956 | T89: =(L89-Settings!$D$24)/Settings!$E$24 -> 0.49005842 | U89: =(M89-Settings!$D$25)/Settings!$E$25 -> 0.93049272 | V89: =Settings!$B$18*(N89-F$6)^2 -> 0.00042942815 | W89: =Settings!$B$19*(O89-G$6)^2 -> 0.35670268 | X89: =Settings!$B$20*(P89-H$6)^2 -> 0.62789787 | Y89: =Settings!$B$21*(Q89-I$6)^2 -> 0.16271562 | Z89: =Settings!$B$22*(R89-J$6)^2 -> 0.051722252 | AA89: =Settings!$B$23*(S89-K$6)^2 -> 0.18468148 | AB89: =Settings!$B$24*(T89-L$6)^2 -> 1.0736222 | AC89: =Settings!$B$25*(U89-M$6)^2 -> 1.2374952 | AD89: =SQRT(SUM(V89:AC89)) -> 1.9223077 | AE89: =AD89/Yardstick -> 0.76088422 | AF89: =EXP(-(AD89^2)/(2*Yardstick^2)) -> 0.74865846 | AG89: =AF89/$E$7 -> 0.0032322579 | AH89: 0.34961502 | AI89: 0 | AJ89: -0.80288683 | AK89: 0 | AL89: -0.52695577 | AM89: 0 | AN89: 0.12062404 | AO89: 0 | AP89: -0.33561404 | AQ89: 0
A90: 80 | B90: Brandon Hagel | C90: 2023-24 & 2024-25 | D90: 26 | E90: 1 | F90: 0.61415846 | G90: 0.12128076 | H90: -0.058676821 | I90: 0.038771357 | J90: 0.1671126 | K90: 19.168496 | L90: 2.6169507 | M90: 0.38304313 | N90: =(F90-Settings!$D$18)/Settings!$E$18 -> 1.5097248 | O90: =(G90-Settings!$D$19)/Settings!$E$19 -> 0.53294208 | P90: =(H90-Settings!$D$20)/Settings!$E$20 -> -1.0129659 | Q90: =(I90-Settings!$D$21)/Settings!$E$21 -> 0.51299242 | R90: =(J90-Settings!$D$22)/Settings!$E$22 -> -0.21725798 | S90: =(K90-Settings!$D$23)/Settings!$E$23 -> 1.3589936 | T90: =(L90-Settings!$D$24)/Settings!$E$24 -> 0.904764 | U90: =(M90-Settings!$D$25)/Settings!$E$25 -> 0.29429881 | V90: =Settings!$B$18*(N90-F$6)^2 -> 0.428065 | W90: =Settings!$B$19*(O90-G$6)^2 -> 0.00016702261 | X90: =Settings!$B$20*(P90-H$6)^2 -> 2.1444699 | Y90: =Settings!$B$21*(Q90-I$6)^2 -> 0.37687525 | Z90: =Settings!$B$22*(R90-J$6)^2 -> 0.027398458 | AA90: =Settings!$B$23*(S90-K$6)^2 -> 0.13604869 | AB90: =Settings!$B$24*(T90-L$6)^2 -> 0.38620239 | AC90: =Settings!$B$25*(U90-M$6)^2 -> 0.22679854 | AD90: =SQRT(SUM(V90:AC90)) -> 1.9302915 | AE90: =AD90/Yardstick -> 0.76404437 | AF90: =EXP(-(AD90^2)/(2*Yardstick^2)) -> 0.74685673 | AG90: =AF90/$E$7 -> 0.0032244792 | AH90: 0.79993857 | AI90: 1
A91: 81 | B91: Josh Norris | C91: 2024-25 & 2025-26 | D91: 26 | E91: 1 | F91: 0.08107262 | G91: 0.091543132 | H91: 0.033294994 | I91: 0.0017310992 | J91: 0.79235815 | K91: 16.600667 | L91: 2.6115687 | M91: -0.46192103 | N91: =(F91-Settings!$D$18)/Settings!$E$18 -> -0.39815621 | O91: =(G91-Settings!$D$19)/Settings!$E$19 -> 0.40905134 | P91: =(H91-Settings!$D$20)/Settings!$E$20 -> -0.17968356 | Q91: =(I91-Settings!$D$21)/Settings!$E$21 -> 0.057496983 | R91: =(J91-Settings!$D$22)/Settings!$E$22 -> 1.4649946 | S91: =(K91-Settings!$D$23)/Settings!$E$23 -> 0.4672456 | T91: =(L91-Settings!$D$24)/Settings!$E$24 -> 0.90104312 | U91: =(M91-Settings!$D$25)/Settings!$E$25 -> -0.27555443 | V91: =Settings!$B$18*(N91-F$6)^2 -> 0.039586497 | W91: =Settings!$B$19*(O91-G$6)^2 -> 0.0018047116 | X91: =Settings!$B$20*(P91-H$6)^2 -> 1.1919087 | Y91: =Settings!$B$21*(Q91-I$6)^2 -> 0.16826232 | Z91: =Settings!$B$22*(R91-J$6)^2 -> 0.34433592 | AA91: =Settings!$B$23*(S91-K$6)^2 -> 1.5891019 | AB91: =Settings!$B$24*(T91-L$6)^2 -> 0.39084093 | AC91: =Settings!$B$25*(U91-M$6)^2 -> 0.0087646172 | AD91: =SQRT(SUM(V91:AC91)) -> 1.9325127 | AE91: =AD91/Yardstick -> 0.76492358 | AF91: =EXP(-(AD91^2)/(2*Yardstick^2)) -> 0.74635491 | AG91: =AF91/$E$7 -> 0.0032223126
A92: 82 | B92: Brendan Gallagher | C92: 2017-18 & 2018-19 | D92: 26 | E92: 1 | F92: 0.63537293 | G92: -0.001269956 | H92: 0.10610496 | I92: -0.0037904481 | J92: 0.25346171 | K92: 15.767378 | L92: 3.2140584 | M92: -0.17160261 | N92: =(F92-Settings!$D$18)/Settings!$E$18 -> 1.58565 | O92: =(G92-Settings!$D$19)/Settings!$E$19 -> 0.022380188 | P92: =(H92-Settings!$D$20)/Settings!$E$20 -> 0.47998872 | Q92: =(I92-Settings!$D$21)/Settings!$E$21 -> -0.010403182 | R92: =(J92-Settings!$D$22)/Settings!$E$22 -> 0.015068353 | S92: =(K92-Settings!$D$23)/Settings!$E$23 -> 0.17786363 | T92: =(L92-Settings!$D$24)/Settings!$E$24 -> 1.3175772 | U92: =(M92-Settings!$D$25)/Settings!$E$25 -> -0.079760453 | V92: =Settings!$B$18*(N92-F$6)^2 -> 0.47364893 | W92: =Settings!$B$19*(O92-G$6)^2 -> 0.046399958 | X92: =Settings!$B$20*(P92-H$6)^2 -> 0.63478074 | Y92: =Settings!$B$21*(Q92-I$6)^2 -> 0.14427237 | Z92: =Settings!$B$22*(R92-J$6)^2 -> 0.0037976776 | AA92: =Settings!$B$23*(S92-K$6)^2 -> 2.4024312 | AB92: =Settings!$B$24*(T92-L$6)^2 -> 0.043530094 | AC92: =Settings!$B$25*(U92-M$6)^2 -> 0.010439617 | AD92: =SQRT(SUM(V92:AC92)) -> 1.9388916 | AE92: =AD92/Yardstick -> 0.76744844 | AF92: =EXP(-(AD92^2)/(2*Yardstick^2)) -> 0.74491247 | AG92: =AF92/$E$7 -> 0.003216085 | AH92: -0.65333441 | AI92: 1 | AJ92: 0.32451948 | AK92: 1 | AL92: -1.3830184 | AM92: 1 | AN92: -1.8360605 | AO92: 1 | AP92: 1.0077058 | AQ92: 1
A93: 83 | B93: Chris Kreider | C93: 2016-17 & 2017-18 | D93: 26 | E93: 0 | F93: 0.32621378 | G93: 0.15183618 | H93: 0.086689131 | I93: -1.6054933e-05 | J93: 0.43524485 | K93: 16.016792 | L93: 2.331401 | M93: -0.25641183 | N93: =(F93-Settings!$D$18)/Settings!$E$18 -> 0.47918872 | O93: =(G93-Settings!$D$19)/Settings!$E$19 -> 0.66023988 | P93: =(H93-Settings!$D$20)/Settings!$E$20 -> 0.30407758 | Q93: =(I93-Settings!$D$21)/Settings!$E$21 -> 0.036011692 | R93: =(J93-Settings!$D$22)/Settings!$E$22 -> 0.50416445 | S93: =(K93-Settings!$D$23)/Settings!$E$23 -> 0.26447935 | T93: =(L93-Settings!$D$24)/Settings!$E$24 -> 0.70734783 | U93: =(M93-Settings!$D$25)/Settings!$E$25 -> -0.13695674 | V93: =Settings!$B$18*(N93-F$6)^2 -> 0.03740241 | W93: =Settings!$B$19*(O93-G$6)^2 -> 0.0048794462 | X93: =Settings!$B$20*(P93-H$6)^2 -> 0.76632715 | Y93: =Settings!$B$21*(Q93-I$6)^2 -> 0.16047186 | Z93: =Settings!$B$22*(R93-J$6)^2 -> 0.02468202 | AA93: =Settings!$B$23*(S93-K$6)^2 -> 2.1414286 | AB93: =Settings!$B$24*(T93-L$6)^2 -> 0.67054481 | AC93: =Settings!$B$25*(U93-M$6)^2 -> 0.0020230348 | AD93: =SQRT(SUM(V93:AC93)) -> 1.9513481 | AE93: =AD93/Yardstick -> 0.77237895 | AF93: =EXP(-(AD93^2)/(2*Yardstick^2)) -> 0.7420901 | AG93: =AF93/$E$7 -> 0.0032038997 | AH93: 0.13881921 | AI93: 1 | AJ93: -0.12981016 | AK93: 1 | AL93: 0.31577574 | AM93: 1 | AN93: 1.9174943 | AO93: 1 | AP93: -0.22454855 | AQ93: 1
A94: 84 | B94: Sean Couturier | C94: 2017-18 & 2018-19 | D94: 26 | E94: 1 | F94: 0.36217547 | G94: 0.12438764 | H94: 0.19033506 | I94: 0.023802307 | J94: 0.29929952 | K94: 21.026749 | L94: 3.6886338 | M94: 2.3302024 | N94: =(F94-Settings!$D$18)/Settings!$E$18 -> 0.60789338 | O94: =(G94-Settings!$D$19)/Settings!$E$19 -> 0.54588576 | P94: =(H94-Settings!$D$20)/Settings!$E$20 -> 1.2431296 | Q94: =(I94-Settings!$D$21)/Settings!$E$21 -> 0.32891342 | R94: =(J94-Settings!$D$22)/Settings!$E$22 -> 0.13839713 | S94: =(K94-Settings!$D$23)/Settings!$E$23 -> 2.0043222 | T94: =(L94-Settings!$D$24)/Settings!$E$24 -> 1.6456771 | U94: =(M94-Settings!$D$25)/Settings!$E$25 -> 1.6074847 | V94: =Settings!$B$18*(N94-F$6)^2 -> 0.062978662 | W94: =Settings!$B$19*(O94-G$6)^2 -> 0.00035015074 | X94: =Settings!$B$20*(P94-H$6)^2 -> 0.20742951 | Y94: =Settings!$B$21*(Q94-I$6)^2 -> 0.28257626 | Z94: =Settings!$B$22*(R94-J$6)^2 -> 4.1873749e-05 | AA94: =Settings!$B$23*(S94-K$6)^2 -> 0.076441602 | AB94: =Settings!$B$24*(T94-L$6)^2 -> 0.014270998 | AC94: =Settings!$B$25*(U94-M$6)^2 -> 3.2020226 | AD94: =SQRT(SUM(V94:AC94)) -> 1.9611506 | AE94: =AD94/Yardstick -> 0.77625896 | AF94: =EXP(-(AD94^2)/(2*Yardstick^2)) -> 0.73986393 | AG94: =AF94/$E$7 -> 0.0031942884 | AH94: -0.17025029 | AI94: 1 | AJ94: -0.53063355 | AK94: 1 | AL94: -0.85960994 | AM94: 1
A95: 85 | B95: Jakob Silfverberg | C95: 2015-16 & 2016-17 | D95: 26 | E95: 0 | F95: 0.35872671 | G95: 0.12999246 | H95: -0.014986073 | I95: -0.073560058 | J95: 0.4227347 | K95: 17.305797 | L95: 2.0534011 | M95: 0.039116891 | N95: =(F95-Settings!$D$18)/Settings!$E$18 -> 0.59555046 | O95: =(G95-Settings!$D$19)/Settings!$E$19 -> 0.56923616 | P95: =(H95-Settings!$D$20)/Settings!$E$20 -> -0.61711932 | Q95: =(I95-Settings!$D$21)/Settings!$E$21 -> -0.86838153 | R95: =(J95-Settings!$D$22)/Settings!$E$22 -> 0.4705053 | S95: =(K95-Settings!$D$23)/Settings!$E$23 -> 0.71212118 | T95: =(L95-Settings!$D$24)/Settings!$E$24 -> 0.51515131 | U95: =(M95-Settings!$D$25)/Settings!$E$25 -> 0.062351125 | V95: =Settings!$B$18*(N95-F$6)^2 -> 0.060238624 | W95: =Settings!$B$19*(O95-G$6)^2 -> 0.0008500099 | X95: =Settings!$B$20*(P95-H$6)^2 -> 1.657329 | Y95: =Settings!$B$21*(Q95-I$6)^2 -> 1.4957951e-05 | Z95: =Settings!$B$22*(R95-J$6)^2 -> 0.020178854 | AA95: =Settings!$B$23*(S95-K$6)^2 -> 1.0316876 | AB95: =Settings!$B$24*(T95-L$6)^2 -> 1.0222515 | AC95: =Settings!$B$25*(U95-M$6)^2 -> 0.05967566 | AD95: =SQRT(SUM(V95:AC95)) -> 1.9627089 | AE95: =AD95/Yardstick -> 0.77687577 | AF95: =EXP(-(AD95^2)/(2*Yardstick^2)) -> 0.73950963 | AG95: =AF95/$E$7 -> 0.0031927588 | AH95: -0.7113227 | AI95: 0 | AJ95: 0.14574676 | AK95: 1 | AL95: 1.1698346 | AM95: 1 | AN95: -0.97633232 | AO95: 1 | AP95: -1.9212486 | AQ95: 1
A96: 86 | B96: Tyler Johnson | C96: 2015-16 & 2016-17 | D96: 26 | E96: 0 | F96: 0.1859666 | G96: -0.16755031 | H96: 0.12699372 | I96: -0.03066164 | J96: 0.48882773 | K96: 17.429259 | L96: 1.5334644 | M96: 0.29279462 | N96: =(F96-Settings!$D$18)/Settings!$E$18 -> -0.022747211 | O96: =(G96-Settings!$D$19)/Settings!$E$19 -> -0.67036496 | P96: =(H96-Settings!$D$20)/Settings!$E$20 -> 0.66924492 | Q96: =(I96-Settings!$D$21)/Settings!$E$21 -> -0.34084649 | R96: =(J96-Settings!$D$22)/Settings!$E$22 -> 0.64833172 | S96: =(K96-Settings!$D$23)/Settings!$E$23 -> 0.75499674 | T96: =(L96-Settings!$D$24)/Settings!$E$24 -> 0.15569062 | U96: =(M96-Settings!$D$25)/Settings!$E$25 -> 0.23343421 | V96: =Settings!$B$18*(N96-F$6)^2 -> 0.00096568956 | W96: =Settings!$B$19*(O96-G$6)^2 -> 0.27584716 | X96: =Settings!$B$20*(P96-H$6)^2 -> 0.50707692 | Y96: =Settings!$B$21*(Q96-I$6)^2 -> 0.053848728 | Z96: =Settings!$B$22*(R96-J$6)^2 -> 0.049097116 | AA96: =Settings!$B$23*(S96-K$6)^2 -> 0.94642678 | AB96: =Settings!$B$24*(T96-L$6)^2 -> 1.8783394 | AC96: =Settings!$B$25*(U96-M$6)^2 -> 0.17253149 | AD96: =SQRT(SUM(V96:AC96)) -> 1.9708205 | AE96: =AD96/Yardstick -> 0.78008647 | AF96: =EXP(-(AD96^2)/(2*Yardstick^2)) -> 0.73766355 | AG96: =AF96/$E$7 -> 0.0031847885 | AH96: -0.33190598 | AI96: 0 | AJ96: 0.31652917 | AK96: 1 | AL96: 0.1338752 | AM96: 1 | AN96: -1.0543444 | AO96: 1 | AP96: -0.53977198 | AQ96: 1
A97: 87 | B97: Robert Thomas | C97: 2024-25 & 2025-26 | D97: 26 | E97: 1 | F97: 0.5004622 | G97: 0.0700092 | H97: 0.092813621 | I97: -0.024946907 | J97: 0.31176808 | K97: 18.676368 | L97: 4.6221732 | M97: 1.8018314 | N97: =(F97-Settings!$D$18)/Settings!$E$18 -> 1.1028129 | O97: =(G97-Settings!$D$19)/Settings!$E$19 -> 0.31933824 | P97: =(H97-Settings!$D$20)/Settings!$E$20 -> 0.35956664 | Q97: =(I97-Settings!$D$21)/Settings!$E$21 -> -0.27057066 | R97: =(J97-Settings!$D$22)/Settings!$E$22 -> 0.17194438 | S97: =(K97-Settings!$D$23)/Settings!$E$23 -> 1.188089 | T97: =(L97-Settings!$D$24)/Settings!$E$24 -> 2.291084 | U97: =(M97-Settings!$D$25)/Settings!$E$25 -> 1.2511454 | V97: =Settings!$B$18*(N97-F$6)^2 -> 0.22305808 | W97: =Settings!$B$19*(O97-G$6)^2 -> 0.0068232258 | X97: =Settings!$B$20*(P97-H$6)^2 -> 0.72349599 | Y97: =Settings!$B$21*(Q97-I$6)^2 -> 0.069422551 | Z97: =Settings!$B$22*(R97-J$6)^2 -> 7.2791505e-05 | AA97: =Settings!$B$23*(S97-K$6)^2 -> 0.29133271 | AB97: =Settings!$B$24*(T97-L$6)^2 -> 0.58502328 | AC97: =Settings!$B$25*(U97-M$6)^2 -> 2.0537191 | AD97: =SQRT(SUM(V97:AC97)) -> 1.9882021 | AE97: =AD97/Yardstick -> 0.78696645 | AF97: =EXP(-(AD97^2)/(2*Yardstick^2)) -> 0.73369777 | AG97: =AF97/$E$7 -> 0.0031676666
A98: 88 | B98: Marcus Johansson | C98: 2015-16 & 2016-17 | D98: 26 | E98: 0 | F98: 0.081292157 | G98: 0.15696233 | H98: 0.14393682 | I98: 0.00053397552 | J98: 0.61727472 | K98: 16.502671 | L98: 2.9081064 | M98: 1.3951171 | N98: =(F98-Settings!$D$18)/Settings!$E$18 -> -0.39737051 | O98: =(G98-Settings!$D$19)/Settings!$E$19 -> 0.68159605 | P98: =(H98-Settings!$D$20)/Settings!$E$20 -> 0.82275268 | Q98: =(I98-Settings!$D$21)/Settings!$E$21 -> 0.042775586 | R98: =(J98-Settings!$D$22)/Settings!$E$22 -> 0.99392438 | S98: =(K98-Settings!$D$23)/Settings!$E$23 -> 0.43321393 | T98: =(L98-Settings!$D$24)/Settings!$E$24 -> 1.1060558 | U98: =(M98-Settings!$D$25)/Settings!$E$25 -> 0.97685277 | V98: =Settings!$B$18*(N98-F$6)^2 -> 0.039446797 | W98: =Settings!$B$19*(O98-G$6)^2 -> 0.0063049637 | X98: =Settings!$B$20*(P98-H$6)^2 -> 0.41401836 | Y98: =Settings!$B$21*(Q98-I$6)^2 -> 0.1629045 | Z98: =Settings!$B$22*(R98-J$6)^2 -> 0.1414756 | AA98: =Settings!$B$23*(S98-K$6)^2 -> 1.6760604 | AB98: =Settings!$B$24*(T98-L$6)^2 -> 0.17653444 | AC98: =Settings!$B$25*(U98-M$6)^2 -> 1.3427889 | AD98: =SQRT(SUM(V98:AC98)) -> 1.9898578 | AE98: =AD98/Yardstick -> 0.78762177 | AF98: =EXP(-(AD98^2)/(2*Yardstick^2)) -> 0.73331933 | AG98: =AF98/$E$7 -> 0.0031660328 | AH98: -1.0193047 | AI98: 0 | AJ98: -1.5307564 | AK98: 1 | AL98: 0.30006361 | AM98: 1 | AN98: -0.3637429 | AO98: 1 | AP98: -0.14425088 | AQ98: 1
A99: 89 | B99: Kyle Turris | C99: 2014-15 & 2015-16 | D99: 26 | E99: 0 | F99: 0.31387024 | G99: -0.18744873 | H99: 0.17236366 | I99: 0.0059114242 | J99: 0.32040595 | K99: 18.955156 | L99: 1.1029167 | M99: -0.99132911 | N99: =(F99-Settings!$D$18)/Settings!$E$18 -> 0.43501194 | O99: =(G99-Settings!$D$19)/Settings!$E$19 -> -0.75326431 | P99: =(H99-Settings!$D$20)/Settings!$E$20 -> 1.0803053 | Q99: =(I99-Settings!$D$21)/Settings!$E$21 -> 0.10890373 | R99: =(J99-Settings!$D$22)/Settings!$E$22 -> 0.19518498 | S99: =(K99-Settings!$D$23)/Settings!$E$23 -> 1.2849055 | T99: =(L99-Settings!$D$24)/Settings!$E$24 -> -0.14197054 | U99: =(M99-Settings!$D$25)/Settings!$E$25 -> -0.63259314 | V99: =Settings!$B$18*(N99-F$6)^2 -> 0.030151048 | W99: =Settings!$B$19*(O99-G$6)^2 -> 0.31616472 | X99: =Settings!$B$20*(P99-H$6)^2 -> 0.27906026 | Y99: =Settings!$B$21*(Q99-I$6)^2 -> 0.18765158 | Z99: =Settings!$B$22*(R99-J$6)^2 -> 0.00035816714 | AA99: =Settings!$B$23*(S99-K$6)^2 -> 0.1961922 | AB99: =Settings!$B$24*(T99-L$6)^2 -> 2.7828458 | AC99: =Settings!$B$25*(U99-M$6)^2 -> 0.20309285 | AD99: =SQRT(SUM(V99:AC99)) -> 1.9988788 | AE99: =AD99/Yardstick -> 0.79119248 | AF99: =EXP(-(AD99^2)/(2*Yardstick^2)) -> 0.7312552 | AG99: =AF99/$E$7 -> 0.0031571211 | AH99: 0.2109114 | AI99: 0 | AJ99: 0.34623574 | AK99: 0 | AL99: -1.2175305 | AM99: 1 | AN99: -0.79546139 | AO99: 1 | AP99: -0.33140339 | AQ99: 1
A100: 90 | B100: Tomas Plekanec | C100: 2007-08 & 2008-09 | D100: 26 | E100: 0 | F100: 0.25602472 | G100: 0.038060731 | H100: 0.042415605 | I100: 0.035278024 | J100: 0.62822092 | K100: 17.185744 | L100: 2.3348218 | M100: -1.4456613 | N100: =(F100-Settings!$D$18)/Settings!$E$18 -> 0.22798646 | O100: =(G100-Settings!$D$19)/Settings!$E$19 -> 0.18623684 | P100: =(H100-Settings!$D$20)/Settings!$E$20 -> -0.097049071 | Q100: =(I100-Settings!$D$21)/Settings!$E$21 -> 0.47003383 | R100: =(J100-Settings!$D$22)/Settings!$E$22 -> 1.0233756 | S100: =(K100-Settings!$D$23)/Settings!$E$23 -> 0.67042958 | T100: =(L100-Settings!$D$24)/Settings!$E$24 -> 0.70971285 | U100: =(M100-Settings!$D$25)/Settings!$E$25 -> -0.93899981 | V100: =Settings!$B$18*(N100-F$6)^2 -> 0.0065700689 | W100: =Settings!$B$19*(O100-G$6)^2 -> 0.020200247 | X100: =Settings!$B$20*(P100-H$6)^2 -> 1.1125828 | Y100: =Settings!$B$21*(Q100-I$6)^2 -> 0.35365619 | Z100: =Settings!$B$22*(R100-J$6)^2 -> 0.15155716 | AA100: =Settings!$B$23*(S100-K$6)^2 -> 1.1181198 | AB100: =Settings!$B$24*(T100-L$6)^2 -> 0.66667714 | AC100: =Settings!$B$25*(U100-M$6)^2 -> 0.57314729 | AD100: =SQRT(SUM(V100:AC100)) -> 2.0006276 | AE100: =AD100/Yardstick -> 0.79188467 | AF100: =EXP(-(AD100^2)/(2*Yardstick^2)) -> 0.73085466 | AG100: =AF100/$E$7 -> 0.0031553918 | AH100: -0.87862345 | AI100: 0 | AJ100: 0.26249705 | AK100: 0 | AL100: -0.40428124 | AM100: 0 | AN100: -0.32737645 | AO100: 0 | AP100: 0.39756264 | AQ100: 0
A101: 91 | B101: Anthony Mantha | C101: 2019-20 & 2020-21 | D101: 26 | E101: 1 | F101: 0.48386599 | G101: 0.18287978 | H101: -0.020454065 | I101: 0.00032867852 | J101: 0.31247149 | K101: 17.762458 | L101: 2.0794687 | M101: -1.0364567 | N101: =(F101-Settings!$D$18)/Settings!$E$18 -> 1.0434161 | O101: =(G101-Settings!$D$19)/Settings!$E$19 -> 0.78957145 | P101: =(H101-Settings!$D$20)/Settings!$E$20 -> -0.66666037 | Q101: =(I101-Settings!$D$21)/Settings!$E$21 -> 0.040250985 | R101: =(J101-Settings!$D$22)/Settings!$E$22 -> 0.17383696 | S101: =(K101-Settings!$D$23)/Settings!$E$23 -> 0.87070897 | T101: =(L101-Settings!$D$24)/Settings!$E$24 -> 0.53317331 | U101: =(M101-Settings!$D$25)/Settings!$E$25 -> -0.66302771 | V101: =Settings!$B$18*(N101-F$6)^2 -> 0.19867274 | W101: =Settings!$B$19*(O101-G$6)^2 -> 0.016305213 | X101: =Settings!$B$20*(P101-H$6)^2 -> 1.7148645 | Y101: =Settings!$B$21*(Q101-I$6)^2 -> 0.16199439 | Z101: =Settings!$B$22*(R101-J$6)^2 -> 8.7950218e-05 | AA101: =Settings!$B$23*(S101-K$6)^2 -> 0.73467605 | AB101: =Settings!$B$24*(T101-L$6)^2 -> 0.98613347 | AC101: =Settings!$B$25*(U101-M$6)^2 -> 0.23145029 | AD101: =SQRT(SUM(V101:AC101)) -> 2.0110158 | AE101: =AD101/Yardstick -> 0.79599652 | AF101: =EXP(-(AD101^2)/(2*Yardstick^2)) -> 0.72847263 | AG101: =AF101/$E$7 -> 0.0031451076 | AH101: -0.74864879 | AI101: 1 | AJ101: -0.17705273 | AK101: 1 | AL101: 1.2757215 | AM101: 1
A102: 92 | B102: Nico Hischier | C102: 2023-24 & 2024-25 | D102: 26 | E102: 1 | F102: 0.31232553 | G102: -0.066226085 | H102: 0.14631988 | I102: -0.062026833 | J102: 0.41310167 | K102: 19.063014 | L102: 4.5220246 | M102: 2.1849727 | N102: =(F102-Settings!$D$18)/Settings!$E$18 -> 0.42948355 | O102: =(G102-Settings!$D$19)/Settings!$E$19 -> -0.24823532 | P102: =(H102-Settings!$D$20)/Settings!$E$20 -> 0.84434365 | Q102: =(I102-Settings!$D$21)/Settings!$E$21 -> -0.72655391 | R102: =(J102-Settings!$D$22)/Settings!$E$22 -> 0.44458718 | S102: =(K102-Settings!$D$23)/Settings!$E$23 -> 1.3223621 | T102: =(L102-Settings!$D$24)/Settings!$E$24 -> 2.2218458 | U102: =(M102-Settings!$D$25)/Settings!$E$25 -> 1.5095402 | V102: =Settings!$B$18*(N102-F$6)^2 -> 0.029298552 | W102: =Settings!$B$19*(O102-G$6)^2 -> 0.11318476 | X102: =Settings!$B$20*(P102-H$6)^2 -> 0.40168571 | Y102: =Settings!$B$21*(Q102-I$6)^2 -> 0.0035473561 | Z102: =Settings!$B$22*(R102-J$6)^2 -> 0.017020166 | AA102: =Settings!$B$23*(S102-K$6)^2 -> 0.1644135 | AB102: =Settings!$B$24*(T102-L$6)^2 -> 0.48390101 | AC102: =Settings!$B$25*(U102-M$6)^2 -> 2.8610879 | AD102: =SQRT(SUM(V102:AC102)) -> 2.0184496 | AE102: =AD102/Yardstick -> 0.79893896 | AF102: =EXP(-(AD102^2)/(2*Yardstick^2)) -> 0.72676527 | AG102: =AF102/$E$7 -> 0.0031377363 | AH102: -0.53457753 | AI102: 1
...

Sheet OReilly 4 Aging path
A1: Ryan O'Reilly: from comparables to projected WAR
A3: Step A. Pull his starting curve level toward 'players like him'
A4: The aging curve runs in WAR per 82 games. It starts from his own two-season level, then pulls 45% of the way toward the weighted level of his comparables. That comparable level is itself blended with the league average for forwards of his age, which counts as if it were one more comparable carrying K_league units of weight.
A7: His own level (WAR per 82, two-season average) | B7: ='OReilly 2 Profile'!$D$16 -> 3.5158407
A8: Comparables' weighted level (their own production-level measure) | B8: =SUMPRODUCT('OReilly 3 Comparables'!$AF$11:$AF$481,'OReilly 3 Comparables'!$L$11:$L$481)/SUM('OReilly 3 Comparables'!$AF$11:$AF$481) -> 1.9625594
A9: Sum of comparable weights | B9: =SUM('OReilly 3 Comparables'!$AF$11:$AF$481) -> 231.62089
A10: League average level, forwards aged 26 | B10: 1.3602982
A11: Weight on the league average | B11: =K_league -> 10
A12: 'Players like him' level = (weighted comparables + league) / total weight | B12: =(SUMPRODUCT('OReilly 3 Comparables'!$AF$11:$AF$481,'OReilly 3 Comparables'!$L$11:$L$481)+B11*B10)/(B9+B11) -> 1.9376335
A13: Share of that level coming from the comparables | B13: =B9/(B9+B11) -> 0.95861285
A14: Share kept from his own level | B14: =Lambda -> 0.55
A15: Starting curve level at age 26 = kept x own + (1 - kept) x players-like-him | B15: =B14*B7+(1-B14)*B12 -> 2.8056475
A18: Step B. Walk the curve forward one year at a time
A19: Each year's change is the weighted average of what his comparables' production did over that same year of age, using only comparables still playing at both ages, again blended with the league average change for forwards of that age. The weights are the same ones set at age 26; comparables who drop out simply stop contributing (the count falls).
A21: From age | B21: To age | C21: Comparables with both seasons | D21: Their total weight | E21: Comparables' weighted change | F21: League average change | G21: Change used | H21: Curve level (WAR per 82) | I21: Share of weight from changes after valuation date
A22: start (age 26) | H22: =B15 -> 2.8056475
A23: 26 | B23: 27 | C23: =SUMPRODUCT(ISNUMBER('OReilly 3 Comparables'!$AH$11:$AH$481)*1) -> 407 | D23: =SUMPRODUCT('OReilly 3 Comparables'!$AF$11:$AF$481,ISNUMBER('OReilly 3 Comparables'!$AH$11:$AH$481)*1) -> 208.80572 | E23: =IF(D23>0,SUMPRODUCT('OReilly 3 Comparables'!$AF$11:$AF$481,'OReilly 3 Comparables'!$AH$11:$AH$481)/D23,NA()) -> -0.13044417 | F23: -0.074807391 | G23: =(SUMPRODUCT('OReilly 3 Comparables'!$AF$11:$AF$481,'OReilly 3 Comparables'!$AH$11:$AH$481)+K_league*F23)/(D23+K_league) -> -0.12790142 | H23: =H22+G23 -> 2.6777461 | I23: =IF(D23>0,SUMPRODUCT('OReilly 3 Comparables'!$AF$11:$AF$481,'OReilly 3 Comparables'!$AI$11:$AI$481)/D23,NA()) -> 0.6098999
A24: 27 | B24: 28 | C24: =SUMPRODUCT(ISNUMBER('OReilly 3 Comparables'!$AJ$11:$AJ$481)*1) -> 358 | D24: =SUMPRODUCT('OReilly 3 Comparables'!$AF$11:$AF$481,ISNUMBER('OReilly 3 Comparables'!$AJ$11:$AJ$481)*1) -> 188.033 | E24: =IF(D24>0,SUMPRODUCT('OReilly 3 Comparables'!$AF$11:$AF$481,'OReilly 3 Comparables'!$AJ$11:$AJ$481)/D24,NA()) -> -0.15037115 | F24: -0.10426367 | G24: =(SUMPRODUCT('OReilly 3 Comparables'!$AF$11:$AF$481,'OReilly 3 Comparables'!$AJ$11:$AJ$481)+K_league*F24)/(D24+K_league) -> -0.14804288 | H24: =H23+G24 -> 2.5297032 | I24: =IF(D24>0,SUMPRODUCT('OReilly 3 Comparables'!$AF$11:$AF$481,'OReilly 3 Comparables'!$AK$11:$AK$481)/D24,NA()) -> 0.63116917
A25: 28 | B25: 29 | C25: =SUMPRODUCT(ISNUMBER('OReilly 3 Comparables'!$AL$11:$AL$481)*1) -> 304 | D25: =SUMPRODUCT('OReilly 3 Comparables'!$AF$11:$AF$481,ISNUMBER('OReilly 3 Comparables'!$AL$11:$AL$481)*1) -> 165.66351 | E25: =IF(D25>0,SUMPRODUCT('OReilly 3 Comparables'!$AF$11:$AF$481,'OReilly 3 Comparables'!$AL$11:$AL$481)/D25,NA()) -> -0.1721169 | F25: -0.15825445 | G25: =(SUMPRODUCT('OReilly 3 Comparables'!$AF$11:$AF$481,'OReilly 3 Comparables'!$AL$11:$AL$481)+K_league*F25)/(D25+K_league) -> -0.17132775 | H25: =H24+G25 -> 2.3583754 | I25: =IF(D25>0,SUMPRODUCT('OReilly 3 Comparables'!$AF$11:$AF$481,'OReilly 3 Comparables'!$AM$11:$AM$481)/D25,NA()) -> 0.68301538
A26: 29 | B26: 30 | C26: =SUMPRODUCT(ISNUMBER('OReilly 3 Comparables'!$AN$11:$AN$481)*1) -> 252 | D26: =SUMPRODUCT('OReilly 3 Comparables'!$AF$11:$AF$481,ISNUMBER('OReilly 3 Comparables'!$AN$11:$AN$481)*1) -> 137.98178 | E26: =IF(D26>0,SUMPRODUCT('OReilly 3 Comparables'!$AF$11:$AF$481,'OReilly 3 Comparables'!$AN$11:$AN$481)/D26,NA()) -> -0.15905905 | F26: -0.16385423 | G26: =(SUMPRODUCT('OReilly 3 Comparables'!$AF$11:$AF$481,'OReilly 3 Comparables'!$AN$11:$AN$481)+K_league*F26)/(D26+K_league) -> -0.15938308 | H26: =H25+G26 -> 2.1989923 | I26: =IF(D26>0,SUMPRODUCT('OReilly 3 Comparables'!$AF$11:$AF$481,'OReilly 3 Comparables'!$AO$11:$AO$481)/D26,NA()) -> 0.70745372
A27: 30 | B27: 31 | C27: =SUMPRODUCT(ISNUMBER('OReilly 3 Comparables'!$AP$11:$AP$481)*1) -> 214 | D27: =SUMPRODUCT('OReilly 3 Comparables'!$AF$11:$AF$481,ISNUMBER('OReilly 3 Comparables'!$AP$11:$AP$481)*1) -> 119.93933 | E27: =IF(D27>0,SUMPRODUCT('OReilly 3 Comparables'!$AF$11:$AF$481,'OReilly 3 Comparables'!$AP$11:$AP$481)/D27,NA()) -> -0.13648542 | F27: -0.12637188 | G27: =(SUMPRODUCT('OReilly 3 Comparables'!$AF$11:$AF$481,'OReilly 3 Comparables'!$AP$11:$AP$481)+K_league*F27)/(D27+K_league) -> -0.13570709 | H27: =H26+G27 -> 2.0632852 | I27: =IF(D27>0,SUMPRODUCT('OReilly 3 Comparables'!$AF$11:$AF$481,'OReilly 3 Comparables'!$AQ$11:$AQ$481)/D27,NA()) -> 0.76653021
A30: Step C. Turn the curve into projected WAR for each contract season
A31: The curve is used only for its SHAPE. Each season's multiplier = curve level that season / curve level in the valuation season (age 27). Projected WAR = starting level (a season total, sheet 1) x multiplier, with the multiplier kept between RatioFloor and RatioCap. If the curve level in the valuation season is at or below BaseFloor, the projection holds flat. The valuation season itself always has multiplier 1.
A33: Contract season | B33: Age | C33: Curve level (WAR per 82) | D33: Multiplier (raw) | E33: Multiplier used | F33: Starting level (WAR) | G33: Projected WAR | H33: Hindsight: actual games | I33: Hindsight: actual WAR (season-length adjusted)
A34: 2018-19 | B34: 27 | C34: =IFERROR(INDEX($H$22:$H$27,MATCH(B34,$B$22:$B$27,0)),$H$27) -> 2.6777461 | D34: =C34/$C$34 -> 1 | E34: =IF($C$34<=BaseFloor,1,MIN(MAX(D34,RatioFloor),RatioCap)) -> 1 | F34: ='OReilly 1 Seasons'!$D$30 -> 3.2796017 | G34: =IF(F34>=0,F34*E34,F34) -> 3.2796017 | H34: ='OReilly 1 Seasons'!$D$14 -> 82 | I34: ='OReilly 1 Seasons'!$N$14 -> 3.944498
A35: 2019-20 | B35: 28 | C35: =IFERROR(INDEX($H$22:$H$27,MATCH(B35,$B$22:$B$27,0)),$H$27) -> 2.5297032 | D35: =C35/$C$34 -> 0.94471362 | E35: =IF($C$34<=BaseFloor,1,MIN(MAX(D35,RatioFloor),RatioCap)) -> 0.94471362 | F35: ='OReilly 1 Seasons'!$D$30 -> 3.2796017 | G35: =IF(F35>=0,F35*E35,0) -> 3.0982844 | H35: ='OReilly 1 Seasons'!$D$15 -> 71 | I35: ='OReilly 1 Seasons'!$N$15 -> 2.1685915
A36: 2020-21 | B36: 29 | C36: =IFERROR(INDEX($H$22:$H$27,MATCH(B36,$B$22:$B$27,0)),$H$27) -> 2.3583754 | D36: =C36/$C$34 -> 0.88073155 | E36: =IF($C$34<=BaseFloor,1,MIN(MAX(D36,RatioFloor),RatioCap)) -> 0.88073155 | F36: ='OReilly 1 Seasons'!$D$30 -> 3.2796017 | G36: =IF(F36>=0,F36*E36,0) -> 2.8884487 | H36: ='OReilly 1 Seasons'!$D$16 -> 56 | I36: ='OReilly 1 Seasons'!$N$16 -> 3.6461639
A37: 2021-22 | B37: 30 | C37: =IFERROR(INDEX($H$22:$H$27,MATCH(B37,$B$22:$B$27,0)),$H$27) -> 2.1989923 | D37: =C37/$C$34 -> 0.82121019 | E37: =IF($C$34<=BaseFloor,1,MIN(MAX(D37,RatioFloor),RatioCap)) -> 0.82121019 | F37: ='OReilly 1 Seasons'!$D$30 -> 3.2796017 | G37: =IF(F37>=0,F37*E37,0) -> 2.6932423 | H37: ='OReilly 1 Seasons'!$D$17 -> 78 | I37: ='OReilly 1 Seasons'!$N$17 -> 2.2179611
A38: 2022-23 | B38: 31 | C38: =IFERROR(INDEX($H$22:$H$27,MATCH(B38,$B$22:$B$27,0)),$H$27) -> 2.0632852 | D38: =C38/$C$34 -> 0.77053059 | E38: =IF($C$34<=BaseFloor,1,MIN(MAX(D38,RatioFloor),RatioCap)) -> 0.77053059 | F38: ='OReilly 1 Seasons'!$D$30 -> 3.2796017 | G38: =IF(F38>=0,F38*E38,0) -> 2.5270334 | H38: ='OReilly 1 Seasons'!$D$18 -> 53 | I38: ='OReilly 1 Seasons'!$N$18 -> 1.6973289
A40: Hindsight columns are for comparison only; the model never sees them. The projection is a forecast of his production if he keeps playing; the separate exit probabilities (not shown here) handle the chance he does not.

Sheet Kadri 1 Seasons
A1: Nazem Kadri: every season of WAR
A2: Traded Toronto to Colorado on 2019-07-01. The model values him as of the 2019-20 season, so it may use seasons up to 2018-19 only. Grey rows are later seasons, shown for hindsight and never used by the model. Source: Patrick Bacon's WAR export (10_SOURCE/WAR.csv); a season split between two teams is added together into one row.
A4: Season | B4: Team | C4: Age | D4: Games | E4: Ice time (min) | F4: Even-strength offence WAR | G4: Even-strength defence WAR | H4: Power-play WAR | I4: Penalty-kill WAR | J4: Penalties WAR | K4: Shooting WAR | L4: Total WAR | M4: Season-length factor | N4: WAR, season-length adjusted | O4: WAR per 82 games | P4: Used by the model for
A5: 2009-10 | B5: TOR | C5: 19 | D5: 1 | E5: 10.533333 | F5: 0.0016091202 | G5: 3.1086864e-05 | H5: 0.00046600302 | I5: 0 | J5: 0.00038045103 | K5: 0 | L5: 0.0024866611 | M5: 1 | N5: =L5*M5 -> 0.0024866611 | O5: =L5/D5*82 -> 0.20390621
A6: 2010-11 | B6: TOR | C6: 20 | D6: 29 | E6: 451.21667 | F6: 0.095783025 | G6: -0.039622351 | H6: 0.067227524 | I6: -5.813905e-05 | J6: 0.44290629 | K6: -0.3796588 | L6: 0.18657755 | M6: 1 | N6: =L6*M6 -> 0.18657755 | O6: =L6/D6*82 -> 0.52756411
A7: 2011-12 | B7: TOR | C7: 21 | D7: 21 | E7: 295.2 | F7: 0.08919998 | G7: -0.022899007 | H7: 0.060923168 | I7: -1.7484788e-05 | J7: 0.17007021 | K7: 0.52516137 | L7: 0.82243823 | M7: 1 | N7: =L7*M7 -> 0.82243823 | O7: =L7/D7*82 -> 3.2114255
A8: 2012-13 | B8: TOR | C8: 22 | D8: 48 | E8: 752.86667 | F8: 0.54991011 | G8: 0.039510301 | H8: 0.0049004955 | I8: -0.0024065111 | J8: 1.2238909 | K8: 1.4936493 | L8: 3.3094546 | M8: 1 | N8: =L8*M8 -> 3.3094546 | O8: =L8/D8*82 -> 5.6536516
A9: 2013-14 | B9: TOR | C9: 23 | D9: 78 | E9: 1335.8 | F9: 0.79930978 | G9: -0.54930006 | H9: -0.069565212 | I9: 0.008790564 | J9: 0.78344317 | K9: 1.3008366 | L9: 2.2735149 | M9: 1 | N9: =L9*M9 -> 2.2735149 | O9: =L9/D9*82 -> 2.3901054
A10: 2014-15 | B10: TOR | C10: 24 | D10: 73 | E10: 1247.0167 | F10: 1.3368482 | G10: -0.52532286 | H10: 0.064811569 | I10: -0.0014059025 | J10: 1.0576446 | K10: 0.20122702 | L10: 2.1338026 | M10: 1 | N10: =L10*M10 -> 2.1338026 | O10: =L10/D10*82 -> 2.3968741
A11: 2015-16 | B11: TOR | C11: 25 | D11: 76 | E11: 1344.3333 | F11: 1.1243747 | G11: -0.60464292 | H11: 0.32048001 | I11: -0.0041901496 | J11: 1.2367378 | K11: -0.88185153 | L11: 1.190908 | M11: 1 | N11: =L11*M11 -> 1.190908 | O11: =L11/D11*82 -> 1.284927
A12: 2016-17 | B12: TOR | C12: 26 | D12: 82 | E12: 1323.4167 | F12: 1.5579219 | G12: 0.36733749 | H12: 0.74786765 | I12: -0.0011586603 | J12: -0.14699283 | K12: 1.7014621 | L12: 4.2264377 | M12: 1 | N12: =L12*M12 -> 4.2264377 | O12: =L12/D12*82 -> 4.2264377
A13: 2017-18 | B13: TOR | C13: 27 | D13: 80 | E13: 1288.7833 | F13: 0.71875161 | G13: -0.39567521 | H13: 0.75955662 | I13: -9.8361738e-05 | J13: 0.4507557 | K13: 1.8982662 | L13: 3.4315566 | M13: 1 | N13: =L13*M13 -> 3.4315566 | O13: =L13/D13*82 -> 3.5173455 | P13: starting level (if 10+ games); comparison profile at age 27
A14: 2018-19 | B14: TOR | C14: 28 | D14: 73 | E14: 1142.25 | F14: 0.71915408 | G14: -0.40765567 | H14: 0.65807688 | I14: -2.0571006e-05 | J14: 0.44046865 | K14: -0.4172534 | L14: 0.99276997 | M14: 1 | N14: =L14*M14 -> 0.99276997 | O14: =L14/D14*82 -> 1.1151663 | P14: starting level (if 10+ games); comparison profile at age 28
A15: 2019-20 | B15: COL | C15: 29 | D15: 51 | E15: 862.25 | F15: 0.25554467 | G15: -0.12421108 | H15: 0.42738784 | I15: 0.00085047574 | J15: -0.1895257 | K15: 1.4000032 | L15: 1.7700494 | M15: 1.1714286 | N15: =L15*M15 -> 2.0734864 | O15: =L15/D15*82 -> 2.8459618 | P15: hindsight only
A16: 2020-21 | B16: COL | C16: 30 | D16: 56 | E16: 898.3 | F16: 0.29984399 | G16: -0.22647776 | H16: 0.26080529 | I16: 6.4664645e-05 | J16: 0.36955607 | K16: -0.49196986 | L16: 0.21182239 | M16: 1.4642857 | N16: =L16*M16 -> 0.3101685 | O16: =L16/D16*82 -> 0.3101685 | P16: hindsight only
A17: 2021-22 | B17: COL | C17: 31 | D17: 71 | E17: 1302.2833 | F17: 0.78278167 | G17: 0.19686333 | H17: 0.55637418 | I17: -0.010677951 | J17: 0.42142935 | K17: 0.4063816 | L17: 2.3531522 | M17: 1 | N17: =L17*M17 -> 2.3531522 | O17: =L17/D17*82 -> 2.7177251 | P17: hindsight only
A18: 2022-23 | B18: CGY | C18: 32 | D18: 82 | E18: 1364.4667 | F18: 1.0362656 | G18: -0.18970363 | H18: 0.5347025 | I18: -0.0047507552 | J18: 0.79878049 | K18: 0.22256103 | L18: 2.3978552 | M18: 1 | N18: =L18*M18 -> 2.3978552 | O18: =L18/D18*82 -> 2.3978552 | P18: hindsight only
A19: 2023-24 | B19: CGY | C19: 33 | D19: 82 | E19: 1463.3833 | F19: 0.84746899 | G19: -0.089045714 | H19: 0.51201804 | I19: 0.0083895228 | J19: 0.85428645 | K19: 0.65110939 | L19: 2.8316654 | M19: 1 | N19: =L19*M19 -> 2.8316654 | O19: =L19/D19*82 -> 2.8316654 | P19: hindsight only
A20: 2024-25 | B20: CGY | C20: 34 | D20: 82 | E20: 1536.95 | F20: 0.59276138 | G20: -0.21646822 | H20: 0.063650023 | I20: 0.0041768155 | J20: 0.59980962 | K20: 1.8257764 | L20: 2.9284738 | M20: 1 | N20: =L20*M20 -> 2.9284738 | O20: =L20/D20*82 -> 2.9284738 | P20: hindsight only
A21: 2025-26 | B21: CGY/COL | C21: 35 | D21: 77 | E21: 1410.35 | F21: 0.8843029 | G21: -0.53818599 | H21: 0.38420914 | I21: 0.0023376315 | J21: 0.51362515 | K21: -0.70949755 | L21: 0.50066779 | M21: 1 | N21: =L21*M21 -> 0.50066779 | O21: =L21/D21*82 -> 0.53317869 | P21: hindsight only
A23: Starting level: how good is he now?
A24: 60% of last season's WAR plus 40% of the season before, each counted only if he played at least the minimum games. If only one season counts, it supplies the whole starting level. This is a season total (not a per-82 rate); it is the number the aging curve's multipliers are applied to on the Aging path sheet.
B26: Season | C26: Games | D26: Adjusted WAR | E26: Counts? | F26: Weight
A27: Last season | B27: =A14 -> 2018-19 | C27: =D14 -> 73 | D27: =N14 -> 0.99276997 | E27: =C27>=MinGP_base -> TRUE | F27: =W_recent -> 0.6
A28: Season before | B28: =A13 -> 2017-18 | C28: =D13 -> 80 | D28: =N13 -> 3.4315566 | E28: =C28>=MinGP_base -> TRUE | F28: =W_older -> 0.4
A30: Starting level (WAR) | D30: =IF(AND(E27,E28),F27*D27+F28*D28,IF(E27,D27,IF(E28,D28,NA()))) -> 1.9682846

Sheet Kadri 2 Profile
A1: Nazem Kadri: his comparison profile
A2: He is 29 in the valuation season (2019-20). The comparison is made one season earlier, at age 28, so it rests only on completed seasons (2018-19 and before). His profile at age 28 uses his two consecutive seasons at ages 27 and 28, each with at least 20 games. It is then compared with every other forward's profile at age 28.
A4: Profile season | B4: Age | C4: Games | D4: Ice time (min) | E4: EV offence WAR | F4: EV defence WAR | G4: Power-play WAR | H4: Penalty-kill WAR | I4: Shooting WAR | J4: Total WAR | K4: WAR per 82
A5: ='Kadri 1 Seasons'!$A$13 -> 2017-18 | B5: ='Kadri 1 Seasons'!$C$13 -> 27 | C5: ='Kadri 1 Seasons'!$D$13 -> 80 | D5: ='Kadri 1 Seasons'!$E$13 -> 1288.7833 | E5: ='Kadri 1 Seasons'!$F$13 -> 0.71875161 | F5: ='Kadri 1 Seasons'!$G$13 -> -0.39567521 | G5: ='Kadri 1 Seasons'!$H$13 -> 0.75955662 | H5: ='Kadri 1 Seasons'!$I$13 -> -9.8361738e-05 | I5: ='Kadri 1 Seasons'!$K$13 -> 1.8982662 | J5: ='Kadri 1 Seasons'!$L$13 -> 3.4315566 | K5: ='Kadri 1 Seasons'!$O$13 -> 3.5173455
A6: ='Kadri 1 Seasons'!$A$14 -> 2018-19 | B6: ='Kadri 1 Seasons'!$C$14 -> 28 | C6: ='Kadri 1 Seasons'!$D$14 -> 73 | D6: ='Kadri 1 Seasons'!$E$14 -> 1142.25 | E6: ='Kadri 1 Seasons'!$F$14 -> 0.71915408 | F6: ='Kadri 1 Seasons'!$G$14 -> -0.40765567 | G6: ='Kadri 1 Seasons'!$H$14 -> 0.65807688 | H6: ='Kadri 1 Seasons'!$I$14 -> -2.0571006e-05 | I6: ='Kadri 1 Seasons'!$K$14 -> -0.4172534 | J6: ='Kadri 1 Seasons'!$L$14 -> 0.99276997 | K6: ='Kadri 1 Seasons'!$O$14 -> 1.1151663
A8: Style shares: each style WAR summed over the two seasons, divided by the sum of the five style WARs ignoring their signs (Penalties WAR is left out). They describe the MIX of his game, not its size. Standard score = (value - forward average) / forward standard deviation. Weighted score = standard score x square root of the measure weight.
A9: Measure | D9: His value | E9: Forward average | F9: Forward SD | G9: Standard score | H9: Measure weight | I9: Weighted score
A10: Even-strength offence share | D10: =SUM(E5:E6)/(ABS(SUM(E5:E6))+ABS(SUM(F5:F6))+ABS(SUM(G5:G6))+ABS(SUM(H5:H6))+ABS(SUM(I5:I6))) -> 0.27974809 | E10: =Settings!$D$18 -> 0.19232245 | F10: =Settings!$E$18 -> 0.27941252 | G10: =(D10-E10)/F10 -> 0.31289091 | H10: =Settings!$B$18 -> 0.2 | I10: =G10*SQRT(H10) -> 0.13992907
A11: Even-strength defence share | D11: =SUM(F5:F6)/(ABS(SUM(E5:E6))+ABS(SUM(F5:F6))+ABS(SUM(G5:G6))+ABS(SUM(H5:H6))+ABS(SUM(I5:I6))) -> -0.15629 | E11: =Settings!$D$19 -> -0.0066418964 | F11: =Settings!$E$19 -> 0.24003106 | G11: =(D11-E11)/F11 -> -0.62345307 | H11: =Settings!$B$19 -> 0.2 | I11: =G11*SQRT(H11) -> -0.27881669
A12: Power-play share | D12: =SUM(G5:G6)/(ABS(SUM(E5:E6))+ABS(SUM(F5:F6))+ABS(SUM(G5:G6))+ABS(SUM(H5:H6))+ABS(SUM(I5:I6))) -> 0.27580409 | E12: =Settings!$D$20 -> 0.053127196 | F12: =Settings!$E$20 -> 0.11037293 | G12: =(D12-E12)/F12 -> 2.0174954 | H12: =Settings!$B$20 -> 0.2 | I12: =G12*SQRT(H12) -> 0.90225139
A13: Penalty-kill share | D13: =SUM(H5:H6)/(ABS(SUM(E5:E6))+ABS(SUM(F5:F6))+ABS(SUM(G5:G6))+ABS(SUM(H5:H6))+ABS(SUM(I5:I6))) -> -2.3138658e-05 | E13: =Settings!$D$21 -> -0.0029444758 | F13: =Settings!$E$21 -> 0.081318614 | G13: =(D13-E13)/F13 -> 0.035924581 | H13: =Settings!$B$21 -> 0.2 | I13: =G13*SQRT(H13) -> 0.016065961
A14: Shooting share | D14: =SUM(I5:I6)/(ABS(SUM(E5:E6))+ABS(SUM(F5:F6))+ABS(SUM(G5:G6))+ABS(SUM(H5:H6))+ABS(SUM(I5:I6))) -> 0.28813469 | E14: =Settings!$D$22 -> 0.24786123 | F14: =Settings!$E$22 -> 0.37167162 | G14: =(D14-E14)/F14 -> 0.10835763 | H14: =Settings!$B$22 -> 0.2 | I14: =G14*SQRT(H14) -> 0.048459006
A15: Ice time per game (min) | D15: =SUM(D5:D6)/SUM(C5:C6) -> 15.889107 | E15: =Settings!$D$23 -> 15.255212 | F15: =Settings!$E$23 -> 2.8795457 | G15: =(D15-E15)/F15 -> 0.2201372 | H15: =Settings!$B$23 -> 1 | I15: =G15*SQRT(H15) -> 0.2201372
A16: Production level (WAR per 82) | D16: =AVERAGE(K5:K6) -> 2.3162559 | E16: =Settings!$D$24 -> 1.3082679 | F16: =Settings!$E$24 -> 1.4464355 | G16: =(D16-E16)/F16 -> 0.69687721 | H16: =Settings!$B$24 -> 1 | I16: =G16*SQRT(H16) -> 0.69687721
A17: Production trend (WAR per 82, per year) | D17: =(K6-K5)/(B6-B5) -> -2.4021792 | E17: =Settings!$D$25 -> -0.053335801 | F17: =Settings!$E$25 -> 1.482775 | G17: =(D17-E17)/F17 -> -1.5840862 | H17: =Settings!$B$25 -> 1 | I17: =G17*SQRT(H17) -> -1.5840862

Sheet Kadri 3 Comparables
A1: Nazem Kadri: every forward profile at age 28, and how close each one is
A2: Every forward with a qualifying two-season profile at age 28 is eligible; there is no fixed number of comparables. Nazem Kadri's own career is excluded (1 row). Distance = square root of the sum of the eight distance pieces; each piece = measure weight x (his standard score - comparable's standard score)^2. Weight = EXP(-(distance^2) / (2 x yardstick^2)). Rows are sorted by weight. 'After valuation date' marks profiles or yearly changes from seasons that had not been played by 2019-07-01: production draws its comparables from the full 2007-2025 data, so these later seasons do inform the valuation (a documented look-ahead limitation).
A4: Nazem Kadri (the target)
F5: Target standard score: Even-strength offence share | G5: Target standard score: Even-strength defence share | H5: Target standard score: Power-play share | I5: Target standard score: Penalty-kill share | J5: Target standard score: Shooting share | K5: Target standard score: Ice time per game (min) | L5: Target standard score: Production level (WAR per 82) | M5: Target standard score: Production trend (WAR per 82, per year)
F6: ='Kadri 2 Profile'!$G$10 -> 0.31289091 | G6: ='Kadri 2 Profile'!$G$11 -> -0.62345307 | H6: ='Kadri 2 Profile'!$G$12 -> 2.0174954 | I6: ='Kadri 2 Profile'!$G$13 -> 0.035924581 | J6: ='Kadri 2 Profile'!$G$14 -> 0.10835763 | K6: ='Kadri 2 Profile'!$G$15 -> 0.2201372 | L6: ='Kadri 2 Profile'!$G$16 -> 0.69687721 | M6: ='Kadri 2 Profile'!$G$17 -> -1.5840862
A7: Sum of comparable weights | E7: =SUM($AF$11:$AF$409) -> 231.84896 | G7: Share of weight on the 5 closest | K7: =SUM($AF$11:$AF$15)/E7 -> 0.020346234
A8: Effective number of comparables | E8: =SUM($AF$11:$AF$409)^2/SUMPRODUCT($AF$11:$AF$409,$AF$11:$AF$409) -> 363.92563 | G8: Share of weight on profiles after valuation date | K8: =SUMPRODUCT($AF$11:$AF$409,$E$11:$E$409)/E7 -> 0.5871829
A10: Rank | B10: Comparable | C10: Profile seasons | D10: Age | E10: After valuation date (1 = yes) | F10: Value: Even-strength offence share | G10: Value: Even-strength defence share | H10: Value: Power-play share | I10: Value: Penalty-kill share | J10: Value: Shooting share | K10: Value: Ice time per game (min) | L10: Value: Production level (WAR per 82) | M10: Value: Production trend (WAR per 82, per year) | N10: Standard score: Even-strength offence share | O10: Standard score: Even-strength defence share | P10: Standard score: Power-play share | Q10: Standard score: Penalty-kill share | R10: Standard score: Shooting share | S10: Standard score: Ice time per game (min) | T10: Standard score: Production level (WAR per 82) | U10: Standard score: Production trend (WAR per 82, per year) | V10: Distance piece: Even-strength offence share | W10: Distance piece: Even-strength defence share | X10: Distance piece: Power-play share | Y10: Distance piece: Penalty-kill share | Z10: Distance piece: Shooting share | AA10: Distance piece: Ice time per game (min) | AB10: Distance piece: Production level (WAR per 82) | AC10: Distance piece: Production trend (WAR per 82, per year) | AD10: Distance | AE10: Distance in yardsticks | AF10: Weight | AG10: Share of total weight | AH10: Change in WAR per 82, age 28 to 29 | AI10: That change after valuation date (1 = yes) | AJ10: Change in WAR per 82, age 29 to 30 | AK10: That change after valuation date (1 = yes) | AL10: Change in WAR per 82, age 30 to 31 | AM10: That change after valuation date (1 = yes)
A11: 1 | B11: Thomas Vanek | C11: 2010-11 & 2011-12 | D11: 28 | E11: 0 | F11: 0.29867521 | G11: -0.16620725 | H11: 0.18577186 | I11: 0.0025432569 | J11: 0.34680243 | K11: 16.855169 | L11: 2.589981 | M11: -1.7243517 | N11: =(F11-Settings!$D$18)/Settings!$E$18 -> 0.38062987 | O11: =(G11-Settings!$D$19)/Settings!$E$19 -> -0.66476959 | P11: =(H11-Settings!$D$20)/Settings!$E$20 -> 1.2017861 | Q11: =(I11-Settings!$D$21)/Settings!$E$21 -> 0.067484336 | R11: =(J11-Settings!$D$22)/Settings!$E$22 -> 0.26620597 | S11: =(K11-Settings!$D$23)/Settings!$E$23 -> 0.55562832 | T11: =(L11-Settings!$D$24)/Settings!$E$24 -> 0.88611833 | U11: =(M11-Settings!$D$25)/Settings!$E$25 -> -1.1269517 | V11: =Settings!$B$18*(N11-F$6)^2 -> 0.00091771344 | W11: =Settings!$B$19*(O11-G$6)^2 -> 0.00034141087 | X11: =Settings!$B$20*(P11-H$6)^2 -> 0.13307634 | Y11: =Settings!$B$21*(Q11-I$6)^2 -> 0.00019920363 | Z11: =Settings!$B$22*(R11-J$6)^2 -> 0.0049832198 | AA11: =Settings!$B$23*(S11-K$6)^2 -> 0.11255429 | AB11: =Settings!$B$24*(T11-L$6)^2 -> 0.035812202 | AC11: =Settings!$B$25*(U11-M$6)^2 -> 0.20897188 | AD11: =SQRT(SUM(V11:AC11)) -> 0.70488031 | AE11: =AD11/Yardstick -> 0.27900441 | AF11: =EXP(-(AD11^2)/(2*Yardstick^2)) -> 0.96182599 | AG11: =AF11/$E$7 -> 0.0041485025 | AH11: -0.20106698 | AI11: 0 | AJ11: -0.98327251 | AK11: 0 | AL11: -1.480873 | AM11: 0
A12: 2 | B12: Jared Mccann | C12: 2023-24 & 2024-25 | D12: 28 | E12: 1 | F12: 0.28707876 | G12: 0.082740665 | H12: 0.20127276 | I12: -0.0094735839 | J12: 0.41943423 | K12: 16.180556 | L12: 2.8675742 | M12: -1.9734326 | N12: =(F12-Settings!$D$18)/Settings!$E$18 -> 0.33912691 | O12: =(G12-Settings!$D$19)/Settings!$E$19 -> 0.37237914 | P12: =(H12-Settings!$D$20)/Settings!$E$20 -> 1.3422273 | Q12: =(I12-Settings!$D$21)/Settings!$E$21 -> -0.080290451 | R12: =(J12-Settings!$D$22)/Settings!$E$22 -> 0.46162525 | S12: =(K12-Settings!$D$23)/Settings!$E$23 -> 0.32135067 | T12: =(L12-Settings!$D$24)/Settings!$E$24 -> 1.0780337 | U12: =(M12-Settings!$D$25)/Settings!$E$25 -> -1.2949347 | V12: =Settings!$B$18*(N12-F$6)^2 -> 0.00013766551 | W12: =Settings!$B$19*(O12-G$6)^2 -> 0.19833636 | X12: =Settings!$B$20*(P12-H$6)^2 -> 0.091197411 | Y12: =Settings!$B$21*(Q12-I$6)^2 -> 0.0027011867 | Z12: =Settings!$B$22*(R12-J$6)^2 -> 0.024959602 | AA12: =Settings!$B$23*(S12-K$6)^2 -> 0.010244166 | AB12: =Settings!$B$24*(T12-L$6)^2 -> 0.1452803 | AC12: =Settings!$B$25*(U12-M$6)^2 -> 0.083608565 | AD12: =SQRT(SUM(V12:AC12)) -> 0.74596599 | AE12: =AD12/Yardstick -> 0.29526686 | AF12: =EXP(-(AD12^2)/(2*Yardstick^2)) -> 0.95734518 | AG12: =AF12/$E$7 -> 0.0041291761 | AH12: 0.058052064 | AI12: 1
A13: 3 | B13: Vincent Trocheck | C13: 2020-21 & 2021-22 | D13: 28 | E13: 1 | F13: 0.44390165 | G13: -0.03428252 | H13: 0.30050758 | I13: -0.013013515 | J13: 0.20829473 | K13: 17.388021 | L13: 1.7407505 | M13: -2.6224086 | N13: =(F13-Settings!$D$18)/Settings!$E$18 -> 0.90038627 | O13: =(G13-Settings!$D$19)/Settings!$E$19 -> -0.11515436 | P13: =(H13-Settings!$D$20)/Settings!$E$20 -> 2.2413138 | Q13: =(I13-Settings!$D$21)/Settings!$E$21 -> -0.12382208 | R13: =(J13-Settings!$D$22)/Settings!$E$22 -> -0.10645552 | S13: =(K13-Settings!$D$23)/Settings!$E$23 -> 0.74067559 | T13: =(L13-Settings!$D$24)/Settings!$E$24 -> 0.29899888 | U13: =(M13-Settings!$D$25)/Settings!$E$25 -> -1.7326113 | V13: =Settings!$B$18*(N13-F$6)^2 -> 0.069030159 | W13: =Settings!$B$19*(O13-G$6)^2 -> 0.051673516 | X13: =Settings!$B$20*(P13-H$6)^2 -> 0.010018936 | Y13: =Settings!$B$21*(Q13-I$6)^2 -> 0.0051037989 | Z13: =Settings!$B$22*(R13-J$6)^2 -> 0.0092289379 | AA13: =Settings!$B$23*(S13-K$6)^2 -> 0.27096021 | AB13: =Settings!$B$24*(T13-L$6)^2 -> 0.15830716 | AC13: =Settings!$B$25*(U13-M$6)^2 -> 0.022059713 | AD13: =SQRT(SUM(V13:AC13)) -> 0.77225801 | AE13: =AD13/Yardstick -> 0.30567372 | AF13: =EXP(-(AD13^2)/(2*Yardstick^2)) -> 0.95435629 | AG13: =AF13/$E$7 -> 0.0041162845 | AH13: -1.4775353 | AI13: 1 | AJ13: 0.85145491 | AK13: 1 | AL13: 0.4409058 | AM13: 1
A14: 4 | B14: Anders Lee | C14: 2017-18 & 2018-19 | D14: 28 | E14: 0 | F14: 0.20704536 | G14: 0.044304589 | H14: 0.15519848 | I14: -6.2323108e-06 | J14: 0.59344533 | K14: 16.637195 | L14: 2.8411033 | M14: -1.6676821 | N14: =(F14-Settings!$D$18)/Settings!$E$18 -> 0.052692382 | O14: =(G14-Settings!$D$19)/Settings!$E$19 -> 0.21224955 | P14: =(H14-Settings!$D$20)/Settings!$E$20 -> 0.92478548 | Q14: =(I14-Settings!$D$21)/Settings!$E$21 -> 0.036132484 | R14: =(J14-Settings!$D$22)/Settings!$E$22 -> 0.9298103 | S14: =(K14-Settings!$D$23)/Settings!$E$23 -> 0.47993109 | T14: =(L14-Settings!$D$24)/Settings!$E$24 -> 1.0597329 | U14: =(M14-Settings!$D$25)/Settings!$E$25 -> -1.0887331 | V14: =Settings!$B$18*(N14-F$6)^2 -> 0.013540655 | W14: =Settings!$B$19*(O14-G$6)^2 -> 0.13967977 | X14: =Settings!$B$20*(P14-H$6)^2 -> 0.23880301 | Y14: =Settings!$B$21*(Q14-I$6)^2 -> 8.6446942e-09 | Z14: =Settings!$B$22*(R14-J$6)^2 -> 0.1349569 | AA14: =Settings!$B$23*(S14-K$6)^2 -> 0.067492862 | AB14: =Settings!$B$24*(T14-L$6)^2 -> 0.13166426 | AC14: =Settings!$B$25*(U14-M$6)^2 -> 0.24537463 | AD14: =SQRT(SUM(V14:AC14)) -> 0.98565314 | AE14: =AD14/Yardstick -> 0.39013938 | AF14: =EXP(-(AD14^2)/(2*Yardstick^2)) -> 0.92671948 | AG14: =AF14/$E$7 -> 0.0039970828 | AH14: -1.3340366 | AI14: 1 | AJ14: 0.73354142 | AK14: 1 | AL14: 0.45007292 | AM14: 1
A15: 5 | B15: Roope Hintz | C15: 2023-24 & 2024-25 | D15: 28 | E15: 1 | F15: 0.31134866 | G15: -0.026187208 | H15: 0.23742787 | I15: 0.0020048377 | J15: 0.42303142 | K15: 16.386218 | L15: 3.5767103 | M15: -1.7310284 | N15: =(F15-Settings!$D$18)/Settings!$E$18 -> 0.42598738 | O15: =(G15-Settings!$D$19)/Settings!$E$19 -> -0.081428259 | P15: =(H15-Settings!$D$20)/Settings!$E$20 -> 1.6697996 | Q15: =(I15-Settings!$D$21)/Settings!$E$21 -> 0.06086323 | R15: =(J15-Settings!$D$22)/Settings!$E$22 -> 0.47130365 | S15: =(K15-Settings!$D$23)/Settings!$E$23 -> 0.39277249 | T15: =(L15-Settings!$D$24)/Settings!$E$24 -> 1.5682983 | U15: =(M15-Settings!$D$25)/Settings!$E$25 -> -1.1314546 | V15: =Settings!$B$18*(N15-F$6)^2 -> 0.0025581621 | W15: =Settings!$B$19*(O15-G$6)^2 -> 0.058758179 | X15: =Settings!$B$20*(P15-H$6)^2 -> 0.024178481 | Y15: =Settings!$B$21*(Q15-I$6)^2 -> 0.00012438724 | Z15: =Settings!$B$22*(R15-J$6)^2 -> 0.026345962 | AA15: =Settings!$B$23*(S15-K$6)^2 -> 0.029802941 | AB15: =Settings!$B$24*(T15-L$6)^2 -> 0.75937468 | AC15: =Settings!$B$25*(U15-M$6)^2 -> 0.20487532 | AD15: =SQRT(SUM(V15:AC15)) -> 1.051674 | AE15: =AD15/Yardstick -> 0.41627162 | AF15: =EXP(-(AD15^2)/(2*Yardstick^2)) -> 0.91700621 | AG15: =AF15/$E$7 -> 0.003955188 | AH15: -1.5975014 | AI15: 1
A16: 6 | B16: Jordan Eberle | C16: 2017-18 & 2018-19 | D16: 28 | E16: 0 | F16: 0.51620196 | G16: -0.10827535 | H16: 0.044287902 | I16: -8.3316641e-06 | J16: 0.33122645 | K16: 15.907547 | L16: 2.7472273 | M16: -2.1975684 | N16: =(F16-Settings!$D$18)/Settings!$E$18 -> 1.1591446 | O16: =(G16-Settings!$D$19)/Settings!$E$19 -> -0.42341793 | P16: =(H16-Settings!$D$20)/Settings!$E$20 -> -0.080085704 | Q16: =(I16-Settings!$D$21)/Settings!$E$21 -> 0.036106667 | R16: =(J16-Settings!$D$22)/Settings!$E$22 -> 0.22429806 | S16: =(K16-Settings!$D$23)/Settings!$E$23 -> 0.22654114 | T16: =(L16-Settings!$D$24)/Settings!$E$24 -> 0.99483135 | U16: =(M16-Settings!$D$25)/Settings!$E$25 -> -1.4460943 | V16: =Settings!$B$18*(N16-F$6)^2 -> 0.14322905 | W16: =Settings!$B$19*(O16-G$6)^2 -> 0.0080028118 | X16: =Settings!$B$20*(P16-H$6)^2 -> 0.87996933 | Y16: =Settings!$B$21*(Q16-I$6)^2 -> 6.6310738e-09 | Z16: =Settings!$B$22*(R16-J$6)^2 -> 0.0026884368 | AA16: =Settings!$B$23*(S16-K$6)^2 -> 4.1010349e-05 | AB16: =Settings!$B$24*(T16-L$6)^2 -> 0.088776673 | AC16: =Settings!$B$25*(U16-M$6)^2 -> 0.019041744 | AD16: =SQRT(SUM(V16:AC16)) -> 1.0685266 | AE16: =AD16/Yardstick -> 0.42294219 | AF16: =EXP(-(AD16^2)/(2*Yardstick^2)) -> 0.91444308 | AG16: =AF16/$E$7 -> 0.0039441328 | AH16: -0.606549 | AI16: 1 | AJ16: 0.54937196 | AK16: 1 | AL16: -0.48840748 | AM16: 1
A17: 7 | B17: Cam Atkinson | C17: 2016-17 & 2017-18 | D17: 28 | E17: 0 | F17: 0.29552313 | G17: -0.19647136 | H17: 0.091798729 | I17: -0.030108494 | J17: 0.38609828 | K17: 17.855556 | L17: 1.7583014 | M17: -2.3070126 | N17: =(F17-Settings!$D$18)/Settings!$E$18 -> 0.3693488 | O17: =(G17-Settings!$D$19)/Settings!$E$19 -> -0.79085375 | P17: =(H17-Settings!$D$20)/Settings!$E$20 -> 0.35037152 | Q17: =(I17-Settings!$D$21)/Settings!$E$21 -> -0.33404429 | R17: =(J17-Settings!$D$22)/Settings!$E$22 -> 0.3719333 | S17: =(K17-Settings!$D$23)/Settings!$E$23 -> 0.90303964 | T17: =(L17-Settings!$D$24)/Settings!$E$24 -> 0.31113279 | U17: =(M17-Settings!$D$25)/Settings!$E$25 -> -1.5199048 | V17: =Settings!$B$18*(N17-F$6)^2 -> 0.00063749862 | W17: =Settings!$B$19*(O17-G$6)^2 -> 0.0056045973 | X17: =Settings!$B$20*(P17-H$6)^2 -> 0.55586043 | Y17: =Settings!$B$21*(Q17-I$6)^2 -> 0.027375393 | Z17: =Settings!$B$22*(R17-J$6)^2 -> 0.013894427 | AA17: =Settings!$B$23*(S17-K$6)^2 -> 0.46635574 | AB17: =Settings!$B$24*(T17-L$6)^2 -> 0.14879875 | AC17: =Settings!$B$25*(U17-M$6)^2 -> 0.0041192512 | AD17: =SQRT(SUM(V17:AC17)) -> 1.1057333 | AE17: =AD17/Yardstick -> 0.43766928 | AF17: =EXP(-(AD17^2)/(2*Yardstick^2)) -> 0.90866645 | AG17: =AF17/$E$7 -> 0.0039192173 | AH17: -0.099361572 | AI17: 0 | AJ17: 0.25084168 | AK17: 1 | AL17: -0.65070678 | AM17: 1
A18: 8 | B18: Mathieu Perreault | C18: 2014-15 & 2015-16 | D18: 28 | E18: 0 | F18: 0.52746965 | G18: 0.20677046 | H18: 0.10361695 | I18: 0.00063707522 | J18: 0.16150586 | K18: 16.021303 | L18: 2.1357916 | M18: -1.801207 | N18: =(F18-Settings!$D$18)/Settings!$E$18 -> 1.1994709 | O18: =(G18-Settings!$D$19)/Settings!$E$19 -> 0.88910309 | P18: =(H18-Settings!$D$20)/Settings!$E$20 -> 0.45744689 | Q18: =(I18-Settings!$D$21)/Settings!$E$21 -> 0.044043434 | R18: =(J18-Settings!$D$22)/Settings!$E$22 -> -0.23234319 | S18: =(K18-Settings!$D$23)/Settings!$E$23 -> 0.26604601 | T18: =(L18-Settings!$D$24)/Settings!$E$24 -> 0.57211237 | U18: =(M18-Settings!$D$25)/Settings!$E$25 -> -1.1787838 | V18: =Settings!$B$18*(N18-F$6)^2 -> 0.15720483 | W18: =Settings!$B$19*(O18-G$6)^2 -> 0.45756522 | X18: =Settings!$B$20*(P18-H$6)^2 -> 0.48675029 | Y18: =Settings!$B$21*(Q18-I$6)^2 -> 1.3183155e-05 | Z18: =Settings!$B$22*(R18-J$6)^2 -> 0.02321541 | AA18: =Settings!$B$23*(S18-K$6)^2 -> 0.0021076184 | AB18: =Settings!$B$24*(T18-L$6)^2 -> 0.015566264 | AC18: =Settings!$B$25*(U18-M$6)^2 -> 0.16427001 | AD18: =SQRT(SUM(V18:AC18)) -> 1.1431067 | AE18: =AD18/Yardstick -> 0.45246234 | AF18: =EXP(-(AD18^2)/(2*Yardstick^2)) -> 0.90270354 | AG18: =AF18/$E$7 -> 0.0038934984 | AH18: -1.2278804 | AI18: 0 | AJ18: 0.77822996 | AK18: 0 | AL18: 0.43133772 | AM18: 0
A19: 9 | B19: David Clarkson | C19: 2011-12 & 2012-13 | D19: 28 | E19: 0 | F19: 0.16457341 | G19: 0.20698678 | H19: 0.20665499 | I19: 1.9522828e-05 | J19: 0.4217653 | K19: 16.441146 | L19: 2.8718901 | M19: -1.3188855 | N19: =(F19-Settings!$D$18)/Settings!$E$18 -> -0.099312082 | O19: =(G19-Settings!$D$19)/Settings!$E$19 -> 0.89000429 | P19: =(H19-Settings!$D$20)/Settings!$E$20 -> 1.3909913 | Q19: =(I19-Settings!$D$21)/Settings!$E$21 -> 0.036449203 | R19: =(J19-Settings!$D$22)/Settings!$E$22 -> 0.46789708 | S19: =(K19-Settings!$D$23)/Settings!$E$23 -> 0.41184768 | T19: =(L19-Settings!$D$24)/Settings!$E$24 -> 1.0810175 | U19: =(M19-Settings!$D$25)/Settings!$E$25 -> -0.85350083 | V19: =Settings!$B$18*(N19-F$6)^2 -> 0.033982261 | W19: =Settings!$B$19*(O19-G$6)^2 -> 0.45811064 | X19: =Settings!$B$20*(P19-H$6)^2 -> 0.078501485 | Y19: =Settings!$B$21*(Q19-I$6)^2 -> 5.5045525e-08 | Z19: =Settings!$B$22*(R19-J$6)^2 -> 0.025853724 | AA19: =Settings!$B$23*(S19-K$6)^2 -> 0.036752906 | AB19: =Settings!$B$24*(T19-L$6)^2 -> 0.1475638 | AC19: =Settings!$B$25*(U19-M$6)^2 -> 0.53375492 | AD19: =SQRT(SUM(V19:AC19)) -> 1.1465251 | AE19: =AD19/Yardstick -> 0.45381542 | AF19: =EXP(-(AD19^2)/(2*Yardstick^2)) -> 0.90215023 | AG19: =AF19/$E$7 -> 0.0038911119 | AH19: -2.4999717 | AI19: 0 | AJ19: -1.5545726 | AK19: 0 | AL19: 0.64254015 | AM19: 0
A20: 10 | B20: Mike Cammalleri | C20: 2009-10 & 2010-11 | D20: 28 | E20: 0 | F20: 0.11963641 | G20: -0.15225327 | H20: 0.23075549 | I20: 0.017309461 | J20: 0.48004537 | K20: 18.635623 | L20: 2.2118082 | M20: -1.4780002 | N20: =(F20-Settings!$D$18)/Settings!$E$18 -> -0.26013882 | O20: =(G20-Settings!$D$19)/Settings!$E$19 -> -0.60663553 | P20: =(H20-Settings!$D$20)/Settings!$E$20 -> 1.6093465 | Q20: =(I20-Settings!$D$21)/Settings!$E$21 -> 0.24906889 | R20: =(J20-Settings!$D$22)/Settings!$E$22 -> 0.62470237 | S20: =(K20-Settings!$D$23)/Settings!$E$23 -> 1.1739393 | T20: =(L20-Settings!$D$24)/Settings!$E$24 -> 0.62466682 | U20: =(M20-Settings!$D$25)/Settings!$E$25 -> -0.96080952 | V20: =Settings!$B$18*(N20-F$6)^2 -> 0.065672615 | W20: =Settings!$B$19*(O20-G$6)^2 -> 5.6565957e-05 | X20: =Settings!$B$20*(P20-H$6)^2 -> 0.033317109 | Y20: =Settings!$B$21*(Q20-I$6)^2 -> 0.0090860994 | Z20: =Settings!$B$22*(R20-J$6)^2 -> 0.053322378 | AA20: =Settings!$B$23*(S20-K$6)^2 -> 0.90973837 | AB20: =Settings!$B$24*(T20-L$6)^2 -> 0.0052143397 | AC20: =Settings!$B$25*(U20-M$6)^2 -> 0.38847376 | AD20: =SQRT(SUM(V20:AC20)) -> 1.2103228 | AE20: =AD20/Yardstick -> 0.4790677 | AF20: =EXP(-(AD20^2)/(2*Yardstick^2)) -> 0.8915864 | AG20: =AF20/$E$7 -> 0.0038455484 | AH20: -0.061569738 | AI20: 0 | AJ20: 0.12386608 | AK20: 0 | AL20: 0.58595714 | AM20: 0
A21: 11 | B21: Paul Byron | C21: 2016-17 & 2017-18 | D21: 28 | E21: 0 | F21: 0.34960626 | G21: 0.036516268 | H21: 0.037793507 | I21: 0.021503897 | J21: 0.55458006 | K21: 15.314315 | L21: 2.6337573 | M21: -1.6956857 | N21: =(F21-Settings!$D$18)/Settings!$E$18 -> 0.56290896 | O21: =(G21-Settings!$D$19)/Settings!$E$19 -> 0.17980241 | P21: =(H21-Settings!$D$20)/Settings!$E$20 -> -0.13892617 | Q21: =(I21-Settings!$D$21)/Settings!$E$21 -> 0.30064916 | R21: =(J21-Settings!$D$22)/Settings!$E$22 -> 0.82524147 | S21: =(K21-Settings!$D$23)/Settings!$E$23 -> 0.020525225 | T21: =(L21-Settings!$D$24)/Settings!$E$24 -> 0.91638328 | U21: =(M21-Settings!$D$25)/Settings!$E$25 -> -1.107619 | V21: =Settings!$B$18*(N21-F$6)^2 -> 0.012501805 | W21: =Settings!$B$19*(O21-G$6)^2 -> 0.12904387 | X21: =Settings!$B$20*(P21-H$6)^2 -> 0.93003083 | Y21: =Settings!$B$21*(Q21-I$6)^2 -> 0.014015821 | Z21: =Settings!$B$22*(R21-J$6)^2 -> 0.10278449 | AA21: =Settings!$B$23*(S21-K$6)^2 -> 0.039844943 | AB21: =Settings!$B$24*(T21-L$6)^2 -> 0.048182917 | AC21: =Settings!$B$25*(U21-M$6)^2 -> 0.2270209 | AD21: =SQRT(SUM(V21:AC21)) -> 1.2261426 | AE21: =AD21/Yardstick -> 0.48532945 | AF21: =EXP(-(AD21^2)/(2*Yardstick^2)) -> 0.8888984 | AG21: =AF21/$E$7 -> 0.0038339547 | AH21: -0.77669176 | AI21: 0 | AJ21: -0.23783375 | AK21: 1 | AL21: -1.0794116 | AM21: 1
A22: 12 | B22: Andrei Kuzmenko | C22: 2023-24 & 2024-25 | D22: 28 | E22: 1 | F22: 0.17946268 | G22: 0.044868627 | H22: 0.15165581 | I22: -4.5015514e-06 | J22: 0.62400838 | K22: 14.950121 | L22: 2.1714938 | M22: -1.060441 | N22: =(F22-Settings!$D$18)/Settings!$E$18 -> -0.046024309 | O22: =(G22-Settings!$D$19)/Settings!$E$19 -> 0.21459941 | P22: =(H22-Settings!$D$20)/Settings!$E$20 -> 0.89268819 | Q22: =(I22-Settings!$D$21)/Settings!$E$21 -> 0.036153767 | R22: =(J22-Settings!$D$22)/Settings!$E$22 -> 1.0120416 | S22: =(K22-Settings!$D$23)/Settings!$E$23 -> -0.10595103 | T22: =(L22-Settings!$D$24)/Settings!$E$24 -> 0.59679525 | U22: =(M22-Settings!$D$25)/Settings!$E$25 -> -0.67920296 | V22: =Settings!$B$18*(N22-F$6)^2 -> 0.025764027 | W22: =Settings!$B$19*(O22-G$6)^2 -> 0.14046639 | X22: =Settings!$B$20*(P22-H$6)^2 -> 0.25303827 | Y22: =Settings!$B$21*(Q22-I$6)^2 -> 1.0505266e-08 | Z22: =Settings!$B$22*(R22-J$6)^2 -> 0.16332895 | AA22: =Settings!$B$23*(S22-K$6)^2 -> 0.10633354 | AB22: =Settings!$B$24*(T22-L$6)^2 -> 0.010016397 | AC22: =Settings!$B$25*(U22-M$6)^2 -> 0.81881358 | AD22: =SQRT(SUM(V22:AC22)) -> 1.2319745 | AE22: =AD22/Yardstick -> 0.48763784 | AF22: =EXP(-(AD22^2)/(2*Yardstick^2)) -> 0.88790073 | AG22: =AF22/$E$7 -> 0.0038296516 | AH22: -0.1054744 | AI22: 1
A23: 13 | B23: Jon Toews | C23: 2015-16 & 2016-17 | D23: 28 | E23: 0 | F23: 0.30090383 | G23: -0.20536285 | H23: 0.13274557 | I23: 0.027633425 | J23: 0.33335433 | K23: 18.957785 | L23: 2.3282058 | M23: -2.2266301 | N23: =(F23-Settings!$D$18)/Settings!$E$18 -> 0.38860597 | O23: =(G23-Settings!$D$19)/Settings!$E$19 -> -0.82789681 | P23: =(H23-Settings!$D$20)/Settings!$E$20 -> 0.72135775 | Q23: =(I23-Settings!$D$21)/Settings!$E$21 -> 0.37602585 | R23: =(J23-Settings!$D$22)/Settings!$E$22 -> 0.23002322 | S23: =(K23-Settings!$D$23)/Settings!$E$23 -> 1.2858186 | T23: =(L23-Settings!$D$24)/Settings!$E$24 -> 0.70513885 | U23: =(M23-Settings!$D$25)/Settings!$E$25 -> -1.4656939 | V23: =Settings!$B$18*(N23-F$6)^2 -> 0.0011465542 | W23: =Settings!$B$19*(O23-G$6)^2 -> 0.0083594489 | X23: =Settings!$B$20*(P23-H$6)^2 -> 0.33599458 | Y23: =Settings!$B$21*(Q23-I$6)^2 -> 0.023133775 | Z23: =Settings!$B$22*(R23-J$6)^2 -> 0.002960503 | AA23: =Settings!$B$23*(S23-K$6)^2 -> 1.1356769 | AB23: =Settings!$B$24*(T23-L$6)^2 -> 6.825483e-05 | AC23: =Settings!$B$25*(U23-M$6)^2 -> 0.014016724 | AD23: =SQRT(SUM(V23:AC23)) -> 1.2334329 | AE23: =AD23/Yardstick -> 0.4882151 | AF23: =EXP(-(AD23^2)/(2*Yardstick^2)) -> 0.88765068 | AG23: =AF23/$E$7 -> 0.0038285731 | AH23: -1.1200769 | AI23: 0 | AJ23: 0.89403445 | AK23: 0 | AL23: -0.37673917 | AM23: 1
A24: 14 | B24: Wayne Simmonds | C24: 2015-16 & 2016-17 | D24: 28 | E24: 0 | F24: 0.23616734 | G24: -0.086111052 | H24: 0.38052678 | I24: 0.030023728 | J24: 0.2671711 | K24: 17.54182 | L24: 2.2164963 | M24: -0.9068692 | N24: =(F24-Settings!$D$18)/Settings!$E$18 -> 0.15691814 | O24: =(G24-Settings!$D$19)/Settings!$E$19 -> -0.33107863 | P24: =(H24-Settings!$D$20)/Settings!$E$20 -> 2.9663032 | Q24: =(I24-Settings!$D$21)/Settings!$E$21 -> 0.40542014 | R24: =(J24-Settings!$D$22)/Settings!$E$22 -> 0.051954111 | S24: =(K24-Settings!$D$23)/Settings!$E$23 -> 0.79408652 | T24: =(L24-Settings!$D$24)/Settings!$E$24 -> 0.62790798 | U24: =(M24-Settings!$D$25)/Settings!$E$25 -> -0.57563243 | V24: =Settings!$B$18*(N24-F$6)^2 -> 0.0048655013 | W24: =Settings!$B$19*(O24-G$6)^2 -> 0.017096563 | X24: =Settings!$B$20*(P24-H$6)^2 -> 0.18004722 | Y24: =Settings!$B$21*(Q24-I$6)^2 -> 0.027305393 | Z24: =Settings!$B$22*(R24-J$6)^2 -> 0.0006362714 | AA24: =Settings!$B$23*(S24-K$6)^2 -> 0.32941781 | AB24: =Settings!$B$24*(T24-L$6)^2 -> 0.0047567541 | AC24: =Settings!$B$25*(U24-M$6)^2 -> 1.0169789 | AD24: =SQRT(SUM(V24:AC24)) -> 1.2574198 | AE24: =AD24/Yardstick -> 0.49770953 | AF24: =EXP(-(AD24^2)/(2*Yardstick^2)) -> 0.88350583 | AG24: =AF24/$E$7 -> 0.0038106957 | AH24: -0.86760118 | AI24: 0 | AJ24: -1.2529524 | AK24: 0 | AL24: -1.0186463 | AM24: 1
A25: 15 | B25: Dylan Strome | C25: 2024-25 & 2025-26 | D25: 28 | E25: 1 | F25: 0.13771189 | G25: -0.32715514 | H25: 0.19897921 | I25: 0.00012688657 | J25: 0.33602687 | K25: 17.133333 | L25: 1.1823497 | M25: -1.2780331 | N25: =(F25-Settings!$D$18)/Settings!$E$18 -> -0.1954478 | O25: =(G25-Settings!$D$19)/Settings!$E$19 -> -1.335299 | P25: =(H25-Settings!$D$20)/Settings!$E$20 -> 1.3214473 | Q25: =(I25-Settings!$D$21)/Settings!$E$21 -> 0.037769488 | R25: =(J25-Settings!$D$22)/Settings!$E$22 -> 0.23721381 | S25: =(K25-Settings!$D$23)/Settings!$E$23 -> 0.65222848 | T25: =(L25-Settings!$D$24)/Settings!$E$24 -> -0.08705418 | U25: =(M25-Settings!$D$25)/Settings!$E$25 -> -0.82594947 | V25: =Settings!$B$18*(N25-F$6)^2 -> 0.051681649 | W25: =Settings!$B$19*(O25-G$6)^2 -> 0.10134493 | X25: =Settings!$B$20*(P25-H$6)^2 -> 0.096896596 | Y25: =Settings!$B$21*(Q25-I$6)^2 -> 6.8073593e-07 | Z25: =Settings!$B$22*(R25-J$6)^2 -> 0.0033207828 | AA25: =Settings!$B$23*(S25-K$6)^2 -> 0.18670287 | AB25: =Settings!$B$24*(T25-L$6)^2 -> 0.61454842 | AC25: =Settings!$B$25*(U25-M$6)^2 -> 0.57477123 | AD25: =SQRT(SUM(V25:AC25)) -> 1.2764275 | AE25: =AD25/Yardstick -> 0.50523315 | AF25: =EXP(-(AD25^2)/(2*Yardstick^2)) -> 0.88017875 | AG25: =AF25/$E$7 -> 0.0037963455
A26: 16 | B26: Tyler Seguin | C26: 2018-19 & 2019-20 | D26: 28 | E26: 1 | F26: 0.4860875 | G26: -0.078452848 | H26: 0.25039556 | I26: -0.001474467 | J26: 0.18358962 | K26: 19.133113 | L26: 1.6420781 | M26: -2.3710396 | N26: =(F26-Settings!$D$18)/Settings!$E$18 -> 1.0513668 | O26: =(G26-Settings!$D$19)/Settings!$E$19 -> -0.29917358 | P26: =(H26-Settings!$D$20)/Settings!$E$20 -> 1.7872893 | Q26: =(I26-Settings!$D$21)/Settings!$E$21 -> 0.01807715 | R26: =(J26-Settings!$D$22)/Settings!$E$22 -> -0.17292578 | S26: =(K26-Settings!$D$23)/Settings!$E$23 -> 1.3467058 | T26: =(L26-Settings!$D$24)/Settings!$E$24 -> 0.23078126 | U26: =(M26-Settings!$D$25)/Settings!$E$25 -> -1.5630852 | V26: =Settings!$B$18*(N26-F$6)^2 -> 0.10906933 | W26: =Settings!$B$19*(O26-G$6)^2 -> 0.021031438 | X26: =Settings!$B$20*(P26-H$6)^2 -> 0.010598974 | Y26: =Settings!$B$21*(Q26-I$6)^2 -> 6.3706162e-05 | Z26: =Settings!$B$22*(R26-J$6)^2 -> 0.015824072 | AA26: =Settings!$B$23*(S26-K$6)^2 -> 1.2691568 | AB26: =Settings!$B$24*(T26-L$6)^2 -> 0.21724544 | AC26: =Settings!$B$25*(U26-M$6)^2 -> 0.00044103812 | AD26: =SQRT(SUM(V26:AC26)) -> 1.2819637 | AE26: =AD26/Yardstick -> 0.50742446 | AF26: =EXP(-(AD26^2)/(2*Yardstick^2)) -> 0.87920271 | AG26: =AF26/$E$7 -> 0.0037921357 | AL26: 0.30651661 | AM26: 1
A27: 17 | B27: Elias Lindholm | C27: 2021-22 & 2022-23 | D27: 28 | E27: 1 | F27: 0.16417806 | G27: -0.089321354 | H27: 0.17013166 | I27: 0.01494793 | J27: 0.561421 | K27: 18.789506 | L27: 2.474165 | M27: -3.2771197 | N27: =(F27-Settings!$D$18)/Settings!$E$18 -> -0.10072704 | O27: =(G27-Settings!$D$19)/Settings!$E$19 -> -0.34445316 | P27: =(H27-Settings!$D$20)/Settings!$E$20 -> 1.060083 | Q27: =(I27-Settings!$D$21)/Settings!$E$21 -> 0.22002841 | R27: =(J27-Settings!$D$22)/Settings!$E$22 -> 0.84364732 | S27: =(K27-Settings!$D$23)/Settings!$E$23 -> 1.2273792 | T27: =(L27-Settings!$D$24)/Settings!$E$24 -> 0.80604844 | U27: =(M27-Settings!$D$25)/Settings!$E$25 -> -2.1741558 | V27: =Settings!$B$18*(N27-F$6)^2 -> 0.034215962 | W27: =Settings!$B$19*(O27-G$6)^2 -> 0.01556819 | X27: =Settings!$B$20*(P27-H$6)^2 -> 0.18332773 | Y27: =Settings!$B$21*(Q27-I$6)^2 -> 0.0067788442 | Z27: =Settings!$B$22*(R27-J$6)^2 -> 0.10813019 | AA27: =Settings!$B$23*(S27-K$6)^2 -> 1.0145365 | AB27: =Settings!$B$24*(T27-L$6)^2 -> 0.011918357 | AC27: =Settings!$B$25*(U27-M$6)^2 -> 0.34818218 | AD27: =SQRT(SUM(V27:AC27)) -> 1.3125006 | AE27: =AD27/Yardstick -> 0.51951155 | AF27: =EXP(-(AD27^2)/(2*Yardstick^2)) -> 0.87376299 | AG27: =AF27/$E$7 -> 0.0037686733 | AH27: -2.7515088 | AI27: 1 | AJ27: 0.25346961 | AK27: 1 | AL27: 0.21864086 | AM27: 1
A28: 18 | B28: Chris Kreider | C28: 2018-19 & 2019-20 | D28: 28 | E28: 1 | F28: 0.31132571 | G28: -0.037241087 | H28: 0.1348578 | I28: -0.00053264011 | J28: 0.51604276 | K28: 16.77946 | L28: 2.34041 | M28: -0.79367058 | N28: =(F28-Settings!$D$18)/Settings!$E$18 -> 0.42590524 | O28: =(G28-Settings!$D$19)/Settings!$E$19 -> -0.12748013 | P28: =(H28-Settings!$D$20)/Settings!$E$20 -> 0.74049498 | Q28: =(I28-Settings!$D$21)/Settings!$E$21 -> 0.029659085 | R28: =(J28-Settings!$D$22)/Settings!$E$22 -> 0.72155505 | S28: =(K28-Settings!$D$23)/Settings!$E$23 -> 0.52933644 | T28: =(L28-Settings!$D$24)/Settings!$E$24 -> 0.71357628 | U28: =(M28-Settings!$D$25)/Settings!$E$25 -> -0.49929002 | V28: =Settings!$B$18*(N28-F$6)^2 -> 0.0025544477 | W28: =Settings!$B$19*(O28-G$6)^2 -> 0.049197832 | X28: =Settings!$B$20*(P28-H$6)^2 -> 0.32614603 | Y28: =Settings!$B$21*(Q28-I$6)^2 -> 7.8512881e-06 | Z28: =Settings!$B$22*(R28-J$6)^2 -> 0.075202214 | AA28: =Settings!$B$23*(S28-K$6)^2 -> 0.095604167 | AB28: =Settings!$B$24*(T28-L$6)^2 -> 0.00027885918 | AC28: =Settings!$B$25*(U28-M$6)^2 -> 1.1767826 | AD28: =SQRT(SUM(V28:AC28)) -> 1.3136872 | AE28: =AD28/Yardstick -> 0.51998121 | AF28: =EXP(-(AD28^2)/(2*Yardstick^2)) -> 0.87354972 | AG28: =AF28/$E$7 -> 0.0037677535 | AH28: 0.31577574 | AI28: 1 | AJ28: 1.9174943 | AK28: 1 | AL28: -0.22454855 | AM28: 1
A29: 19 | B29: Justin Abdelkader | C29: 2014-15 & 2015-16 | D29: 28 | E29: 0 | F29: 0.025245812 | G29: 0.16264104 | H29: 0.19334083 | I29: 0.049112098 | J29: 0.56966023 | K29: 17.627778 | L29: 2.0084113 | M29: -3.4579287 | N29: =(F29-Settings!$D$18)/Settings!$E$18 -> -0.59795688 | O29: =(G29-Settings!$D$19)/Settings!$E$19 -> 0.70525428 | P29: =(H29-Settings!$D$20)/Settings!$E$20 -> 1.2703625 | Q29: =(I29-Settings!$D$21)/Settings!$E$21 -> 0.6401557 | R29: =(J29-Settings!$D$22)/Settings!$E$22 -> 0.86581535 | S29: =(K29-Settings!$D$23)/Settings!$E$23 -> 0.82393766 | T29: =(L29-Settings!$D$24)/Settings!$E$24 -> 0.48404739 | U29: =(M29-Settings!$D$25)/Settings!$E$25 -> -2.2960953 | V29: =Settings!$B$18*(N29-F$6)^2 -> 0.16592874 | W29: =Settings!$B$19*(O29-G$6)^2 -> 0.35309264 | X29: =Settings!$B$20*(P29-H$6)^2 -> 0.11164154 | Y29: =Settings!$B$21*(Q29-I$6)^2 -> 0.073019049 | Z29: =Settings!$B$22*(R29-J$6)^2 -> 0.11474844 | AA29: =Settings!$B$23*(S29-K$6)^2 -> 0.36457499 | AB29: =Settings!$B$24*(T29-L$6)^2 -> 0.045296532 | AC29: =Settings!$B$25*(U29-M$6)^2 -> 0.50695709 | AD29: =SQRT(SUM(V29:AC29)) -> 1.3172923 | AE29: =AD29/Yardstick -> 0.52140818 | AF29: =EXP(-(AD29^2)/(2*Yardstick^2)) -> 0.8729009 | AG29: =AF29/$E$7 -> 0.003764955 | AH29: -1.8218837 | AI29: 0 | AJ29: -0.099872687 | AK29: 0 | AL29: -0.75138744 | AM29: 0
A30: 20 | B30: Andrew Shaw | C30: 2018-19 & 2019-20 | D30: 28 | E30: 1 | F30: 0.52549143 | G30: -0.098425275 | H30: 0.11186427 | I30: 0.0061137165 | J30: 0.25810532 | K30: 14.990449 | L30: 1.1134347 | M30: -1.446662 | N30: =(F30-Settings!$D$18)/Settings!$E$18 -> 1.192391 | O30: =(G30-Settings!$D$19)/Settings!$E$19 -> -0.38238125 | P30: =(H30-Settings!$D$20)/Settings!$E$20 -> 0.53216914 | Q30: =(I30-Settings!$D$21)/Settings!$E$21 -> 0.11139138 | R30: =(J30-Settings!$D$22)/Settings!$E$22 -> 0.0275622 | S30: =(K30-Settings!$D$23)/Settings!$E$23 -> -0.091945811 | T30: =(L30-Settings!$D$24)/Settings!$E$24 -> -0.13469889 | U30: =(M30-Settings!$D$25)/Settings!$E$25 -> -0.9396747 | V30: =Settings!$B$18*(N30-F$6)^2 -> 0.15470408 | W30: =Settings!$B$19*(O30-G$6)^2 -> 0.011623124 | X30: =Settings!$B$20*(P30-H$6)^2 -> 0.44123884 | Y30: =Settings!$B$21*(Q30-I$6)^2 -> 0.0011390474 | Z30: =Settings!$B$22*(R30-J$6)^2 -> 0.0013055803 | AA30: =Settings!$B$23*(S30-K$6)^2 -> 0.097395809 | AB30: =Settings!$B$24*(T30-L$6)^2 -> 0.6915188 | AC30: =Settings!$B$25*(U30-M$6)^2 -> 0.41526612 | AD30: =SQRT(SUM(V30:AC30)) -> 1.3469192 | AE30: =AD30/Yardstick -> 0.53313505 | AF30: =EXP(-(AD30^2)/(2*Yardstick^2)) -> 0.86752019 | AG30: =AF30/$E$7 -> 0.0037417472
A31: 21 | B31: Zack Smith | C31: 2015-16 & 2016-17 | D31: 28 | E31: 0 | F31: 0.15729144 | G31: 0.10609077 | H31: 0.016276155 | I31: -0.058912423 | J31: 0.66142922 | K31: 15.509677 | L31: 1.8206427 | M31: -2.118671 | N31: =(F31-Settings!$D$18)/Settings!$E$18 -> -0.12537382 | O31: =(G31-Settings!$D$19)/Settings!$E$19 -> 0.46965865 | P31: =(H31-Settings!$D$20)/Settings!$E$20 -> -0.33387752 | Q31: =(I31-Settings!$D$21)/Settings!$E$21 -> -0.68825506 | R31: =(J31-Settings!$D$22)/Settings!$E$22 -> 1.1127241 | S31: =(K31-Settings!$D$23)/Settings!$E$23 -> 0.088370124 | T31: =(L31-Settings!$D$24)/Settings!$E$24 -> 0.35423274 | U31: =(M31-Settings!$D$25)/Settings!$E$25 -> -1.3928851 | V31: =Settings!$B$18*(N31-F$6)^2 -> 0.038415194 | W31: =Settings!$B$19*(O31-G$6)^2 -> 0.23897865 | X31: =Settings!$B$20*(P31-H$6)^2 -> 1.105791 | Y31: =Settings!$B$21*(Q31-I$6)^2 -> 0.10488723 | Z31: =Settings!$B$22*(R31-J$6)^2 -> 0.20175042 | AA31: =Settings!$B$23*(S31-K$6)^2 -> 0.017362564 | AB31: =Settings!$B$24*(T31-L$6)^2 -> 0.11740523 | AC31: =Settings!$B$25*(U31-M$6)^2 -> 0.036557853 | AD31: =SQRT(SUM(V31:AC31)) -> 1.364239 | AE31: =AD31/Yardstick -> 0.53999054 | AF31: =EXP(-(AD31^2)/(2*Yardstick^2)) -> 0.86433497 | AG31: =AF31/$E$7 -> 0.0037280088 | AH31: -1.9197653 | AI31: 0 | AJ31: -0.62779924 | AK31: 0 | AL31: 0.24056771 | AM31: 1
